Workbook

Sheet 使用说明
A2: 《把工厂变绿》游戏数据配置
A3: 管理员编辑黄色输入单元格后，运行游戏包中的“管理员更新游戏配置.command”。玩家页面不显示配置入口。
A5: 步骤 | B5: 操作
A6: 1 | B6: 只修改黄色输入格；灰白字段是游戏结构和公式说明，更新工具不会把它们作为可改配置写入游戏。
A7: 2 | B7: 保存 Excel；双击游戏包中的“管理员更新游戏配置.command”。
A8: 3 | B8: 更新工具会生成 config/game-config.js；再打开 index.html 即可使用新配置。
A9: 4 | B9: 标记为“重置后生效”的初始值，需要在玩家页面重置演示数据。
A10: 5 | B10: CG 文案和图片文件名在“CG配置”维护；图片文件仍单独放在 cg/images 文件夹。
A11: 6 | B11: 不要改动参数ID、项目ID、行动ID、事件ID、公式规则和表头。日常事件文本、条件和权重可直接维护。
A13: 关键口径 | B13: 确认结果
A14: 招聘工程师人工成本 | B14: 38 万/人/年，不是 38 万/人/月。
A15: 招聘工程师月度成本 | B15: 38 ÷ 12 = 3.1667 万/人/月，进入月度经营成本。
A16: 项目支出 | B16: 项目总成本 ÷ 实际完成月数；项目卡直接维护完成月数。
A17: 经营现金流 | B17: 先按原 HTML 年度损益公式计算，再除以 12 得到月度值。
A18: 绿色信贷 | B18: 放款增加现金并形成同额欠款；本金按贷款年限逐月减少，还本付息进入融资费用。

Sheet 经营参数
A2: 经营参数
A3: 黄色为可编辑数值；参数ID供游戏识别，请勿修改。年值在游戏中按原公式计算，再换算为月度。
A5: 分组 | B5: 参数ID | C5: 参数名称 | D5: 数值 | E5: 单位 | F5: 月度/计算口径 | G5: 来源 | H5: 生效时点 | I5: 备注
A6: 初始状态 | B6: startFund | C6: 初始现金 | D6: 520 | E6: 万元 | F6: 不换算 | G6: 当前原型 defaultState | H6: 重置后生效
A7: 初始状态 | B7: startCapacity | C7: 初始产能 | D7: 120 | E7: 万件/年 | F7: 不换算 | G7: 当前原型 defaultState | H7: 重置后生效
A8: 初始状态 | B8: startStress | C8: 初始厂长压力 | D8: 20 | E8: 0-100 | F8: 不换算 | G8: 当前原型 defaultState | H8: 重置后生效
A9: 节奏规则 | B9: freeActionsPerQuarter | C9: 每季度自由行动次数 | D9: 3 | E9: 次/季度 | F9: 不换算 | G9: 用户确认规则 | H9: 立即生效
A10: 压力规则 | B10: idleStress | C10: 摸鱼/空过压力变化 | D10: -10 | E10: 点/月 | F10: 不换算 | G10: 当前原型规则 | H10: 立即生效
A11: 压力规则 | B11: quarterProjectStress | C11: 季度项目压力 | D11: 5 | E11: 点/季度 | F11: 不换算 | G11: 用户确认规则 | H11: 立即生效
A12: 压力规则 | B12: quarterHolidayStress | C12: 季度小长假压力变化 | D12: -15 | E12: 点/季度 | F12: 不换算 | G12: 用户确认规则 | H12: 立即生效
A13: 日常事件 | B13: dailyQuarterNoneRate | C13: 每季度不出现日常事件的权重 | D13: 20 | E13: 相对权重 | F13: 与一条/两条权重共同抽取 | G13: 本轮建议值 | H13: 立即生效 | I13: 20:65:15 对应平均每季度 0.95 条
A14: 日常事件 | B14: dailyQuarterOneRate | C14: 每季度出现1条日常事件的权重 | D14: 65 | E14: 相对权重 | F14: 与零条/两条权重共同抽取 | G14: 本轮建议值 | H14: 立即生效 | I14: 先抽季度条数，再分配到不同月份
A15: 日常事件 | B15: dailyQuarterTwoRate | C15: 每季度出现2条日常事件的权重 | D15: 15 | E15: 相对权重 | F15: 与零条/一条权重共同抽取 | G15: 本轮建议值 | H15: 立即生效 | I15: 同一月份最多一条
A16: 日常事件 | B16: rainSpring | C16: 春季月份雨天/雨后条件命中率 | D16: 0.35 | E16: 概率 | F16: 0-1 | G16: 本轮建议值 | H16: 立即生效
A17: 日常事件 | B17: rainSummer | C17: 夏季月份雨天/雨后条件命中率 | D17: 0.45 | E17: 概率 | F17: 0-1 | G17: 本轮建议值 | H17: 立即生效
A18: 日常事件 | B18: rainAutumn | C18: 秋季月份雨天/雨后条件命中率 | D18: 0.25 | E18: 概率 | F18: 0-1 | G18: 本轮建议值 | H18: 立即生效
A19: 日常事件 | B19: rainWinter | C19: 冬季月份雨天/雨后条件命中率 | D19: 0.15 | E19: 概率 | F19: 0-1 | G19: 本轮建议值 | H19: 立即生效
A20: 经营损益 | B20: matCost | C20: 单位材料成本 | D20: 44 | E20: 元/件 | F20: 随产量计入年度成本 | G20: 用户提供 HTML cashCFG | H20: 立即生效
A21: 经营损益 | B21: laborFix | C21: 固定人工成本 | D21: 900 | E21: 万元/年 | F21: ÷12 | G21: 用户提供 HTML cashCFG | H21: 立即生效
A22: 经营损益 | B22: laborVar | C22: 单位变动人工成本 | D22: 5.5 | E22: 元/件 | F22: 随产量计入年度成本 | G22: 用户提供 HTML cashCFG | H22: 立即生效
A23: 经营损益 | B23: hireSalary | C23: 每名工程师新增人工成本 | D23: 38 | E23: 万元/人/年 | F23: ÷12 | G23: 用户提供 HTML cashCFG | H23: 立即生效
A24: 经营损益 | B24: fixCost | C24: 固定经营费用 | D24: 500 | E24: 万元/年 | F24: ÷12 | G24: 用户提供 HTML cashCFG | H24: 立即生效
A25: 经营损益 | B25: maintBase | C25: 基础维护费用 | D25: 400 | E25: 万元/年 | F25: ÷12 | G25: 用户提供 HTML cashCFG | H25: 立即生效
A26: 经营损益 | B26: taxRate | C26: 所得税率 | D26: 0.25 | E26: 比例 | F26: 按年度税前利润计算 | G26: 用户提供 HTML cashCFG | H26: 立即生效
A27: 经营损益 | B27: payout | C27: 盈利上缴比例 | D27: 0.4 | E27: 比例 | F27: 按年度净利润计算 | G27: 用户提供 HTML cashCFG | H27: 立即生效
... A60: 评分与能耗 | B60: ppaCover0 | C60: 绿电直购初始覆盖率 | D60: 0.7 | E60: 比例 | F60: 年度评分公式直接使用 | G60: 用户提供 HTML scoreCFG | H60: 立即生效
A61: 事件规则 | B61: yearEventChance | C61: 季度末年度事件出现概率 | D61: 0.5 | E61: 0-1 | F61: 不换算 | G61: 管理员配置 | H61: 立即生效 | I61: 每季度末先判定是否出现年度事件；0 表示不出现，1 表示必定出现。

Sheet 项目卡
A2: 项目卡
A3: 施工款逐月支付；“按月线性”项目每完成一个施工月，同步释放相同比例的经营和绿色数值成效。资格、认证与前置解锁仍以完整完成为准。
A5: 分类 | B5: 项目ID | C5: 来源ID | D5: 项目名称 | E5: 说明 | F5: 完整效果 | G5: 总成本_万元 | H5: 基础完成月数 | I5: 基础月均施工支出_万元 | J5: 项目类型 | K5: 收益释放方式 | L5: 每施工月释放比例 | M5: 最多完成次数 | N5: 前置项目ID | O5: 可重复安排 | P5: 是否动态成本 | Q5: 标签 | R5: 启用 | S5: 备注
A6: 日常安排 | B6: idle | C6: idle | D6: 摸鱼 / 空过 | E6: 这个月不启动新项目，维持日常生产经营。 | F6: 项目支出 0；仍按 HTML 经营公式结算当月经营现金流 | G6: 0 | H6: 0 | I6: =IF(H6=0,0,G6/H6) | J6: 可重复月度安排 | K6: 完成时 | L6: =IF(OR(H6=0,K6<>"按月线性"),0,1/H6) | M6: 999 | O6: 是 | P6: 否 | Q6: 日常 | R6: 是 | S6: 摸鱼可每月重复；项目支出为0
A7: 经营与产能 | B7: line2 | C7: line2 | D7: 扩建一条产线 | E7: 扩产同时会推高能耗与排放总量。 | F7: 产能 +40 万件/年；施工当年产量损失约 10% | G7: 850 | H7: 12 | I7: =IF(H7=0,0,G7/H7) | J7: 多月项目 | K7: 按月线性 | L7: =IF(OR(H7=0,K7<>"按月线性"),0,1/H7) | M7: 2 | O7: 否 | P7: 否 | Q7: 扩产 | R7: 是 | S7: 每施工一个月，按进度比例释放数值成效；完整后才解锁资格和前置条件
A8: 经营与产能 | B8: hire | C8: hire | D8: 招聘能源与 EHS 工程师 | E8: 项目做不完往往不是没钱，是没人盯。 | F8: 后续项目完成月数缩短；此后每年增加 38 万人力成本 | G8: 15 | H8: 0 | I8: =IF(H8=0,0,G8/H8) | J8: 管理事项 | K8: 完成时 | L8: =IF(OR(H8=0,K8<>"按月线性"),0,1/H8) | M8: 2 | O8: 否 | P8: 否 | Q8: 团队 | R8: 是 | S8: 完整完成后一次生效
A9: 经营与产能 | B9: auto | C9: auto | D9: 产线自动化改造 | E9: 与“生产工艺和设备先进性”共用一套佐证材料。 | F9: 单位人工成本下降约 18%，良率提升带来单价 +2 元；施工当年停产约 15% | G9: 600 | H9: 12 | I9: =IF(H9=0,0,G9/H9) | J9: 多月项目 | K9: 按月线性 | L9: =IF(OR(H9=0,K9<>"按月线性"),0,1/H9) | M9: 1 | O9: 否 | P9: 否 | Q9: 技改 | R9: 是 | S9: 每施工一个月，按进度比例释放数值成效；完整后才解锁资格和前置条件
A10: 经营与产能 | B10: iso9 | C10: iso9 | D10: ISO 9001 质量管理体系 | E10: 没有质量体系，绿色做得再好也进不了合格供应商名录。 | F10: 大客户供应商准入；每年 6 万维持费 | G10: 55 | H10: 1 | I10: =IF(H10=0,0,G10/H10) | J10: 多月项目 | K10: 完成时 | L10: =IF(OR(H10=0,K10<>"按月线性"),0,1/H10) | M10: 1 | O10: 否 | P10: 否 | Q10: 体系 | R10: 是 | S10: 完整完成后一次生效
A11: 经营与产能 | B11: iso14 | C11: iso14 | D11: ISO 14001 环境管理体系 | E11: 体系认证有年审，也会因环保处罚被暂停。 | F11: 大客户与海外客户准入；每年 6 万维持费 | G11: 65 | H11: 1 | I11: =IF(H11=0,0,G11/H11) | J11: 多月项目 | K11: 完成时 | L11: =IF(OR(H11=0,K11<>"按月线性"),0,1/H11) | M11: 1 | O11: 否 | P11: 否 | Q11: 体系 | R11: 是 | S11: 完整完成后一次生效
A12: 经营与产能 | B12: iso50 | C12: iso50 | D12: ISO 50001 能源管理体系 | E12: 需要能碳平台的数据支撑。 | F12: 海外客户能源管理要求；绿色评分加分 | G12: 70 | H12: 1 | I12: =IF(H12=0,0,G12/H12) | J12: 多月项目 | K12: 完成时 | L12: =IF(OR(H12=0,K12<>"按月线性"),0,1/H12) | M12: 1 | N12: digital | O12: 否 | P12: 否 | Q12: 体系 | R12: 是 | S12: 完整完成后一次生效
A13: 经营与产能 | B13: credit | C13: credit | D13: 申请绿色信贷 | E13: 获得一笔可用于工厂经营与项目建设的长期贷款。 | F13: 现金 +400 万，同时形成 400 万贷款本金；8 年内每年还本付息 62 万 | G13: 0 | H13: 0 | I13: =IF(H13=0,0,G13/H13) | J13: 管理事项 | K13: 完成时 | L13: =IF(OR(H13=0,K13<>"按月线性"),0,1/H13) | M13: 1 | O13: 否 | P13: 否 | Q13: 融资 | R13: 是 | S13: 完整完成后一次生效
A14: 经营与产能 | B14: brand | C14: brand | D14: ESG 品牌与客户沟通 | E14: 绿色能力要被客户看见，才会变成订单。 | F14: 国内与大客户订单需求 +8%；获评后媒体愿意报道 | G14: 120 | H14: 0 | I14: =IF(H14=0,0,G14/H14) | J14: 管理事项 | K14: 完成时 | L14: =IF(OR(H14=0,K14<>"按月线性"),0,1/H14) | M14: 1 | O14: 否 | P14: 否 | Q14: 市场 | R14: 是 | S14: 完整完成后一次生效
A15: 能源低碳化 | B15: digital | C15: ems | D15: 能碳管理平台 | E15: 《数字化能碳管理中心建设指南》要求 12 项业务功能。 | F15: 全厂用能自动计量，能源费用下降 1.2%；解锁碳足迹核算与绿电直购 | G15: 160 | H15: 3 | I15: =IF(H15=0,0,G15/H15) | J15: 多月项目 | K15: 按月线性 | L15: =IF(OR(H15=0,K15<>"按月线性"),0,1/H15) | M15: 1 | O15: 否 | P15: 否 | Q15: 数据 | R15: 是 | S15: 每施工一个月，按进度比例释放数值成效；完整后才解锁资格和前置条件
A16: 能源低碳化 | B16: fake | C16: fake | D16: 做几张漂亮的截图 | E16: 现场复核会逐项点开功能、逐月回溯数据。 | F16: 能碳平台项暂计分；现场复核有扣分风险 | G16: 8 | H16: 0 | I16: =IF(H16=0,0,G16/H16) | J16: 管理事项 | K16: 完成时 | L16: =IF(OR(H16=0,K16<>"按月线性"),0,1/H16) | M16: 1 | O16: 否 | P16: 否 | Q16: 风险 | R16: 是 | S16: 完整完成后一次生效
A17: 能源低碳化 | B17: motor | C17: motor | D17: 高效电机与变压器 | E17: 依据节能降碳技术装备推荐目录。 | F17: 单位产品电耗 −8% | G17: 180 | H17: 6 | I17: =IF(H17=0,0,G17/H17) | J17: 多月项目 | K17: 按月线性 | L17: =IF(OR(H17=0,K17<>"按月线性"),0,1/H17) | M17: 1 | O17: 否 | P17: 否 | Q17: 节能 | R17: 是 | S17: 每施工一个月，按进度比例释放数值成效；完整后才解锁资格和前置条件
A18: 能源低碳化 | B18: energy | C18: air | D18: 空压系统与余热回收 | E18: 工业绿色微电网与重点用能设备能效提升。 | F18: 电耗 −5%，天然气 −12% | G18: 150 | H18: 6 | I18: =IF(H18=0,0,G18/H18) | J18: 多月项目 | K18: 按月线性 | L18: =IF(OR(H18=0,K18<>"按月线性"),0,1/H18) | M18: 1 | O18: 否 | P18: 否 | Q18: 节能 | R18: 是 | S18: 每施工一个月，按进度比例释放数值成效；完整后才解锁资格和前置条件
A19: 能源低碳化 | B19: boiler | C19: boiler | D19: 燃气锅炉电气化 | E19: 1000℃以下中低温热源改电。 | F19: 天然气归零，电耗相应上升；柴油叉车同步电动化；施工当年停产约 15% | G19: 340 | H19: 12 | I19: =IF(H19=0,0,G19/H19) | J19: 多月项目 | K19: 按月线性 | L19: =IF(OR(H19=0,K19<>"按月线性"),0,1/H19) | M19: 1 | O19: 否 | P19: 否 | Q19: 减碳 | R19: 是 | S19: 每施工一个月，按进度比例释放数值成效；完整后才解锁资格和前置条件
A20: 能源低碳化 | B20: solar | C20: pv | D20: 屋顶分布式光伏 | E20: 自用光伏可将自用部分电力因子按 0 处理。 | F20: 每期年发电 200 万 kWh；初始自用率 80% | G20: 430 | H20: 6 | I20: =IF(H20=0,0,G20/H20) | J20: 多月项目 | K20: 按月线性 | L20: =IF(OR(H20=0,K20<>"按月线性"),0,1/H20) | M20: 3 | O20: 否 | P20: 否 | Q20: 绿电 | R20: 是 | S20: 每施工一个月，按进度比例释放数值成效；完整后才解锁资格和前置条件
A21: 能源低碳化 | B21: storage | C21: ess | D21: 用户侧储能 | E21: 储能不产生绿电，只提高绿电利用效率。 | F21: 光伏自用率 80%→95%，峰谷套利 +45 万/年；本身几乎不减碳 | G21: 240 | H21: 6 | I21: =IF(H21=0,0,G21/H21) | J21: 多月项目 | K21: 按月线性 | L21: =IF(OR(H21=0,K21<>"按月线性"),0,1/H21) | M21: 1 | N21: solar | O21: 否 | P21: 否 | Q21: 配套 | R21: 是 | S21: 每施工一个月，按进度比例释放数值成效；完整后才解锁资格和前置条件
A22: 能源低碳化 | B22: greenPower | C22: ppa | D22: 绿电直购（市场化交易） | E22: 需市场化交易合同与逐月结算凭证。 | F22: 外购电排放按 0 计；初始覆盖 70%，另按用电量支付溢价 | G22: 180 | H22: 6 | I22: =IF(H22=0,0,G22/H22) | J22: 多月项目 | K22: 按月线性 | L22: =IF(OR(H22=0,K22<>"按月线性"),0,1/H22) | M22: 1 | N22: digital | O22: 否 | P22: 否 | Q22: 绿电 | R22: 是 | S22: 每施工一个月，按进度比例释放数值成效；完整后才解锁资格和前置条件
A23: 能源低碳化 | B23: ppa2 | C23: ppa2 | D23: 绿电直购扩容至 100% | E23: 全额覆盖通常需要跨省交易或更高价格。 | F23: 外购绿电覆盖率 70%→100% | G23: 120 | H23: 6 | I23: =IF(H23=0,0,G23/H23) | J23: 多月项目 | K23: 按月线性 | L23: =IF(OR(H23=0,K23<>"按月线性"),0,1/H23) | M23: 1 | N23: greenPower | O23: 否 | P23: 否 | Q23: 绿电 | R23: 是 | S23: 每施工一个月，按进度比例释放数值成效；完整后才解锁资格和前置条件
A24: 能源低碳化 | B24: gec | C24: gec | D24: 绿证采购（GEC） | E24: 绿证对应电量的排放因子不能按 0 计。 | F24: 计入可再生能源利用率；不降低碳排放强度 | G24: 0 | H24: 0 | I24: =IF(H24=0,0,G24/H24) | J24: 管理事项 | K24: 完成时 | L24: =IF(OR(H24=0,K24<>"按月线性"),0,1/H24) | M24: 1 | O24: 否 | P24: 否 | Q24: 绿证 | R24: 是 | S24: 完整完成后一次生效
A25: 资源高效化 | B25: water | C25: water | D25: 节水工艺与水平衡测试 | E25: 指标：单位产值取水量。 | F25: 取水强度达到行业先进水平 | G25: 90 | H25: 6 | I25: =IF(H25=0,0,G25/H25) | J25: 多月项目 | K25: 按月线性 | L25: =IF(OR(H25=0,K25<>"按月线性"),0,1/H25) | M25: 1 | O25: 否 | P25: 否 | Q25: 节水 | R25: 是 | S25: 每施工一个月，按进度比例释放数值成效；完整后才解锁资格和前置条件
A26: 资源高效化 | B26: reuse | C26: reuse | D26: 中水回用系统 | E26: 指标：工业用水重复利用率。 | F26: 工业用水重复利用率大幅提升；一克碳都不减 | G26: 130 | H26: 6 | I26: =IF(H26=0,0,G26/H26) | J26: 多月项目 | K26: 按月线性 | L26: =IF(OR(H26=0,K26<>"按月线性"),0,1/H26) | M26: 1 | O26: 否 | P26: 否 | Q26: 循环 | R26: 是 | S26: 每施工一个月，按进度比例释放数值成效；完整后才解锁资格和前置条件
A27: 资源高效化 | B27: waste | C27: solid | D27: 固废资源化协同 | E27: 需申报登记表、转移联单、综合利用证明。 | F27: 一般工业固废综合利用率提升 | G27: 60 | H27: 6 | I27: =IF(H27=0,0,G27/H27) | J27: 多月项目 | K27: 按月线性 | L27: =IF(OR(H27=0,K27<>"按月线性"),0,1/H27) | M27: 1 | O27: 否 | P27: 否 | Q27: 固废 | R27: 是 | S27: 每施工一个月，按进度比例释放数值成效；完整后才解锁资格和前置条件
A28: 资源高效化 | B28: material | C28: mat | D28: 原材料减量与再生料 | E28: 非重点行业可用应用案例赋分。 | F28: 单位材料成本 −4%，原材料消耗强度下降 | G28: 70 | H28: 6 | I28: =IF(H28=0,0,G28/H28) | J28: 多月项目 | K28: 按月线性 | L28: =IF(OR(H28=0,K28<>"按月线性"),0,1/H28) | M28: 1 | O28: 否 | P28: 否 | Q28: 材料 | R28: 是 | S28: 每施工一个月，按进度比例释放数值成效；完整后才解锁资格和前置条件
A29: 生产洁净化 | B29: process | C29: proc | D29: 工艺装备对标升级 | E29: 需与近三年发布的推荐目录逐项对标。 | F29: 电耗 −6%；设备故障风险显著下降；施工当年停产约 15% | G29: 260 | H29: 12 | I29: =IF(H29=0,0,G29/H29) | J29: 多月项目 | K29: 按月线性 | L29: =IF(OR(H29=0,K29<>"按月线性"),0,1/H29) | M29: 1 | O29: 否 | P29: 否 | Q29: 工艺 | R29: 是 | S29: 每施工一个月，按进度比例释放数值成效；完整后才解锁资格和前置条件
A30: 生产洁净化 | B30: pollution | C30: poll | D30: 污染物深度治理 | E30: 需在线监测记录或每季度检测报告。 | F30: 排放浓度优于许可限值，环保抽查免罚；消除制冷剂逸散 | G30: 140 | H30: 6 | I30: =IF(H30=0,0,G30/H30) | J30: 多月项目 | K30: 按月线性 | L30: =IF(OR(H30=0,K30<>"按月线性"),0,1/H30) | M30: 1 | O30: 否 | P30: 否 | Q30: 治理 | R30: 是 | S30: 每施工一个月，按进度比例释放数值成效；完整后才解锁资格和前置条件
A31: 产品绿色化 | B31: design | C31: design | D31: 产品绿色设计 | E31: 依据 GB/T 24256 产品生态设计通则。 | F31: 出具生态设计报告，产品更轻、更好拆 | G31: 50 | H31: 6 | I31: =IF(H31=0,0,G31/H31) | J31: 多月项目 | K31: 完成时 | L31: =IF(OR(H31=0,K31<>"按月线性"),0,1/H31) | M31: 1 | O31: 否 | P31: 否 | Q31: 设计 | R31: 是 | S31: 完整完成后一次生效
A32: 产品绿色化 | B32: cfp | C32: cfp | D32: 产品碳足迹核算 | E32: 依据 GB/T 24067；需先有能碳平台的数据底座。 | F32: 出具碳足迹报告——海外订单的准入门票 | G32: 60 | H32: 6 | I32: =IF(H32=0,0,G32/H32) | J32: 多月项目 | K32: 完成时 | L32: =IF(OR(H32=0,K32<>"按月线性"),0,1/H32) | M32: 1 | N32: digital | O32: 否 | P32: 否 | Q32: 准入 | R32: 是 | S32: 完整完成后一次生效
A33: 产品绿色化 | B33: effp | C33: effp | D33: 产品能效升级至 2 级 | E33: 以现行强制性能效国家标准为准。 | F33: 节能产品占比得分；单价 +3 元 | G33: 120 | H33: 6 | I33: =IF(H33=0,0,G33/H33) | J33: 多月项目 | K33: 按月线性 | L33: =IF(OR(H33=0,K33<>"按月线性"),0,1/H33) | M33: 1 | O33: 否 | P33: 否 | Q33: 能效 | R33: 是 | S33: 每施工一个月，按进度比例释放数值成效；完整后才解锁资格和前置条件
A34: 产品绿色化 | B34: supplier | C34: chain | D34: 供应链碳协同 | E34: II 型零碳工厂覆盖范围一、二、三。 | F34: 具备申报 II 型零碳工厂资格；大客户订单 +10% | G34: 150 | H34: 6 | I34: =IF(H34=0,0,G34/H34) | J34: 多月项目 | K34: 按月线性 | L34: =IF(OR(H34=0,K34<>"按月线性"),0,1/H34) | M34: 1 | N34: cfp | O34: 否 | P34: 否 | Q34: 协同 | R34: 是 | S34: 每施工一个月，按进度比例释放数值成效；完整后才解锁资格和前置条件
A35: 用地集约化 | B35: land | C35: land | D35: 立体仓储与厂区提容 | E35: 指标：土地产出率。 | F35: 容积率与单位用地面积产值提升 | G35: 200 | H35: 6 | I35: =IF(H35=0,0,G35/H35) | J35: 多月项目 | K35: 按月线性 | L35: =IF(OR(H35=0,K35<>"按月线性"),0,1/H35) | M35: 1 | O35: 否 | P35: 否 | Q35: 用地 | R35: 是 | S35: 每施工一个月，按进度比例释放数值成效；完整后才解锁资格和前置条件
A36: 申报与认证 | B36: apply | C36: apply | D36: 启动绿色工厂申报 | E36: 区级初审 → 市级评审与现场复核 → 省级遴选 → 国家级复核。 | F36: 进入材料评审与现场复核；获评后逐年复评晋级 | G36: 0 | H36: 0 | I36: =IF(H36=0,0,G36/H36) | J36: 管理事项 | K36: 完成时 | L36: =IF(OR(H36=0,K36<>"按月线性"),0,1/H36) | M36: 1 | O36: 否 | P36: 否 | Q36: 认证 | R36: 是 | S36: 完整完成后一次生效
A37: 申报与认证 | B37: bribe | C37: bribe | D37: 找关系疏通评审 | E37: 真实世界里这一条不叫捷径，叫风险敞口。 | F37: 评审时暂加 12 分；此后每年可能被追责 | G37: 90 | H37: 0 | I37: =IF(H37=0,0,G37/H37) | J37: 管理事项 | K37: 完成时 | L37: =IF(OR(H37=0,K37<>"按月线性"),0,1/H37) | M37: 1 | O37: 否 | P37: 否 | Q37: 风险 | R37: 是 | S37: 完整完成后一次生效
A38: 申报与认证 | B38: cert | C38: cert | D38: 冲刺零碳工厂认证 | E38: 剩余排放用碳信用抵消，申请第三方评价。 | F38: 按剩余排放量支付抵消与评价成本 | G38: 0 | H38: 0 | I38: =IF(H38=0,0,G38/H38) | J38: 管理事项 | K38: 完成时 | L38: =IF(OR(H38=0,K38<>"按月线性"),0,1/H38) | M38: 1 | N38: apply | O38: 否 | P38: 是 | Q38: 零碳 | R38: 是 | S38: 完整完成后一次生效

Sheet 日常行动
A2: 日常行动
A3: 行动ID、名称、场景和备注为锁定结构；黄色格可修改日志文案、压力、好感、随机权重与启用状态。
A5: 行动ID | B5: 行动名称 | C5: 日志文案 | D5: 压力变化 | E5: 好感变化 | F5: 出现权重 | G5: 使用场景 | H5: 启用 | I5: 备注
A6: idle_month | B6: 摸鱼 / 空过 | C6: 这个月不启动新项目，维持日常生产经营。 | D6: -10 | E6: 0 | F6: 100 | G6: 每月项目安排 | H6: 是 | I6: 不消耗自由行动；经营现金流正常结算
A7: walk | B7: 午间散步 | C7: 沿厂区走了一圈，头脑清醒了一些。 | D7: -10 | E7: 0 | F7: 100 | G7: 自由行动 | H7: 是
A8: meeting_speak | B8: 小会：临时发言 | C8: 临时被点名发言，会议结束后仍有些紧绷。 | D8: 8 | E8: 0 | F8: 50 | G8: 自由行动随机分支 | H8: 是 | I8: 与 meeting_listen 的权重相对计算
A9: meeting_listen | B9: 小会：旁听 | C9: 以旁听为主，理清了接下来的工作。 | D9: -5 | E9: 0 | F9: 50 | G9: 自由行动随机分支 | H9: 是 | I9: 与 meeting_speak 的权重相对计算
A10: chat_leader | B10: 与领导闲聊 | C10: 分管领导问了问这个季度的经营重点，也提醒要把项目节奏讲清楚。 | D10: 5 | E10: 5 | F10: 100 | G10: 闲聊对象规则 | H10: 是 | I10: 领导始终使用此行
A11: chat_subordinate_unfamiliar | B11: 与不熟的下属闲聊 | C11: 聊了聊近期工作与现场情况。 | D11: 5 | E11: 5 | F11: 100 | G11: 闲聊对象规则 | H11: 是 | I11: 关系值低于60
A12: chat_subordinate_familiar | B12: 与熟络的下属闲聊 | C12: 聊了聊近期工作与现场情况。 | D12: -8 | E12: 5 | F12: 100 | G12: 闲聊对象规则 | H12: 是 | I12: 关系值达到60
A13: quarter_project | B13: 季度项目压力 | C13: 这个季度的项目推进带来额外压力。 | D13: 5 | E13: 0 | F13: 100 | G13: 季度结算 | H13: 是 | I13: 每季度一次
A14: quarter_holiday | B14: 季度小长假 | C14: 小长假让身心得到休息。 | D14: -15 | E14: 0 | F14: 100 | G14: 季度结算 | H14: 是 | I14: 每季度一次

Sheet 日常事件
A2: 日常事件
A3: 先按经营参数抽取本季度 0/1/2 条，再分配到不同月份；每月最多一条。黄色字段可改，权重只在当月符合条件的候选事件之间比较。
A5: 事件ID | B5: 分类 | C5: 标题 | D5: 正文 | E5: 季节条件 | F5: 天气条件 | G5: 月份条件 | H5: 最早年份 | I5: 仅第一年 | J5: 前置项目ID | K5: 任一前置项目ID | L5: 出现权重 | M5: 是否一次性 | N5: 启用 | O5: 备注
A6: A01 | B6: 厂区的四季 | C6: 门口的花 | D6: 门卫室旁边的花开了。你路过时才发现，原来那片不起眼的角落已经热闹了好几天。 | E6: 春季 | I6: 否 | L6: 130 | M6: 是 | N6: 是
A7: A02 | B7: 厂区的四季 | C7: 一场春雨 | D7: 雨后的厂区有一股湿润的泥土味。几只麻雀在屋檐下跳来跳去，似乎比工人们还着急开工。 | E7: 春季 | F7: 雨天或雨后 | I7: 否 | L7: 145 | M7: 是 | N7: 是
A8: A03 | B8: 厂区的四季 | C8: 夏天的柏油路 | D8: 午后的阳光把厂区道路晒得发亮。远远望过去，路面上的空气似乎也在轻轻晃动。 | E8: 夏季 | I8: 否 | L8: 130 | M8: 是 | N8: 是
A9: A04 | B9: 厂区的四季 | C9: 雨停了 | D9: 一场大雨刚刚过去，厂区的水洼里倒映着仓库的屋顶。有人经过时特意绕开了它，也有人一脚踩了进去。 | F9: 雨天或雨后 | I9: 否 | L9: 140 | M9: 是 | N9: 是
A10: A05 | B10: 厂区的四季 | C10: 第一片黄叶 | D10: 办公楼外的树开始落叶了。你发现这件事，是因为有一片叶子正好落在了车前挡风玻璃上。 | E10: 秋季 | I10: 否 | L10: 130 | M10: 是 | N10: 是
A11: A06 | B11: 厂区的四季 | C11: 窗外的风 | D11: 今天的风很大，办公室窗外的树枝一直晃个不停。下午开会时，有人忍不住朝窗外看了好几次。 | E11: 秋季 | I11: 否 | L11: 130 | M11: 是 | N11: 是
A12: A07 | B12: 厂区的四季 | C12: 冬天的早晨 | D12: 早班员工陆续走进厂区，有人把双手揣进口袋，有人端着还冒热气的早餐。新的一天就在这样的寒冷里开始了。 | E12: 冬季 | I12: 否 | L12: 130 | M12: 是 | N12: 是
A13: A08 | B13: 厂区的四季 | C13: 天黑得早了 | D13: 下班时，天已经暗了。办公楼和车间的灯一盏盏亮着，工厂看起来和平时有些不一样。 | E13: 秋冬 | I13: 否 | L13: 130 | M13: 是 | N13: 是
A14: B01 | B14: 生产线旁 | C14: 熟悉的声音 | D14: 你经过车间时，刘师傅正听着一台设备运转。他说机器开久了，哪怕不看仪表，也能听出和平时有什么不同。 | I14: 否 | L14: 100 | M14: 是 | N14: 是
A15: B02 | B15: 生产线旁 | C15: 工具抽屉 | D15: 陈工打开工具柜，里面的工具排得整整齐齐。他说倒不是有什么讲究，只是找不到工具的时候真的很耽误事。 | I15: 否 | L15: 100 | M15: 是 | N15: 是
A16: B03 | B16: 生产线旁 | C16: 交接班 | D16: 交接班记录本又写满了一页。有人的字工整得像打印出来的，有人的字则需要同班组的人才能认出来。 | I16: 否 | L16: 100 | M16: 是 | N16: 是
A17: B04 | B17: 生产线旁 | C17: 最后一件产品 | D17: 今天一批订单完成了最后一道工序。负责检验的员工在记录上画了一个小小的勾，然后准备迎接下一批产品。 | I17: 否 | L17: 100 | M17: 是 | N17: 是
A18: B05 | B18: 生产线旁 | C18: 新人的笔记 | D18: 新来的员工随身带着一个巴掌大的本子，上面记满了设备编号和操作要点。他说记性不太好，多写几遍总不会错。 | I18: 否 | L18: 100 | M18: 是 | N18: 是
A19: B06 | B19: 生产线旁 | C19: 保养日 | D19: 今天有几台设备按计划停机保养。车间里少了熟悉的机器声，反倒让人一时有些不习惯。 | I19: 否 | L19: 100 | M19: 是 | N19: 是
A20: B07 | B20: 生产线旁 | C20: 换班时间 | D20: 换班前的几分钟，大家陆续在指定区域整理工具、核对记录。上一班的人准备回家，下一班的人刚刚开始一天的工作。 | I20: 否 | L20: 100 | M20: 是 | N20: 是
A21: B08 | B21: 生产线旁 | C21: 师傅的习惯 | D21: 刘师傅每次完成检查，都会把用过的笔放回同一个位置。有人问他为什么，他想了想，说大概是怕自己忘记了。 | I21: 否 | L21: 100 | M21: 是 | N21: 是
A22: C01 | B22: 熟悉的人 | C22: 陈工的图纸 | D22: 陈工又在一张图纸边上写满了注释。你问他是不是还有问题没解决，他说：“问题倒不大，就是还能再改改。” | I22: 否 | L22: 100 | M22: 是 | N22: 是
A23: C02 | B23: 熟悉的人 | C23: 林经理的数字 | D23: 林经理拿着计算器核对报表，同一个数字算了三遍。你问她是不是不相信电脑，她说：“我是不相信自己第一遍没按错。” | I23: 否 | L23: 100 | M23: 是 | N23: 是
A24: C03 | B24: 熟悉的人 | C24: 周经理的电话 | D24: 周经理刚结束一通客户电话，转头又接起了下一通。他把手机放下时长舒了一口气：“今天已经解释同一个问题四遍了。” | I24: 否 | L24: 100 | M24: 是 | N24: 是
A25: C04 | B25: 熟悉的人 | C25: 刘师傅的照片 | D25: 刘师傅在休息时翻出一张旧合照，照片里的人都穿着多年前的工作服。他指着其中一个年轻人说：“这个是我，那时候头发还挺多。” | I25: 否 | L25: 100 | M25: 是 | N25: 是
... A30: D01 | B30: 食堂与公共空间 | C30: 今天吃什么 | D30: 食堂今天的菜谱刚贴出来，就有人站在前面研究了半天。 | I30: 否 | L30: 100 | M30: 是 | N30: 是
A31: D02 | B31: 食堂与公共空间 | C31: 最后一块西瓜 | D31: 食堂午餐后准备了一些西瓜。最后一块在餐盘里放了好一会儿，谁路过都说让给别人，最后还是被食堂阿姨收走了。 | E31: 夏季 | I31: 否 | L31: 130 | M31: 是 | N31: 是
A32: D03 | B32: 食堂与公共空间 | C32: 公告栏 | D32: 公告栏上又多了一张通知，贴得稍微有点歪。第二天再经过时，你发现它已经被人重新贴正了。 | I32: 否 | L32: 100 | M32: 是 | N32: 是
A33: D04 | B33: 食堂与公共空间 | C33: 失物招领 | D33: 门卫室的失物招领处多了一把折叠伞，旁边还有一只没人认领的手套。门卫说，这些东西总会有人记起来的。 | I33: 否 | L33: 100 | M33: 是 | N33: 是
A34: D05 | B34: 食堂与公共空间 | C34: 食堂阿姨 | D34: 今天食堂阿姨问你最近是不是很忙。你还没来得及回答，她已经多给你盛了一勺菜：“看你这几天吃得少。” | I34: 否 | L34: 100 | M34: 是 | N34: 是
A35: D06 | B35: 食堂与公共空间 | C35: 午后的休息区 | D35: 午休时间，休息区难得安静下来。有人靠着椅背闭目养神，有人戴着耳机听歌，偶尔传来翻书的声音。 | I35: 否 | L35: 100 | M35: 是 | N35: 是
A36: D07 | B36: 食堂与公共空间 | C36: 雨伞架 | D36: 办公楼门口的伞架突然变得拥挤。下午雨停后，大家又陆续把自己的伞领走，剩下了几把颜色几乎一样的黑伞。 | F36: 雨天或雨后 | I36: 否 | L36: 140 | M36: 是 | N36: 是
A37: D08 | B37: 食堂与公共空间 | C37: 一张生日卡 | D37: 休息区的桌上放着一张写满签名的生日卡。没有盛大的庆祝仪式，只是有人记得今天是谁的生日。 | I37: 否 | L37: 100 | M37: 是 | N37: 是
A38: E01 | B38: 围墙外的世界 | C38: 早餐摊 | D38: 厂门口的早餐摊今天来得特别早。你经过时，摊主已经能叫出好几位员工的名字，甚至知道他们平时吃什么。 | I38: 否 | L38: 100 | M38: 是 | N38: 是
A39: E02 | B39: 围墙外的世界 | C39: 等车的人 | D39: 下班时，公交站旁站着几个熟悉的身影。大家都低头看着手机，直到公交车从路口转过来，才一起抬起头。 | I39: 否 | L39: 100 | M39: 是 | N39: 是
A40: E03 | B40: 围墙外的世界 | C40: 司机的路线 | D40: 送货司机说，来厂里的这条路他已经跑了好几年。有时候导航还在提示转弯，他就已经知道前面哪个路口容易堵车。 | I40: 否 | L40: 100 | M40: 是 | N40: 是
A41: E04 | B41: 围墙外的世界 | C41: 隔壁工厂 | D41: 隔壁厂区传来了施工的声音，听说他们最近正在改造一栋老厂房。门卫和司机们已经讨论了好几天，猜测那边究竟要做什么。 | I41: 否 | L41: 100 | M41: 是 | N41: 是
A42: E05 | B42: 围墙外的世界 | C42: 水果摊 | D42: 路边的水果摊换上了当季的水果。你经过时听见摊主招呼熟客：“今天这个比上周的甜。” | E42: 夏秋 | I42: 否 | L42: 130 | M42: 是 | N42: 是
A43: E06 | B43: 围墙外的世界 | C43: 街角的小店 | D43: 厂区附近那家经营多年的小店换了新招牌。老板还是原来的老板，只是门口的招牌看起来亮堂了不少。 | I43: 否 | L43: 100 | M43: 是 | N43: 是
A44: E07 | B44: 围墙外的世界 | C44: 放学时间 | D44: 下午经过工厂外的路口时，正好遇上附近学校放学。几名学生背着书包从人行道走过，叽叽喳喳地讨论着明天的考试。 | I44: 否 | L44: 100 | M44: 是 | N44: 是
A45: E08 | B45: 围墙外的世界 | C45: 回家的路 | D45: 今天你比平时早了一点离开工厂。路边的店铺还没有打烊，天也没有完全黑下来，你突然发现这条路其实挺热闹的。 | I45: 否 | L45: 100 | M45: 是 | N45: 是
A46: F01 | B46: 厂长自己的日常 | C46: 桌上的文件 | D46: 你整理办公桌时发现一份找了两天的文件。它就夹在最常用的文件夹里，偏偏之前翻了好几遍都没看见。 | I46: 否 | L46: 100 | M46: 是 | N46: 是
A47: F02 | B47: 厂长自己的日常 | C47: 第一声厂长 | D47: 今天有人在走廊里喊了一声“厂长”，你过了半秒才反应过来是在叫自己。 | I47: 是 | L47: 180 | M47: 是 | N47: 是
A48: F03 | B48: 厂长自己的日常 | C48: 会议结束之后 | D48: 今天最后一场会议结束得比预想中早。你坐在办公室里，一时竟然有点不知道该先做什么。 | I48: 否 | L48: 100 | M48: 是 | N48: 是
A49: F04 | B49: 厂长自己的日常 | C49: 便签纸 | D49: 显示器旁边的便签越贴越多，颜色也越来越杂。你决定认真整理一次，结果发现其中三张写的是同一件事。 | I49: 否 | L49: 100 | M49: 是 | N49: 是
A50: F05 | B50: 厂长自己的日常 | C50: 窗外的灯 | D50: 傍晚，你抬头看见车间的灯已经亮了。你还没有完成手头的工作，但至少今天最棘手的几件事已经有了眉目。 | I50: 否 | L50: 100 | M50: 是 | N50: 是
A51: F06 | B51: 厂长自己的日常 | C51: 写错的日期 | D51: 你在文件上写下日期，才发现月份已经变了。把数字划掉重写时，你突然觉得上个月过得实在太快。 | I51: 否 | L51: 100 | M51: 是 | N51: 是
A52: F07 | B52: 厂长自己的日常 | C52: 没响的电话 | D52: 今天下午，办公室电话难得安静了很久。你甚至看了一眼手机，确认不是自己错过了什么消息。 | I52: 否 | L52: 100 | M52: 是 | N52: 是
A53: F08 | B53: 厂长自己的日常 | C53: 锁门之前 | D53: 离开办公室前，你又回头看了一眼桌上的文件。明天还有不少事情要做，不过今天可以先到这里了。 | I53: 否 | L53: 100 | M53: 是 | N53: 是
A54: G01 | B54: 小意外与幽默 | C54: 神秘的订书机 | D54: 办公室那台总也找不到的订书机终于出现了，就放在打印机旁边。至于它之前去了哪里，至今没有人承认。 | I54: 否 | L54: 100 | M54: 是 | N54: 是
... A64: H03 | B64: 绿色改变的痕迹 | C64: 纸箱的第二次使用 | D64: 仓库员工把一批完好、符合复用要求的纸箱留了下来，准备用于内部物料周转。箱子上原来的标签已经被仔细去除。 | I64: 否 | L64: 100 | M64: 是 | N64: 是
A65: H04 | B65: 绿色改变的痕迹 | C65: 数字的变化 | D65: 陈工指着新整理的能源使用记录，告诉你有几个车间的数据与上个月不太一样。他已经记下来，准备再看看究竟是什么原因。 | I65: 否 | J65: digital | L65: 180 | M65: 是 | N65: 是 | O65: 完成能源计量或监测项目后
A66: H05 | B66: 绿色改变的痕迹 | C66: 换下来的灯 | D66: 仓库一角放着刚换下来的旧灯具，等待按规定分类处置。走进改造后的车间，有员工说：“现在看东西确实清楚些了。” | I66: 否 | J66: lighting | L66: 180 | M66: 是 | N66: 是 | O66: 当前项目库尚无 lighting；新增同ID项目后自动可抽取
A67: H06 | B67: 绿色改变的痕迹 | C67: 屋顶上的新东西 | D67: 厂区的屋顶和以前不一样了。今天有人在楼下抬头看了好一会儿，才想起自己已经有几天没注意过那些新装的光伏板。 | I67: 否 | J67: solar | L67: 180 | M67: 是 | N67: 是
A68: H07 | B68: 绿色改变的痕迹 | C68: 分类的习惯 | D68: 新设置的废弃物分类区前，有位员工停下来确认标识。想清楚该放在哪里之后，他才把手里的东西投进去。 | I68: 否 | J68: waste | L68: 180 | M68: 是 | N68: 是
A69: H08 | B69: 绿色改变的痕迹 | C69: 一张旧记录 | D69: 整理改造资料时，陈工翻出了一张几年前的设备运行记录。他把新旧两张表并排放在一起，准备对照一下变化。 | I69: 否 | K69: motor|energy|boiler|auto|process | L69: 180 | M69: 是 | N69: 是 | O69: 完成任一节能改造后
A70: I01 | B70: 时间与人来人往 | C70: 新年日历 | D70: 办公室的日历又换了一本。你把旧日历拿下来时，发现上面还记着一些已经完成、也有一些来不及完成的事。 | G70: 1 | I70: 否 | L70: 170 | M70: 是 | N70: 是
A71: I02 | B71: 时间与人来人往 | C71: 春节前的行李 | D71: 临近春节，有些同事开始讨论回家的车票。休息区里多了不少关于天气、行李和家乡年夜饭的话题。 | G71: 1-2 | I71: 否 | L71: 150 | M71: 是 | N71: 是
A72: I03 | B72: 时间与人来人往 | C72: 新来的同事 | D72: 今天有几位新员工来办理入职手续。他们站在厂区示意图前认真研究，看起来和当初第一次走进这里的你有些相似。 | I72: 否 | L72: 100 | M72: 是 | N72: 是
A73: I04 | B73: 时间与人来人往 | C73: 一封告别邮件 | D73: 一位同事即将离开工厂，发来一封简短的告别邮件。邮件最后写着：“以后有机会路过，我会回来看看。” | I73: 否 | L73: 100 | M73: 是 | N73: 是
A74: I05 | B74: 时间与人来人往 | C74: 老照片 | D74: 宣传栏上翻出了一张几年前的厂区照片。你盯着看了很久，才发现照片里那栋已经习以为常的建筑，当时还没有重新粉刷。 | H74: 3 | I74: 否 | L74: 150 | M74: 是 | N74: 是
A75: I06 | B75: 时间与人来人往 | C75: 又一个夏天 | D75: 蝉鸣又一次从办公楼外传来。你忽然想起刚来工厂时，也曾在同样闷热的下午坐在这间办公室里看报表。 | E75: 夏季 | H75: 3 | I75: 否 | L75: 160 | M75: 是 | N75: 是
A76: I07 | B76: 时间与人来人往 | C76: 换了好几支笔 | D76: 整理抽屉时，你翻出一支早就写不出字的旧笔。想了半天才记起来，它好像是自己刚上任那年用的。 | H76: 5 | I76: 否 | L76: 170 | M76: 是 | N76: 是
A77: I08 | B77: 时间与人来人往 | C77: 年末的灯 | D77: 又到了一年的最后一个工作月。傍晚离开办公楼时，你看见车间、仓库和门卫室的灯依旧亮着，和平常一样。 | G77: 12 | I77: 否 | L77: 170 | M77: 是 | N77: 是

Sheet 季度事件
A2: 季度事件
A3: 本表是季度特殊事件数据库。年度事件在对应年份和季节的季度末参与抽取；每季度最多出现一条，是否出现由经营参数 yearEventChance 控制。可直接修改标题、正文、权重、选项和启用状态。
A5: 事件ID | B5: 标题 | C5: 触发条件 | D5: 出现权重 | E5: 是否一次性 | F5: 日志正文 | G5: 资金变化_万元 | H5: 压力变化 | I5: 好感对象ID | J5: 好感变化 | K5: 关联项目ID | L5: 启用 | M5: 备注 | N5: 事件类型 | O5: 年份 | P5: 季节 | Q5: 说话人ID | R5: 说话人 | S5: 选项JSON | T5: 未触发文本 | U5: 原版条件
A6: GF15_Y01_SPRING_001 | B6: 一号线电机烧了 | C6: 第1年·春季 | D6: 100 | E6: 是 | F6: 厂长，一号线的电机又烧了。修一修还能转，可它吃电吃得凶。换新的要二十五万，而且得停线三天。后天那批货要交，您看着办。 | G6: 0 | H6: 0 | J6: 0 | L6: 是 | M6: 源自 green-factory-15-years 厂长路线；原版条件事件已保留条件文本，当前按年份与季节抽取。 | N6: year_story | O6: 1 | P6: 春 | Q6: zhou | R6: 老周 | S6: [{"id": "1", "text": "先修，货要紧", "hint": "花 8 万 · 当天复产 · 老周松口气", "result": "电机连夜拆下来，第二天中午一号线重新转起来，声音还是那么响。货按时出了。当月电费单来的时候，老赵看了一眼，没说话。", "effects": {"money": -8, "aff": {"zhou": 2, "chen": -1}}}, {"id": "2", "text": "换新的，停三天也认了", "hint": "花 25 万 · 这批货要延期", "result": "客户在电话里发了火，最后同意延三天，但下一批订单转给了对门的宏远厂。新电机装好那周，陈工每天下班前去抄一次表——比老的省了将近一成。省下的电费，要两年才补得回丢掉的那批单。", "effects": {"money": -25, "orders": -7, "smoke": -4, "rival": 5, "aff": {"chen": 3, "zhou": -1, "zhao": -2}, "flag": "motor", "fac": {"power": 1}}}, {"id": "3", "text": "先修着，年底再换", "hint": "花 8 万 · 把选择推给未来的自己", "result": "你在本子上写下\"年底换电机\"。这个本子后来又记了很多类似的事。年底盘账的时候，这一条被划掉了——那年年底有更急的事。", "effects": {"money": -8, "smoke": 1, "aff": {"zhou": 1, "chen": -2}}}] | T6: 电机一直没修利索，那两个月三天两头停机，交期一延再延。老周自己带人凑合修了三次，没跟你提第四次。
A7: GF15_Y01_AUTUMN_002 | B7: 一笔压价的急单 | C7: 第1年·秋季 | D7: 100 | E7: 是 | F7: 有笔急单，量不小，但价压到了成本线上。宏远厂也在抢。接，这季度现金流就活了；不接，年底的账难看，明年集团给的额度也跟着缩。 | G7: 0 | H7: 0 | J7: 0 | L7: 是 | M7: 源自 green-factory-15-years 厂长路线；原版条件事件已保留条件文本，当前按年份与季节抽取。 | N7: year_story | O7: 1 | P7: 秋 | Q7: zhao | R7: 老赵 | S7: [{"id": "1", "text": "接，先把现金流转起来", "hint": "钱多了 · 人要连轴转两个月", "result": "那两个月，三车间的灯一直亮到十一点。单子交了，钱进来了。老周说：\"钱是挣到了，人也快熬干了。\"年后走了两个人。", "effects": {"money": 32, "orders": 6, "morale": -8, "smoke": 3, "group": 6, "rival": -4, "aff": {"zhao": 2, "zhou": -2}, "flag": "ord_take"}}, {"id": "2", "text": "不接，这种价没意义", "hint": "老周赞成 · 集团那边不好交代", "result": "宏远厂接了，他们厂长在行业群里发了张加班的照片，配文\"感谢客户信任\"。年底集团经营分析会上，你的产能利用率排在后面，马副总问了句\"你们的产线是不是有点闲\"。", "effects": {"money": -4, "orders": -6, "morale": 4, "group": -8, "rival": 8, "aff": {"zhao": -2, "zhou": 3}, "flag": "ord_refuse"}}, {"id": "3", "text": "谈：价格照给，交期放宽", "hint": "要么谈成，要么谈崩", "result": "林薇跑了三趟。客户同意分两批交货，条件是账期拉到九十天。少赚，还压资金，但车间没有加班到半夜。她回来说：\"客户其实没那么难说话，是我们自己不敢开口。\"", "effects": {"money": 14, "orders": 4, "morale": 1, "group": 1, "aff": {"lin": 3, "zhao": -1}, "flag": "ord_nego"}}] | T7: 你没顾上表态，林薇按老规矩报了价，客户转头给了宏远。这种单子丢了不心疼，但老赵那本账上，这个季度是空的。
A8: GF15_Y02_SPRING_003 | B8: 老赵问：这厂靠什么吃饭 | C8: 第2年·春季 | D8: 100 | E8: 是 | F8: 厂长，来了快一年了，有句话我得问。这个厂到底靠什么吃饭？报价再低总有人比我们低，技术又比不过南方那几家。想清楚这个，我才知道每一笔钱该往哪儿批。 | G8: 0 | H8: 0 | J8: 0 | L8: 是 | M8: 源自 green-factory-15-years 厂长路线；原版条件事件已保留条件文本，当前按年份与季节抽取。 | N8: year_story | O8: 2 | P8: 春 | Q8: zhao | R8: 老赵 | S8: [{"id": "1", "text": "靠成本：谁也别想比我们便宜", "hint": "接得多、赚得薄 · 绿色投入回本最慢", "result": "方向定了。往后几年，凡是能压的都压：采购比价、工时定额、能耗指标。老赵如鱼得水，报表越来越干净。但林薇提醒过一句：\"走这条路，客户永远只跟你谈价格，别的什么都不会跟你谈。\"", "effects": {"money": 20, "orders": 6, "morale": -2, "aff": {"zhao": 4, "lin": -2}, "flag": "m_cost"}}, {"id": "2", "text": "靠技术：做别人做不了的活", "hint": "前几年会很紧 · 但技改的效果会翻倍", "result": "方向定了。陈工听说以后，那天在办公室待到十点。往后你的钱大部分会花在设备和工艺上，账面会难看好几年。老赵说了句实话：\"这条路要是走成了，我们就不用天天跟人吵价钱；走不成，我们就死在半路上。\"", "effects": {"money": -15, "tech": 14, "aff": {"chen": 5, "zhao": -2}, "flag": "m_tech"}}, {"id": "3", "text": "靠客户：把牌子和口碑做起来", "hint": "要持续投合规和品牌 · 名声就是订单", "result": "方向定了。往后你会在认证、审核、宣传上花掉很多钱，这些钱短期看都是\"没有产出\"的。林薇很高兴，老赵不太高兴：\"这条路上，你花的每一分钱都要等别人认了才算数。\"", "effects": {"money": -10, "fame": 8, "aff": {"lin": 5, "zhao": -3}, "flag": "m_brand"}}] | T8: 这个问题被搁置了。往后几年每次做预算，老赵都得凭感觉批钱——没有方向的厂，钱花得最散。
A9: GF15_Y02_SUMMER_004 | B9: 客户发来一份八页问卷 | C9: 第2年·夏季 | D9: 100 | E9: 是 | F9: 客户发来一份问卷，八页纸，问我们用不用绿电、一年排多少碳、有没有环保处罚记录。以前从来没人问过这些。宏远厂找了家咨询公司，两周就交上去了。 | G9: 0 | H9: 0 | J9: 0 | L9: 是 | M9: 源自 green-factory-15-years 厂长路线；原版条件事件已保留条件文本，当前按年份与季节抽取。 | N9: year_story | O9: 2 | P9: 夏 | Q9: lin | R9: 林薇 | S9: [{"id": "1", "text": "随便填填交上去", "hint": "省事 · 把问题留到以后", "result": "问卷交了上去，大部分栏填的是\"符合相关要求\"。这一轮你留在了名单里。林薇把那份问卷打印出来压在玻璃板下——她说总有一天会再被问到。", "effects": {"orders": 2, "fame": -2, "flag": "q_fake", "aff": {"lin": -2}}}, {"id": "2", "text": "照实填，不知道的就写不知道", "hint": "这一轮大概率出局", "result": "那份问卷一半是空的。三周后短名单公布，你们不在上面，宏远在。但采购回了封私人邮件，只有一句：\"感谢坦诚，两年后我们会复评，届时希望看到变化。\"林薇把邮件转给你，标题是\"两年\"。", "effects": {"orders": -8, "fame": 4, "rival": 6, "aff": {"lin": 3}, "flag": "q_honest"}}, {"id": "3", "text": "也找家咨询公司，做一份漂亮的", "hint": "花 6 万 · 好看，但是空的", "result": "代填的问卷很专业，图表都是彩色的。林薇翻了两页就合上：\"这上面写我们有能源管理体系。厂长，我们连电表都只有总表一块。\"这份材料留了底，两年后客户来现场时，它还在档案柜里。", "effects": {"money": -6, "orders": 4, "fame": 2, "flag": "q_fake", "aff": {"lin": -3, "chen": -2}}}] | T9: 问卷过了期限没交。三周后短名单公布，你们不在上面。林薇打电话去问，对方说：没收到回复，就当贵司没兴趣。
A10: GF15_Y02_AUTUMN_005 | B10: 陈工想装几块电表 | C10: 第2年·秋季 | D10: 100 | E10: 是 | F10: 我想在几个大车间装分表，六万块。现在全厂就一块总表，每个月电费单来了，我只能告诉您花了多少钱，说不清是哪儿花的。 | G10: 0 | H10: 0 | J10: 0 | L10: 是 | M10: 源自 green-factory-15-years 厂长路线；原版条件事件已保留条件文本，当前按年份与季节抽取。 | N10: year_story | O10: 2 | P10: 秋 | Q10: chen | R10: 陈工 | S10: [{"id": "1", "text": "装，我也想知道电花在哪", "hint": "花 6 万 · 车间会觉得是在盯着他们", "result": "表装上的第二个月，陈工拿着手画的图来找你：空压机房夜里没生产，用电却和白天差不多——管路漏了三年没人发现。补完当月省了一万一。但夜班的人私下嘀咕，说厂里开始查他们的岗了。", "effects": {"money": -6, "smoke": -3, "morale": -3, "aff": {"chen": 4, "zhou": -1}, "flag": "meter", "fac": {"meter": 1}}}, {"id": "2", "text": "六万块买几块表，没必要", "hint": "省下钱 · 陈工失望", "result": "陈工\"哦\"了一声就走了。后来很久他都没再提过建议。你偶尔在下班路上看见他一个人蹲在空压机房门口，拿着本子写写画画。", "effects": {"aff": {"chen": -4}}}, {"id": "3", "text": "先装一块，看看有没有用", "hint": "花 2 万 · 算是给个机会", "result": "一块表装在三车间。数据不多，但足以让陈工发现夜班待机能耗高得离谱。他写了一页纸交上来，最后一行是：\"如果有第二块表，我能找出更多。\"", "effects": {"money": -2, "smoke": -1, "aff": {"chen": 2}, "flag": "meter1"}}] | T10: 六万块的事你一直没批。陈工后来再没提过，那几个月他一个人蹲在空压机房门口，拿本子写写画画。
A11: GF15_Y03_SPRING_006 | B11: 老周私下说：废水的事 | C11: 第3年·春季 | D11: 100 | E11: 是 | F11: 厂长，废水处理那套设备老了，处理量跟不上，近半年有几次是直接从雨水管走的。没人看见。要治得停线改造，四十万。这话我只跟您一个人说。 | G11: 0 | H11: 0 | J11: 0 | L11: 是 | M11: 源自 green-factory-15-years 厂长路线；原版条件事件已保留条件文本，当前按年份与季节抽取。 | N11: year_story | O11: 3 | P11: 春 | Q11: zhou | R11: 老周 | S11: [{"id": "1", "text": "停线改造，该花的钱花", "hint": "花 40 万 · 停产两周 · 现在最痛", "result": "两周停产，两笔订单延期，客户扣了违约金。改造完那天，老周站在新的调节池边上说：\"这钱花得肉疼，可我这心里踏实了。\"这件事厂里没几个人知道，但知道的人都记住了你是怎么做的。", "effects": {"money": -40, "orders": -8, "morale": 4, "fame": 2, "aff": {"zhou": 4, "zhao": -2}, "flag": "water_fixed", "fac": {"water": 1}}}, {"id": "2", "text": "先控制排放量，等年底再说", "hint": "能拖一阵 · 隐患留着", "result": "你让老周把生产排期错开，尽量不超负荷。多数时候没问题，个别赶工的日子还是走了雨水管。这件事没有再被提起，直到很久以后。", "effects": {"money": -4, "risk": 1, "aff": {"zhou": 1}, "flag": "water_risk"}}, {"id": "3", "text": "这四十万，先给车间换空调和更衣室", "hint": "省 40 万 · 工人会很高兴", "result": "夏天车间第一次有了空调，更衣室也翻新了，班组的人见你都笑。老周站在新装的柜子前看了很久，说了句\"厂长办了件实事\"，然后补了一句：\"那个口的事，我就不再提了。\"这两句话隔了三秒，中间的那三秒你听懂了。", "effects": {"morale": 10, "risk": 2, "aff": {"zhou": -3}, "flag": "water_risk"}}] | T11: 你没接这个话头。老周站了几秒，说了句我知道了，转身走了。那半年赶工的日子，废水还是从雨水管走的——只是从此再没人跟你提起。
A12: GF15_Y03_SUMMER_007 | B12: 执法人员上门检查 | C12: 第3年·夏季 | D12: 100 | E12: 是 | F12: 周三早上九点，两辆车停在厂门口。执法人员要看废气排口的在线监测记录、危废转移联单和排污许可证执行报告。老周在你身后小声说：那个柜子的钥匙在谁手里来着？ | G12: 0 | H12: 0 | J12: 0 | L12: 是 | M12: 源自 green-factory-15-years 厂长路线；原版条件事件已保留条件文本，当前按年份与季节抽取。 | N12: year_story | O12: 3 | P12: 夏 | Q12: narr | R12: 旁白 | S12: [{"id": "1", "text": "如实说：有些记录我们没做", "hint": "认罚，但态度在", "result": "你没有绕。执法人员反倒缓了语气，开了限期整改通知书，罚十五万。临走那位说：\"很多厂到这一步还在找钥匙。你们至少知道自己缺什么。\"整改期三个月，陈工第一次有了正当理由把台账制度建起来。", "effects": {"money": -15, "fame": -3, "morale": -2, "flag": "fined", "aff": {"chen": 2}}}, {"id": "2", "text": "先带他们去看新装的设备", "hint": "拖一拖 · 不解决问题", "result": "那位很客气地看完设备，然后说：\"现在可以看台账了吗。\"该查的还是查了，罚了二十万，通报上了市局网站。宏远厂的人当天就在群里转发了那条链接。", "effects": {"money": -20, "fame": -6, "morale": -3, "rival": 4, "flag": "fined"}}, {"id": "3", "text": "先打个电话，看能不能缓一缓", "hint": "这一次大概管用 · 以后就说不准了", "result": "电话打通了，那边说\"按程序走，我尽量说说\"。当天只开了一份责令改正，罚了五万。事情压下去了，但你欠了一份人情，而且从此厂里管台账的人都知道：查得严不严，是可以打电话的。往后三年，那个柜子的钥匙又不知道在谁手里了。", "effects": {"money": -5, "risk": 2, "group": -2, "morale": -2, "flag": "pulled_string"}}] | T12: 你在外地开会，副手接待的。台账翻到一半就翻不下去了，开了整改通知书，罚二十万。回来后没有人愿意详细跟你讲那天的经过。
A13: GF15_Y03_AUTUMN_008 | B13: 有人来谈屋顶光伏 | C13: 第3年·秋季 | D13: 100 | E13: 是 | F13: 一家做光伏的公司找上门，说你的厂房屋顶两万平米空着可惜。老周插了一句：厂长，那屋顶去年就在漏水，先修还是先铺板子？ | G13: 0 | H13: 0 | J13: 0 | L13: 是 | M13: 源自 green-factory-15-years 厂长路线；原版条件事件已保留条件文本，当前按年份与季节抽取。 | N13: year_story | O13: 3 | P13: 秋 | Q13: narr | R13: 旁白 | S13: [{"id": "1", "text": "连屋顶一起修，自己投", "hint": "花 62 万 · 账上会很紧", "result": "防水做完才铺的板。并网那天陈工在屋顶待了一下午，傍晚发来一张照片：一整片深蓝色的板子，后面是烧红的云。那年年底账上剩不到五十万，老赵开会时把计算器按得很响。", "effects": {"money": -62, "smoke": -12, "morale": 3, "aff": {"chen": 4, "zhao": -2}, "flag": "pv_own", "fac": {"roof": 1}}}, {"id": "2", "text": "租给他们，一分钱不用出", "hint": "免费 · 但这些电不算你的", "result": "合同签得很顺，二十年后资产归你，用电也便宜了些。屋顶漏水的事对方说不归他们管，你另外花八万补了几处。后来客户来问\"你们自己发多少绿电\"，你才知道租出去的屋顶答不上这道题。", "effects": {"money": -8, "smoke": -5, "flag": "pv_lease"}}, {"id": "3", "text": "只修屋顶，板子的事以后再说", "hint": "花 12 万 · 车间不漏水了", "result": "雨季来的时候，三车间第一次没有接水盆，工人挺高兴。那家光伏公司的人走时留了张名片，说想通了随时联系。名片在抽屉里越压越下面。", "effects": {"money": -12, "morale": 5, "aff": {"zhou": 2}}}] | T13: 你说再研究研究。那家公司的人留了张名片就走了，名片在抽屉里越压越下面。屋顶继续空着，也继续漏水。
A14: GF15_Y04_SPRING_009 | B14: 大客户要收窄供应商名单 | C14: 第4年·春季 | D14: 100 | E14: 是 | F14: 那家大客户要收窄供应商名单，留下来得有绿色工厂或者环境管理体系的资质。四十万，还要整整一年整改，车间要天天配合。宏远厂上个月已经启动了。 | G14: 0 | H14: 0 | J14: 0 | L14: 是 | M14: 源自 green-factory-15-years 厂长路线；原版条件事件已保留条件文本，当前按年份与季节抽取。 | N14: year_story | O14: 4 | P14: 春 | Q14: lin | R14: 林薇 | S14: [{"id": "1", "text": "做，认认真真做一遍", "hint": "花 40 万 · 车间会被折腾一年", "result": "那一年厂里到处是人在整理文件、贴标识、补台账。老周嘴上抱怨\"天天搞形式\"，班组怨声载道。但审核那天，是他领着审核员一间间车间走的，每个问题都答得上来。证书下来那天他把复印件贴在了车间门口。", "effects": {"money": -40, "orders": 14, "fame": 8, "morale": -5, "smoke": -4, "group": 5, "rival": -6, "flag": "cert", "aff": {"lin": 3, "zhou": 2}}}, {"id": "2", "text": "花钱买个证，别折腾车间", "hint": "花 18 万 · 两个月拿证 · 车间照常生产", "result": "证书两个月就到了，挂在会议室墙上，很好看。名单保住了，车间一天没停，省下的二十二万和一年工期都实打实。林薇看着那张纸说：\"客户明年要来现场审核。到时候他们不看墙，看车间。\"", "effects": {"money": -18, "orders": 11, "fame": 3, "morale": 2, "risk": 1, "flag": "cert_fake", "aff": {"lin": -2, "chen": -2}}}, {"id": "3", "text": "不做，这单丢了就丢了", "hint": "四成的量", "result": "名单公布那天你们不在上面，宏远在。林薇在办公室坐了很久，然后开始一个个打电话找新客户。她没抱怨，但那个季度她瘦了七斤。", "effects": {"orders": -18, "morale": -4, "group": -6, "rival": 10, "aff": {"lin": -3}}}] | T14: 名单公布那天你们不在上面，宏远在。这件事从头到尾你只在会上听林薇提过一次，当时手上正忙着别的。
A15: GF15_Y04_AUTUMN_010 | B15: 涨工资还是买设备 | C15: 第4年·秋季 | D15: 100 | E15: 是 | F15: 厂长，班组三年没涨过工资了。陈工那边说要买套余热回收，也要这个数。钱只够一头。我不替谁说话，就是把话摆上来。 | G15: 0 | H15: 0 | J15: 0 | L15: 是 | M15: 源自 green-factory-15-years 厂长路线；原版条件事件已保留条件文本，当前按年份与季节抽取。 | N15: year_story | O15: 4 | P15: 秋 | Q15: zhou | R15: 老周 | S15: [{"id": "1", "text": "先给工人涨", "hint": "花 30 万 · 人心", "result": "涨薪通知贴出去那天，车间里有人放了挂鞭炮，被老周骂了一顿——厂区不许明火。但他自己笑得比谁都开。陈工的报价单又在抽屉里躺了一年，那年冬天蒸汽锅炉还是照常烧。", "effects": {"money": -30, "morale": 12, "smoke": 2, "aff": {"zhou": 4, "chen": -3}}}, {"id": "2", "text": "先买设备，工资明年一定涨", "hint": "花 30 万 · 欠一句话", "result": "余热回收装好，锅炉负荷降了两成，一年省下的煤气钱比设备还贵。陈工很兴奋，老周没说什么，只是那阵子很少再来办公室坐了。你记着自己欠了一句话——这句话要么明年还，要么永远还不上。", "effects": {"money": -30, "smoke": -8, "morale": -8, "aff": {"chen": 4, "zhou": -4}, "flag": "heat", "fac": {"power": 2}}}, {"id": "3", "text": "两边各一半", "hint": "花 34 万 · 谁都不满意", "result": "工资涨了一点，设备买了个小的。老周说\"聊胜于无\"，陈工说\"这个功率不够\"。你发现有些事情是没法折中的，但当时你确实想不出更好的办法。", "effects": {"money": -34, "smoke": -3, "morale": 3, "aff": {"zhou": 1, "chen": 1}}}] | T15: 两件事都没办。第二年春天走了四个熟练工，陈工的报价单在抽屉里又躺了一年。老周那阵子话很少。
A16: GF15_Y05_SPRING_011 | B16: 陈工提出辞职 | C16: 第5年·春季 | D16: 100 | E16: 是 | F16: 厂长，我想了很久……我打算走了。我来这儿五年，提过十七个方案，做成了三个。不是钱的事，是我看不到这厂有变化。 | G16: 0 | H16: 0 | J16: 0 | L16: 是 | M16: 源自 green-factory-15-years 厂长路线；原版条件事件已保留条件文本，当前按年份与季节抽取。 | N16: year_story | O16: 5 | P16: 春 | Q16: chen | R16: 陈工 | S16: [{"id": "1", "text": "把能源这一摊交给他，直接向我汇报", "hint": "他会留 · 老周那边不好交代", "result": "你把节能技改的立项权交给了他，还有一间小办公室。他愣了很久，说\"那我再试一年\"。老周知道后没说什么，只是在下一次生产会上当着所有人问：\"以后车间的事，是不是也归陈工管？\"你花了半年才把这件事捋顺。", "effects": {"morale": 2, "aff": {"chen": 6, "zhou": -3}, "flag": "chen_stay"}}, {"id": "2", "text": "加钱留人", "hint": "花 12 万/年 · 治标", "result": "他留下了，工资涨了。但那之后很少再提方案，交代什么做什么。有次你路过他办公室，看见他在看别的公司的招聘页面，很快就切走了。", "effects": {"money": -12, "aff": {"chen": 1}, "flag": "chen_paid"}}, {"id": "3", "text": "留不住就算了", "hint": "他走了", "result": "交接花了三天。走的那天他把五年的记录本全留下了，一共十一本，每页都是手写的表格和曲线。最上面一本扉页写着：\"总有一天有人会用得上。\"三个月后你听说，他去了宏远厂。厂里招了个技术员顶上，姓吴，刚毕业两年，人很勤快，只是那十一本记录他要看很久才看得懂。", "effects": {"smoke": 2, "morale": -5, "rival": 6, "flag": "chen_left"}}] | T16: 你一直没找他谈。三周后他把辞呈放在了你桌上，这次没有再问你的意见。走的那天你在外地。
A17: GF15_Y05_SUMMER_012 | B17: 危废合同到期了 | C17: 第5年·夏季 | D17: 100 | E17: 是 | F17: 危废处置的合同到期了。老单位涨价三成，一年要二十二万。另有一家报价九万，手续说是"能办下来"。仓库里那些桶已经堆到走道上了。 | G17: 0 | H17: 0 | J17: 0 | L17: 是 | M17: 源自 green-factory-15-years 厂长路线；原版条件事件已保留条件文本，当前按年份与季节抽取。 | N17: year_story | O17: 5 | P17: 夏 | Q17: zhao | R17: 老赵 | S17: [{"id": "1", "text": "跟老单位续，贵就贵", "hint": "花 22 万/年 · 安全", "result": "合同续了。每次转移都有联单、有称重、有对方回执。老赵每次签字都要叹口气。这笔钱在报表上一直很扎眼，直到很多年后你才知道它替你挡掉了什么。", "effects": {"money": -22, "aff": {"zhao": -1}, "flag": "haz_ok", "fac": {"waste": 1}}}, {"id": "2", "text": "换便宜那家，当天就来拉", "hint": "省 13 万 · 走道立刻通了", "result": "对方第二天就开车来拉，两趟拉完，堆了半年的桶一次清空，消防隐患也解决了。安全员特意来道了谢。你没问那些桶最后去了哪里，对方也没主动说。这件事就这么过去了——大部分时候，它确实就这么过去了。", "effects": {"money": -9, "morale": 4, "risk": 2, "flag": "haz_cheap"}}, {"id": "3", "text": "先减量：能不能少产生一点", "hint": "花 16 万 改工艺 · 慢，但是根上的办法", "result": "〔陈工和老周一起把清洗工序改了|老周带着新来的小吴，照着柜子里那些旧记录把清洗工序改了〕，溶剂用量降了四成，危废产生量跟着降。第二年处置费反而比原来还低。老周说：\"早知道能这么弄，何必年年跟人吵价钱。\"", "effects": {"money": -16, "smoke": -2, "aff": {"chen": 3, "zhou": 2}, "flag": "haz_reduce", "fac": {"waste": 2}}}] | T17: 合同断了两个月，桶越堆越多，最后是采购自己找了家便宜的拉走。手续齐不齐，没人问过。
... A20: GF15_Y06_AUTUMN_015 | B20: 高温限电，开五停二 | C20: 第6年·秋季 | D20: 100 | E20: 是 | F20: 今年热得邪门，电网下了有序用电通知，全市工业开五停二。厂长，咱们的单子交期都压着，怎么办？ | G20: 0 | H20: 0 | J20: 0 | L20: 是 | M20: 源自 green-factory-15-years 厂长路线；原版条件事件已保留条件文本，当前按年份与季节抽取。 | N20: year_story | O20: 6 | P20: 秋 | Q20: zhou | R20: 老周 | S20: [{"id": "1", "text": "按规定停，跟客户解释", "hint": "损失产量 · 讲信用", "result": "你亲自给三个客户打电话，能延的延、能调的调。有一家很不高兴，另外两家表示理解。老周说：\"厂长，你这电话打得比赶工强。\"宏远厂那边偷开了几天，被通报了。", "effects": {"orders": -6, "morale": 3, "fame": 3, "rival": -6}}, {"id": "2", "text": "想办法多开几天", "hint": "有风险", "result": "托了些关系多开三天。单子交上去了，但月底通报里出现了你们的名字。罚款不多，那条通报却被客户的合规部门看见了，年度评价扣了分。", "effects": {"money": -8, "fame": -6, "orders": -3, "group": -3, "risk": 1, "flag": "fined"}}] | T20: 你没有专门处理，车间按通知停了。交期全线延后，有客户在电话里发了很大的火，林薇挨的骂比你多。
A21: GF15_Y07_SPRING_016 | B21: 第 7 年春季事件 | C21: 第7年·春季 | D21: 100 | E21: 是 | F21: 中央生态环境保护督察组进驻本省，为期一个月。本市所有涉危废、涉废水的企业全面自查，随时可能被抽到。老周和〔陈工|小吴〕这两天都没怎么回家。 | G21: 0 | H21: 0 | J21: 0 | L21: 是 | M21: 源自 green-factory-15-years 厂长路线；原版条件事件已保留条件文本，当前按年份与季节抽取。 | N21: year_story | O21: 7 | P21: 春 | Q21: narr | R21: 旁白 | S21: [{"id": "1", "text": "（等消息）", "hint": "", "result": "", "effects": {}}]
A22: GF15_Y07_SUMMER_017 | B22: 马副总要砍掉一个项目 | C22: 第7年·夏季 | D22: 100 | E22: 是 | F22: 集团今年压降资本性支出，各厂一律砍一个在建项目。我知道你在推技改，也知道那些有用。但我在董事会上要有个能说出口的理由——你给我一个。 | G22: 0 | H22: 0 | J22: 0 | L22: 是 | M22: 源自 green-factory-15-years 厂长路线；原版条件事件已保留条件文本，当前按年份与季节抽取。 | N22: year_story | O22: 7 | P22: 夏 | Q22: ma | R22: 马副总 | S22: [{"id": "1", "text": "砍技改，先保生产", "hint": "集团满意 · 转型停一年", "result": "技改停了，生产照常。年底集团报表上你的成本控制排进前三，马副总在会上点名表扬。只是〔陈工那本方案本子又厚了一层，一个字都没动过。他后来说了句：\"停一年，赶回来要三年。\"|陈工留下的那十一本记录，又在柜子里多待了一年。小吴翻过几次，说看不太懂里面的批注。〕", "effects": {"money": 22, "smoke": 5, "group": 10, "aff": {"chen": -4, "zhao": 2}}}, {"id": "2", "text": "把客户审核的要求摆出来，让他替我们说话", "hint": "需要拿得出东西", "result": "你把客户审核清单、认证要求和整改期限整理成两页纸发过去。马副总看完打来电话：\"这个我能拿去说。\"董事会上他替你挡了下来，条件是你要在半年内拿出成效。这不是人情，是弹药。", "effects": {"money": -10, "smoke": -4, "group": 4, "aff": {"ma": 3, "chen": 4}, "flag": "held"}}, {"id": "3", "text": "硬顶：技改不能停，理由我说不清但我知道是对的", "hint": "顶住 · 他也很难做", "result": "你在电话里争了二十分钟。马副总最后说：\"我信你，但我在会上没法这么说。\"技改保住了，代价是他替你担了责任。那年你的成本排名很难看，年中被叫去做了一次专项说明。半年后他来厂里，只问了一句：\"成效呢？\"", "effects": {"money": -16, "smoke": -5, "fame": 2, "group": -12, "aff": {"chen": 5, "ma": -3}, "flag": "held"}}, {"id": "4", "text": "把方案改小，两头都保一点", "hint": "各退一步", "result": "项目缩了一半规模报上去，勉强算是执行了集团要求。效果打了折扣，但至少没断。有时候把事情做成的办法不是赢，是让它别死。", "effects": {"money": 4, "smoke": -1, "group": 2}}] | T22: 你没有回话。集团直接从名单上划掉了那个金额最大的技改项目，理由栏写着厂方未提出异议。
A23: GF15_Y07_AUTUMN_018 | B23: 年度报告的数据怎么报 | C23: 第7年·秋季 | D23: 100 | E23: 是 | F23: 年度报告要报集团了。咱们的减排数据不好看，宏远报的比我们漂亮一倍。有些口径其实是可以调一调的。集团只看排名。 | G23: 0 | H23: 0 | J23: 0 | L23: 是 | M23: 源自 green-factory-15-years 厂长路线；原版条件事件已保留条件文本，当前按年份与季节抽取。 | N23: year_story | O23: 7 | P23: 秋 | Q23: zhao | R23: 老赵 | S23: [{"id": "1", "text": "不调，是多少写多少", "hint": "排名难看 · 集团会问", "result": "报告报上去，排名中游偏后。马副总在电话里问了句\"你们这个数据怎么比宏远差这么多\"，你回：\"因为我们是实测的。\"他沉默几秒说\"知道了\"。那年的评优名单里没有你们。", "effects": {"fame": 3, "group": -6, "aff": {"zhao": -1}, "flag": "honest_report"}}, {"id": "2", "text": "调一调，跟同行差不多就行", "hint": "好看 · 埋下一颗雷", "result": "口径调整之后数据一下子体面了。集团年会上你们进了绿色制造标杆名单，马副总很高兴，配套奖励二十万当场落实，年终评优也有了你们的名字。老赵把报告交上去，什么也没说。这件事就这么过去了——大部分时候，它确实就这么过去了。", "effects": {"money": 20, "fame": 6, "group": 10, "risk": 1, "flag": "faked"}}] | T23: 报告是老赵按老口径交的，数字很难看。集团年会上点评了一句个别厂的绿色指标明显落后，虽然没点名。
A24: GF15_Y08_SPRING_019 | B24: 老周想退休了 | C24: 第8年·春季 | D24: 100 | E24: 是 | F24: 厂长，我腰上的老毛病犯了，医生让我别再下车间。我想着，是不是该退了。三车间那帮兄弟，我推荐小刘，他跟了我八年。 | G24: 0 | H24: 0 | J24: 0 | L24: 是 | M24: 源自 green-factory-15-years 厂长路线；原版条件事件已保留条件文本，当前按年份与季节抽取。 | N24: year_story | O24: 8 | P24: 春 | Q24: zhou | R24: 老周 | S24: [{"id": "1", "text": "让老周带小刘一年再退", "hint": "传下去 · 这一年产能会打折", "result": "那一年老周坐在车间办公室里看着小刘跑，把二十六年攒的东西一样样交出去——哪台机器听声音就知道要出事，哪个供应商的料不能收。过渡期磕碰不少，废品率高了一阵。退休那天全车间来送他，他说了三句话就说不下去了。", "effects": {"money": -10, "orders": -4, "morale": 9, "aff": {"zhou": 4}, "flag": "zhou_pass"}}, {"id": "2", "text": "挽留他再干几年", "hint": "他会答应 · 但身体扛不住", "result": "他答应了，还是每天下车间。第二年冬天在楼梯上滑了一跤，住了三个月院。你去看他，他躺在病床上说的第一句话是\"三车间的电机换了没\"。", "effects": {"morale": -5, "aff": {"zhou": 2}}}, {"id": "3", "text": "办退休手续，从外面招个厂长助理", "hint": "快 · 但断了", "result": "新人履历很漂亮，三个月后走了。第二个也没待满半年。车间里的人开始说\"外面来的不懂我们\"。老周那些经验，最后一样都没留下。", "effects": {"morale": -10, "orders": -3, "aff": {"zhou": -3}, "flag": "zhou_quit"}}] | T24: 你没有正面答复。他又硬撑了一年，冬天在楼梯上滑了一跤，住了三个月院。三车间那半年是散的。
A25: GF15_Y08_AUTUMN_020 | B25: 大客户要求独家供货 | C25: 第8年·秋季 | D25: 100 | E25: 是 | F25: 最大的那家客户提出做独家供应商，量翻倍，但不许再供他们的竞争对手。他们占我们四成，翻倍就是七成。宏远厂去年签了同样的协议。 | G25: 0 | H25: 0 | J25: 0 | L25: 是 | M25: 源自 green-factory-15-years 厂长路线；原版条件事件已保留条件文本，当前按年份与季节抽取。 | N25: year_story | O25: 8 | P25: 秋 | Q25: lin | R25: 林薇 | S25: [{"id": "1", "text": "签，把产线填满", "hint": "订单大涨 · 命交给一家", "result": "产线立刻排满，报表好看得不像话，集团年中通报表扬了你们。庆功宴上林薇喝多了，说了句：\"从今天起，我们的经营计划要看别人的脸色定。\"第二天她说自己喝醉了，不算数。", "effects": {"orders": 22, "money": 20, "group": 6, "flag": "exclusive", "aff": {"lin": -1, "zhao": 2}}}, {"id": "2", "text": "不签，宁可份额小一点", "hint": "短期掉量 · 睡得着", "result": "那家客户把三成份额转给了同行，但你们也接住了他们竞争对手的单子。林薇说：\"客户名单厚一点，冬天就没那么冷。\"这话第二年冬天应验了——宏远的独家客户砍单，他们空了两条线。", "effects": {"orders": -6, "fame": 2, "rival": -8, "aff": {"lin": 3}}}, {"id": "3", "text": "谈条件：要三年承诺和预付款", "hint": "手上得有他们换不掉的东西", "result": "林薇跑了四趟，拿回来三年最低采购量承诺和一笔预付款。她把合同拍在桌上：\"他们答应了。因为我们现在有他们换不掉的东西。\"那些东西，是你这些年一件件攒下来的。", "effects": {"orders": 14, "money": 32, "group": 5, "aff": {"lin": 5}, "flag": "good_deal"}}] | T25: 你迟迟没有表态。对方等了两个月，把份额分给了别人一半。既没有拿到独家的量，也没有守住多元的客户。
A26: GF15_Y09_SPRING_021 | B26: 排污许可证要换证 | C26: 第9年·春季 | D26: 100 | E26: 是 | F26: 排污许可证下个月到期，换证要核对这五年的排放数据。〔有几个月的在线监测是断的，报表上是补录的|我翻了半个月，有几个月的在线监测是断的。前任留下的批注我也看不太懂〕。审核员会看原始数据。 | G26: 0 | H26: 0 | J26: 0 | L26: 是 | M26: 源自 green-factory-15-years 厂长路线；原版条件事件已保留条件文本，当前按年份与季节抽取。 | N26: year_story | O26: 9 | P26: 春 | Q26: chen | R26: 陈工 | S26: [{"id": "1", "text": "如实申报，把断档的说明清楚", "hint": "可能被降类 · 但不留把柄", "result": "环保局要求补做一次全项监测和一份说明，多花了十二万，换证晚了一个月。管理类别没降。经办人临走说：\"断档不可怕，可怕的是补得天衣无缝——那才是真要查的。\"〔|小吴把这句话记在了本子第一页。〕", "effects": {"money": -12, "orders": -2, "fame": 2, "flag": "permit_ok", "aff": {"chen": 2}}}, {"id": "2", "text": "把断档的数据补齐再交", "hint": "省 12 万 · 不耽误生产 · 数据是编的", "result": "补录的曲线做得很自然，换证一次通过。〔陈工|小吴〕把那份表格存进文件夹，命名是\"最终版-勿动\"。他没说什么，但那天下班走得比平时早。", "effects": {"money": 6, "orders": 3, "risk": 2, "flag": "permit_fake", "aff": {"chen": -4}}}] | T26: 换证材料是办公室按老数据填的。环保局发现断档，要求补做全项监测并说明，罚了八万，管理类别降了一档。
A27: GF15_Y09_AUTUMN_022 | B27: 省媒体要来拍专题 | C27: 第9年·秋季 | D27: 100 | E27: 是 | F27: 省里的媒体要做绿色制造专题，集团报了两家，你们和宏远。他们只会选一家去拍。你们准备怎么讲这个故事？ | G27: 0 | H27: 0 | J27: 0 | L27: 是 | M27: 源自 green-factory-15-years 厂长路线；原版条件事件已保留条件文本，当前按年份与季节抽取。 | N27: year_story | O27: 9 | P27: 秋 | Q27: ma | R27: 马副总 | S27: [{"id": "1", "text": "让他们随便拍，车间也可以进", "hint": "敞开 · 万一拍到不该拍的", "result": "记者在厂里待了一天，什么都拍了，包括还没整改完的那个角落。最后那张照片是〔#zhou〕站在光伏板下面，安全帽拿在手里。稿子标题叫《一个车间主任的十年》。〔#zhou〕把报纸塑封了挂在家里。宏远那期没播。", "effects": {"fame": 12, "morale": 6, "orders": 6, "group": 6, "rival": -6}}, {"id": "2", "text": "安排好路线，只看做得好的地方", "hint": "稳妥", "result": "稿子发出来了，四平八稳，像所有那类稿子一样。厂里没人转发。你后来想，如果当时让他们随便走走，会不会不一样。", "effects": {"fame": 3, "group": 2}}, {"id": "3", "text": "让给宏远，我们没什么好讲的", "hint": "集团会记住这句话", "result": "马副总在电话里停顿很久，说了句\"好，我知道了\"。那期专题拍了宏远，他们厂长在镜头前讲了七分钟。年底集团的资源分配会上，你的名字排在后面。", "effects": {"fame": -3, "group": -8, "rival": 8, "aff": {"ma": -3}}}] | T27: 你让办公室对接，走了个流程。那期专题最后拍的是宏远，他们厂长在镜头前讲了七分钟。
A28: GF15_Y10_SPRING_023 | B28: 邻居投诉噪声和异味 | C28: 第10年·春季 | D28: 100 | E28: 是 | F28: 厂东墙外新建了一片住宅，去年交房。这个月环保投诉平台上，关于夜间噪声和异味的举报来了十一条。街道办打了电话，语气还算客气。 | G28: 0 | H28: 0 | J28: 0 | L28: 是 | M28: 源自 green-factory-15-years 厂长路线；原版条件事件已保留条件文本，当前按年份与季节抽取。 | N28: year_story | O28: 10 | P28: 春 | Q28: narr | R28: 旁白 | S28: [{"id": "1", "text": "停夜班，白天生产", "hint": "产能掉两成 · 投诉会停", "result": "夜班停了，投诉也停了。但订单交期开始紧张，有两家客户转了单。老赵算给你看：一年少赚八十万。你说：\"这钱是从人家窗户底下抢的。\"他没接话。", "effects": {"orders": -10, "money": -20, "fame": 4, "morale": 2, "flag": "noise_fixed"}}, {"id": "2", "text": "花钱做隔声和除臭", "hint": "花 46 万 · 根上解决", "result": "隔声屏和活性炭装置装了三个月。街道办后来把你们厂当成正面案例，在社区会上讲过一次。有位老太太送了面锦旗，上面写着\"还我安宁\"——〔#zhou〕把它挂在了传达室。", "effects": {"money": -46, "fame": 6, "morale": 3, "smoke": -2, "flag": "noise_fixed"}}, {"id": "3", "text": "先跟街道解释，观察一段", "hint": "省 46 万 · 夜班照开 · 投诉不会自己消失", "result": "你去街道办说明情况，态度诚恳，又送了两台净化器给居委会。投诉少了一阵，夜班一天没停，那笔五十五万留在账上过了个宽裕的冬天。入夏投诉又多起来，有人开始往生态环境部门举报，还拍了视频。这件事没有结束，只是暂时安静。", "effects": {"money": 10, "risk": 2, "fame": -3, "flag": "noise_risk"}}] | T28: 投诉一直没处理。入夏之后有人往生态环境部门举报，还拍了视频。街道办第三次打电话来时，语气已经不客气了。
A29: GF15_Y10_AUTUMN_024 | B29: 一笔要加班两个月的大单 | C29: 第10年·秋季 | D29: 100 | E29: 是 | F29: 有笔大单，交期只有两个月。要接，车间得连着加两个月的班。厂长，我先说清楚：这单能让今年的数字很好看，集团那边也交代得过去。 | G29: 0 | H29: 0 | J29: 0 | L29: 是 | M29: 源自 green-factory-15-years 厂长路线；原版条件事件已保留条件文本，当前按年份与季节抽取。 | N29: year_story | O29: 10 | P29: 秋 | Q29: lin | R29: 林薇 | S29: [{"id": "1", "text": "接，全厂动员", "hint": "钱和面子 · 人会很累", "result": "两个月，车间的灯几乎没灭过。单子交了，年终奖发得比往年厚，集团通报点了名。但年后走了七个人，其中三个是干了十年以上的老师傅。〔#zhou〕说：\"钱能补，人补不回来。\"", "effects": {"money": 50, "orders": 8, "morale": -15, "smoke": 5, "group": 8}}, {"id": "2", "text": "接一半，另一半推给同行", "hint": "少赚 · 人不垮", "result": "林薇把一半的量介绍给了另一家小厂，还拿了协调费。客户没有不满，反而觉得你们实在。年后没有人辞职。", "effects": {"money": 26, "orders": 4, "morale": 2, "aff": {"lin": 2}}}, {"id": "3", "text": "不接，产能不够就是不够", "hint": "放弃", "result": "这单被宏远接走。老赵在会上算了笔账，说够全厂两个月的利润。你说：\"算不进去的是那七个人。\"他没再说话。", "effects": {"orders": -4, "morale": 7, "rival": 6, "group": -4}}] | T29: 你没有下决心，林薇按常规产能报了个交期，客户嫌慢，转给了宏远。车间那两个月很轻松。
A30: GF15_Y11_SPRING_025 | B30: 马副总一个人来了 | C30: 第11年·春季 | D30: 100 | E30: 是 | F30: （他这次是一个人来的，没带秘书，在车间外面站了很久）其实我知道你这些年做的是什么。但集团考核只有三个指标，没有一个跟这些有关。我快到年纪了，你有什么想说的，趁现在。 | G30: 0 | H30: 0 | J30: 0 | L30: 是 | M30: 源自 green-factory-15-years 厂长路线；原版条件事件已保留条件文本，当前按年份与季节抽取。 | N30: year_story | O30: 11 | P30: 春 | Q30: ma | R30: 马副总 | S30: [{"id": "1", "text": "请他把绿色投入单列一项考核", "hint": "他要为此得罪人", "result": "他听完只说\"我试试\"。半年后集团确实加了一项\"绿色制造\"考核，权重不高，但从此这些投入不再是\"额外的支出\"。代价是他在那次会上得罪了两位同级。他没跟你提过这件事，是老赵后来听说的。", "effects": {"group": 12, "fame": 4, "aff": {"ma": 5}, "flag": "kpi"}}, {"id": "2", "text": "请他多批点预算", "hint": "实在 · 但只解一时", "result": "他批了一百二十万专项。钱很快就花完了，用在了该用的地方。但第二年他退了，新来的人不认这笔账，问的第一个问题是\"去年那笔钱产出是多少\"。", "effects": {"money": 58, "group": 2, "aff": {"ma": 2}}}, {"id": "3", "text": "什么都没说，陪他在车间外站着", "hint": "有些话说了也没用", "result": "你们抽了两根烟。他临走说：\"我在这个位子上二十年，见过太多厂长跟我讲道理。你算讲得少的。\"上车前他补了一句：\"厂子是你的，我是过路的。\"", "effects": {"aff": {"ma": 3}, "morale": 1}}] | T30: 你陪他在车间外站了会儿，聊的都是场面话。他上车前看了你一眼，什么也没说。半年后他退了。
A31: GF15_Y11_AUTUMN_026 | B31: 本行业纳入了碳市场 | C31: 第11年·秋季 | D31: 100 | E31: 是 | F31: 本行业被纳入全国碳市场了。超出基准的排放要买配额清缴，我算了一下，按现在的排放水平，一年要多掏一笔不小的钱。 | G31: 0 | H31: 0 | J31: 0 | L31: 是 | M31: 源自 green-factory-15-years 厂长路线；原版条件事件已保留条件文本，当前按年份与季节抽取。 | N31: year_story | O31: 11 | P31: 秋 | Q31: zhao | R31: 老赵 | S31: [{"id": "1", "text": "买配额，先把合规问题解决", "hint": "每年都要掏", "result": "配额买了，合规了。老赵每年做预算的时候都会单列这一行，数字一年比一年大。他说：\"这笔钱是白花的。\"你说：\"不是白花，是替过去的十年还账。\"", "effects": {"money": -30, "flag": "quota_buy"}}, {"id": "2", "text": "借这个由头，把该做的技改一次做完", "hint": "花 70 万 · 一次性解决", "result": "你把碳市场当成了说服所有人的理由——包括集团、老赵、还有那些觉得节能是折腾的人。锅炉、空压、电机一起改完，第二年不但不用买配额，还富余出一点可以卖。老赵第一次主动说了句：\"这钱花得值。\"", "effects": {"money": -70, "smoke": -14, "group": 4, "fame": 4, "aff": {"zhao": 3, "chen": 4}, "flag": "quota_cut"}}, {"id": "3", "text": "先按最低标准应付，观望一年", "hint": "观望 · 明年配额只会更贵", "result": "你选择观望。第二年配额价格涨了四成，你多掏了将近一倍的钱。这类事情的规律是：越晚动手越贵，而每一年当时看都\"再等等也行\"。", "effects": {"money": -20, "smoke": 2, "flag": "quota_wait"}}] | T31: 配额是财务按最低标准买的，多花了不少钱。这件事从此每年都要花一笔，而你始终没想明白它到底能不能省。
A32: GF15_Y12_SPRING_027 | B32: 新客户要产品碳足迹报告 | C32: 第12年·春季 | D32: 100 | E32: 是 | F32: 一家做储能的新客户来问，说他们的供应商必须提供产品碳足迹报告。这个客户所在的行业每年翻一倍。但报告要做，得先有这些年的完整数据。 | G32: 0 | H32: 0 | J32: 0 | L32: 是 | M32: 源自 green-factory-15-years 厂长路线；原版条件事件已保留条件文本，当前按年份与季节抽取。 | N32: year_story | O32: 12 | P32: 春 | Q32: lin | R32: 林薇 | S32: [{"id": "1", "text": "做，把这些年的数据整理出来", "hint": "花 25 万 · 要看你有没有底子", "result": "〔陈工|小吴照着陈工留下的那十一本记录，〕把这些年的表、单据、监测记录整理了两个月，做出了第一份产品碳足迹报告。客户看完只说了一句：\"你们这个是真做出来的，不是买的。\"当年就下了第一批单，第二年翻了三倍。", "effects": {"money": -25, "orders": 18, "fame": 8, "group": 4, "aff": {"chen": 4, "lin": 4}, "flag": "cfp"}}, {"id": "2", "text": "找家机构快速出一份", "hint": "花 15 万 · 数据是估的", "result": "报告出得很快，客户看完提了十七个问题，其中十一个你们答不上来。这单最后没成。林薇说：\"他们不是不信我们，是我们真的说不清。\"", "effects": {"money": -15, "orders": 2, "aff": {"lin": -2}}}, {"id": "3", "text": "这个行业太新，先不碰", "hint": "放弃一条赛道", "result": "你婉拒了。三年后这个客户成了行业里的头部，宏远厂是他们的一级供应商。林薇偶尔会提起这件事，语气很平静，但每次都会提。", "effects": {"orders": -4, "rival": 10}}] | T32: 你让办公室回了封客气的邮件，说正在筹备中。对方没有再来。三年后这家客户成了行业头部，一级供应商里有宏远。
A33: GF15_Y12_AUTUMN_028 | B33: VOCs 设施平时没开 | C33: 第12年·秋季 | D33: 100 | E33: 是 | F33: 〔zhou:厂长，有件事我憋了两年，今天跟您说。|老周退了以后没人再提这事，今天是我壮着胆子说的。〕VOCs 那套治理设施，这两年基本没开过，一开电费一个月多两万。老工人都知道，就是没人说。 | G33: 0 | H33: 0 | J33: 0 | L33: 是 | M33: 源自 green-factory-15-years 厂长路线；原版条件事件已保留条件文本，当前按年份与季节抽取。 | N33: year_story | O33: 12 | P33: 秋 | Q33: zhou | R33: 老周 | S33: [{"id": "1", "text": "从今天起必须开，电费我认", "hint": "20 万/年 · 没人会为此表扬你", "result": "设施开了，电费涨了，报表难看了。没有客户会因为这个多给你一分钱，没有媒体会来报道。三年后一次夜查，执法人员调了运行记录，看完什么也没说就走了——那一刻你才知道这笔钱买的是什么。", "effects": {"money": -20, "smoke": -2, "fame": 2, "flag": "voc_on", "aff": {"zhou": 3}, "fac": {"air": 1}}}, {"id": "2", "text": "检查的时候开，平时关", "hint": "一年省 20 万 · 这行大半都这么干", "result": "你没有明说，只是让车间\"灵活掌握\"。省下的电费，年底给全厂发了笔奖金，人人有份。厂里所有人都懂那句\"灵活掌握\"是什么意思，也没有人觉得有什么不对——这件事从此成了心照不宣的一部分，直到有一天它不再是。", "effects": {"money": 30, "morale": 5, "risk": 3, "flag": "voc_off"}}, {"id": "3", "text": "改工艺，从源头少产生 VOCs", "hint": "花 58 万 · 贵，但一劳永逸", "result": "水性替代做了半年，产生量降了六成，治理设施常开也不心疼了。这笔钱花得比谁都多，但从此这项再没让你半夜惊醒过。〔陈工说：\"厂长，这是我这些年做过最有价值的项目。\"|小吴说：\"厂长，这个方案陈工的本子里写过，第七本第三页。\"〕", "effects": {"money": -58, "smoke": -4, "fame": 4, "aff": {"chen": 5, "zhou": 2}, "flag": "voc_clean", "fac": {"air": 2}}}] | T33: 这句话你听过就算了。设施照旧是检查才开，厂里所有人都懂那句灵活掌握是什么意思。
... A62: GF15_Y14_SUMMER_057 | B62: 〔陈工|小吴〕递上来一份技改方案 | C62: 第14年·夏季 | D62: 100 | E62: 是 | F62: 厂长，这是今年的技改方案。我按轻重缓急排了序，钱您看着定。哪一项都不白花，就是不知道哪一项最急。 | G62: 0 | H62: 0 | J62: 0 | L62: 否 | M62: 原版年度技改菜单，仅作为资料保留；按已确认规则不在当前游戏触发。 | N62: year_story | O62: 14 | P62: 夏 | Q62: chen | R62: 陈工 | S62: [] | T62: 方案压在你桌上一年，没批也没退。〔陈工|小吴〕后来自己把它收回去了，说等厂里宽裕了再提。
A63: GF15_Y08_SUMMER_058 | B63: 副厂长的位子还空着 | C63: 第8年·夏季 | D63: 100 | E63: 是 | F63: 厂长，副厂长这个位子空了五年了。小刘现在能顶半个班，集团那边也可以派人下来。再拖下去，底下的人不知道该听谁的。 | G63: 0 | H63: 0 | J63: 0 | L63: 是 | M63: 源自 green-factory-15-years 厂长路线；原版条件事件已保留条件文本，当前按年份与季节抽取。 | N63: year_story | O63: 8 | P63: 夏 | Q63: zhao | R63: 老赵 | S63: [{"id": "1", "text": "提小刘", "hint": "自己人 · 他还嫩", "result": "小刘上任那天，老周在食堂多喝了两杯。他确实还嫩，头一年出过两次差错，但三年后他能独当一面了。从此有些事你终于可以放手。", "effects": {"morale": 6, "orders": -2, "aff": {"zhou": 4}, "flag": "vp_zhou"}}, {"id": "2", "text": "请集团派一个下来", "hint": "快 · 但他向集团负责", "result": "集团派来的人很能干，也很清楚自己该向谁汇报。厂里的事从此有两个人在管，有些话你不方便当着他说了——但精力确实腾出来了。", "effects": {"group": 6, "morale": -3, "tech": 5, "flag": "vp_out"}}] | T63: 位子继续空着。你一个人扛到底，第十年开始发现自己在会上讲的每句话都要重复三遍。 | U63: function(s){ return !s.flag.vp_zhou && !s.flag.vp_out; }
A64: GF15_Y06_SUMMER_059 | B64: 招个厂长助理 | C64: 第6年·夏季 | D64: 100 | E64: 是 | F64: 厂长，您一个人签的字比三个副厂长加起来还多。招个助理吧，一年三十万，帮您跑会、盯进度、整材料。 | G64: 0 | H64: 0 | J64: 0 | L64: 是 | M64: 源自 green-factory-15-years 厂长路线；原版条件事件已保留条件文本，当前按年份与季节抽取。 | N64: year_story | O64: 6 | P64: 夏 | Q64: zhao | R64: 老赵 | S64: [{"id": "1", "text": "招", "hint": "花 28 万/年 · 每年多一份精力", "result": "助理来的第一个月就把你桌上积了半年的材料清空了。往后每年你能多办一件事——这笔钱，是这些年花得最不显眼也最值的一笔。", "effects": {"money": -28, "flag": "assistant"}}, {"id": "2", "text": "不招，我自己来", "hint": "省钱 · 也省不下多少", "result": "你继续一个人扛。省下的那笔钱，大概相当于每年少办一件事的代价——只是这笔账，没有人会替你算。", "effects": {"money": 12}}] | T64: 招人的事一直没定。那些本该有人替你跑的会、写的材料、盯的进度，还是你自己在做。
A65: GF15_Y05_SUMMER_060 | B65: 宏远在客户那儿说我们坏话 | C65: 第5年·夏季 | D65: 100 | E65: 是 | F65: 宏远的销售在客户那儿说，我们的环保手续有问题、随时可能被停产。客户昨天专门来问了我。厂长，这话不好听，但也不全是假的。 | G65: 0 | H65: 0 | J65: 0 | L65: 是 | M65: 源自 green-factory-15-years 厂长路线；原版条件事件已保留条件文本，当前按年份与季节抽取。 | N65: year_story | O65: 5 | P65: 夏 | Q65: lin | R65: 林薇 | S65: [{"id": "1", "text": "把手续和台账全部摆给客户看", "hint": "要经得起看", "result": "你把排污许可证、监测报告、整改记录装订成册寄了过去。客户的采购看完打了个电话：\"贵司比传言里干净得多。\"那一年他们加了两成的量，宏远的销售被换掉了。", "effects": {"orders": 12, "fame": 6, "rival": -10}}, {"id": "2", "text": "请客户来厂里走一趟", "hint": "花 8 万 接待 · 眼见为实", "result": "客户来了半天，车间转了一圈。回去后没再提这事，但也没加量。有些疑虑消除不了，只能稀释。", "effects": {"money": -8, "orders": 3, "fame": 2}}, {"id": "3", "text": "也去说他们两句", "hint": "互泼脏水", "result": "两家的销售在客户那儿吵起来，客户嫌烦，把这一档的份额分给了第三家。林薇后来说：\"那次是我这些年最丢人的一场仗。\"", "effects": {"orders": -8, "fame": -5, "rival": -4, "aff": {"lin": -3}}}] | T65: 你没有回应。那家客户后来把份额调走了三成，理由是"综合考量"。有些话不解释，就成了事实。
A66: GF15_Y10_SUMMER_061 | B66: 宏远来谈合并 | C66: 第10年·夏季 | D66: 100 | E66: 是 | F66: 宏远的董事长托人来问，愿不愿意谈合并。他们出钱，你们出产能和资质，合并后你做副总。厂子还在，但名字要换。 | G66: 0 | H66: 0 | J66: 0 | L66: 是 | M66: 源自 green-factory-15-years 厂长路线；原版条件事件已保留条件文本，当前按年份与季节抽取。 | N66: year_story | O66: 10 | P66: 夏 | Q66: zhao | R66: 老赵 | S66: [{"id": "1", "text": "谈，把厂子并进去", "hint": "提前上岸 · 但故事到此为止", "result": "谈了三个月，条件不错。签字那天你在会议室外站了很久，想起十年前第一次走进这个厂门的下午。", "effects": {"money": 90, "flag": "merged"}}, {"id": "2", "text": "不谈", "hint": "硬扛 · 他们会更用力", "result": "你回绝得很干脆。那之后宏远在每一个客户、每一次招标上都咬着你。压力大了，但厂里的人反而拧成了一股绳——〔#zhou〕说：\"咱们厂长没卖我们。\"", "effects": {"morale": 8, "rival": 8, "orders": -4, "flag": "refused_merge"}}, {"id": "3", "text": "反过来问他们卖不卖", "hint": "虚张声势 · 也可能真成", "result": "对方愣了几秒，笑了，说回去问问。这事没成，但从那以后，行业里再没人把你们当成随时能被吃掉的那一家。", "effects": {"fame": 6, "group": 4, "rival": -6}}] | T66: 你没回话。三个月后他们收购了另一家同行，产能一下超过你们一倍。行业里从此只有"宏远和其他"。
A67: GF15_Y04_SUMMER_062 | B67: 有个工伤要处理 | C67: 第4年·夏季 | D67: 100 | E67: 是 | F67: 厂长，二车间小张昨天让机器压了手，三根指头。按规矩该走工伤，但那台机器的防护罩三个月前就坏了，一直没换。这事怎么说，您定。 | G67: 0 | H67: 0 | J67: 0 | L67: 是 | M67: 源自 green-factory-15-years 厂长路线；原版条件事件已保留条件文本，当前按年份与季节抽取。 | N67: year_story | O67: 4 | P67: 夏 | Q67: zhou | R67: 老周 | S67: [{"id": "1", "text": "如实上报，该赔赔，该整改整改", "hint": "花 28 万 · 会被处罚", "result": "工伤认定、安监罚款、全厂设备排查，一样没落。老周带人把所有防护罩换了一遍。厂里从此有了个规矩：安全隐患上报当天必须闭环。这规矩后来救过至少两个人。", "effects": {"money": -28, "fame": -3, "morale": 9, "risk": -1, "aff": {"zhou": 5}, "flag": "safety"}}, {"id": "2", "text": "私下和解，别报了", "hint": "花 18 万 · 省事", "result": "家属拿了钱，字签了，事情压了下来。车间里没人再提这件事，但也没人再相信\"有问题及时报\"这句话。往后两年，小毛病都是自己扛着不说。", "effects": {"money": -18, "morale": -8, "risk": 2, "aff": {"zhou": -4}, "flag": "hidden_injury"}}, {"id": "3", "text": "按规矩办，但先追责班组", "hint": "严 · 但人心散", "result": "班长被处分，赔偿按最低标准给。程序上无可挑剔。老周只说了一句：\"厂长，防护罩坏了三个月，是我没盯住，不是他。\"从那以后他再没替谁说过话。", "effects": {"money": -22, "morale": -11, "aff": {"zhou": -6}}}] | T67: 处理拖了两个月，家属堵了厂门。最后赔的钱比一开始谈的多了一倍，还上了本地新闻。
A68: GF15_Y12_SUMMER_063 | B68: 集团内部两派要你站队 | C68: 第12年·夏季 | D68: 100 | E68: 是 | F68: 集团在争一个方案：一派要把下属厂整合成事业部，一派要各厂保持独立核算。两边都来找过你了。你怎么表态，他们都记着。 | G68: 0 | H68: 0 | J68: 0 | L68: 是 | M68: 源自 green-factory-15-years 厂长路线；原版条件事件已保留条件文本，当前按年份与季节抽取。 | N68: year_story | O68: 12 | P68: 夏 | Q68: ma | R68: 马副总 | S68: [{"id": "1", "text": "支持整合", "hint": "顺势 · 但会失去自主权", "result": "方案通过了，你成了事业部下面的一个生产基地。资源多了，技改预算不用自己争了，但从此立项要报三级。有些事你再也做不了主。", "effects": {"group": 12, "money": 42, "tech": -4, "flag": "integrated"}}, {"id": "2", "text": "支持独立核算", "hint": "保住自主 · 得罪另一派", "result": "独立核算保住了。你可以继续自己拍板，代价是那一派掌权之后，你的名字在几份名单上都排在后面。老赵说：\"厂长，您这是拿前程换了拍板权。\"", "effects": {"group": -10, "morale": 4, "flag": "independent"}}, {"id": "3", "text": "谁也不得罪，说都有道理", "hint": "安全 · 但两边都不把你当自己人", "result": "你打了太极。方案定下来之后，你既没被整合掉，也没进核心圈。往后几年，凡是需要集团出面的事，你总要多等一轮。", "effects": {"group": -4, "money": -10}}] | T68: 你两边都没表态。方案通过后，新体系里你们厂被划进了"待整合"那一类——不是惩罚，只是没人替你说话。
A69: GF15_Y05_SUMMER_064 | B69: 老赵又问了一次 | C69: 第5年·夏季 | D69: 100 | E69: 是 | F69: 三年前我问过您一次，这厂靠什么吃饭。那次您没答，我就当您还在想。现在三年过去了，每一笔钱我都是凭感觉批的。厂长，我不是催您，我是快退休了。 | G69: 0 | H69: 0 | J69: 0 | L69: 是 | M69: 源自 green-factory-15-years 厂长路线；原版条件事件已保留条件文本，当前按年份与季节抽取。 | N69: year_story | O69: 5 | P69: 夏 | Q69: zhao | R69: 老赵 | S69: [{"id": "1", "text": "靠成本：谁也别想比我们便宜", "hint": "晚了三年 · 该压的地方已经压过一轮", "result": "方向总算定了。老赵松了口气，但也说了实话：\"厂长，这三年该攒的成本优势，别人已经攒完了。我们现在做的，是补课。\"", "effects": {"money": 12, "orders": 4, "aff": {"zhao": 3, "lin": -2}, "flag": "m_cost"}}, {"id": "2", "text": "靠技术：做别人做不了的活", "hint": "晚了三年 · 起步的钱更贵了", "result": "方向定了。〔陈工|小吴〕听说以后什么也没说，只是把压在最下面那本方案翻了出来。老赵算了一遍：\"同样的事，三年前做要八十万，现在要一百二。等待也是有价钱的。\"", "effects": {"money": -22, "tech": 11, "aff": {"chen": 4, "zhao": -2}, "flag": "m_tech"}}, {"id": "3", "text": "靠客户：把牌子和口碑做起来", "hint": "晚了三年 · 名声要从头攒", "result": "方向定了。林薇很高兴，但也提醒你：\"名声这东西，前三年攒的最值钱，因为那时候没人看着你。现在开始攒，得跑得比别人快一倍。\"", "effects": {"money": -14, "fame": 6, "aff": {"lin": 4, "zhao": -2}, "flag": "m_brand"}}] | T69: 他没再问第三遍。往后做预算，凡是拿不准的，他一律按上一年的数照抄——一个没有方向的厂，钱花得最散，也最无声。 | U69: function(s){ return !s.mode; }
A70: GF15_Y09_SUMMER_065 | B70: 集团当众问：你们厂到底是什么厂 | C70: 第9年·夏季 | D70: 100 | E70: 是 | F70: （经营分析会上，他忽然打断了你）别念数字了。我就问一句：你们厂在集团里，到底是干什么的那一家？台下十几个厂长都在听。 | G70: 0 | H70: 0 | J70: 0 | L70: 是 | M70: 源自 green-factory-15-years 厂长路线；原版条件事件已保留条件文本，当前按年份与季节抽取。 | N70: year_story | O70: 9 | P70: 夏 | Q70: ma | R70: 马副总 | S70: [{"id": "1", "text": "我们是成本最低的那一家", "hint": "当众定调 · 从此只能拼价格", "result": "你说完，会场安静了两秒。有个老厂长点了点头。散会后马副总说：\"这话说出去就收不回来了，往后集团给你的单子都是这一类。\"果然如此。", "effects": {"money": 20, "orders": 6, "fame": -4, "group": 5, "flag": "m_cost"}}, {"id": "2", "text": "我们是能接别人接不了的活的那一家", "hint": "把话说满 · 半年内要拿出东西", "result": "马副总说：\"好，我记下了。半年后我来看。\"回厂的路上你才开始想，这话到底靠什么兑现。那半年〔陈工|小吴〕几乎住在车间——你把自己逼到了没有退路的位置。", "effects": {"money": -25, "tech": 16, "morale": -4, "group": 4, "aff": {"chen": 5}, "flag": "m_tech"}}, {"id": "3", "text": "我们是客户敢把名字挂上去的那一家", "hint": "漂亮话 · 也是最难兑现的那句", "result": "台下有人笑了一声。马副总没笑，他说：\"这句话我在集团听过三次，前两次说完都没了下文。\"这句话后来一直压在你心上——它逼着你在每一次可以省事的时候没有省。", "effects": {"money": -16, "fame": 9, "group": 3, "aff": {"lin": 4}, "flag": "m_brand"}}] | T70: 你在会上讲了二十分钟的生产数据，没有回答那个问题。散会后马副总跟你走了一段，说："下次别讲那么细，讲细了就是没话说。" | U70: function(s){ return !s.mode; }
A71: GF15_Y13_SPRING_066 | B71: 年报上那一栏还空着 | C71: 第13年·春季 | D71: 100 | E71: 是 | F71: 集团年报要各厂填一栏：核心竞争力。这栏咱们填了十二年"性价比"。厂长，我明年也该退了，这一栏，能不能这次填个真的。 | G71: 0 | H71: 0 | J71: 0 | L71: 是 | M71: 源自 green-factory-15-years 厂长路线；原版条件事件已保留条件文本，当前按年份与季节抽取。 | N71: year_story | O71: 13 | P71: 春 | Q71: zhao | R71: 老赵 | S71: [{"id": "1", "text": "填\"成本\"，认了", "hint": "诚实 · 也是十二年的定论", "result": "你填了成本两个字。老赵看了很久，说：\"其实这十二年，咱们真的把成本做到了这一带最低。只是从来没人敢把它当成一件正经事来说。\"", "effects": {"money": 16, "orders": 4, "flag": "m_cost"}}, {"id": "2", "text": "填\"技术\"，然后用剩下三年把它变成真的", "hint": "先立字据 · 逼自己一把", "result": "填完这两个字，你把剩下的钱全砸进了技改。老赵在退休前最后一次签字时说：\"厂长，您这是先写答案再做题。\"三年时间不够把它做成，但够把它做像。", "effects": {"money": -30, "tech": 14, "flag": "m_tech"}}, {"id": "3", "text": "空着，等新厂长来填", "hint": "留白 · 集团会自己填", "result": "那一栏交上去是空的。集团办公室的人打电话来确认，你说就空着吧。第二年印出来的年报上，那一栏被人代填了四个字：\"产能配套\"。", "effects": {"group": -9, "fame": -3}}] | T71: 那一栏最后填的是"综合型制造企业"。集团的人看到这六个字就明白了：这个厂没有想清楚过自己是谁。 | U71: function(s){ return !s.mode; }
A72: GF15_Y01_SUMMER_067 | B72: 老周的侄子想进厂 | C72: 第1年·夏季 | D72: 100 | E72: 是 | F72: 厂长，有件私事。我侄子技校刚毕业，想进厂，从学徒干起。我知道这话不该我说。我在这厂二十六年，头一回开这个口。 | G72: 0 | H72: 0 | J72: 0 | L72: 是 | M72: 源自 green-factory-15-years 厂长路线；原版条件事件已保留条件文本，当前按年份与季节抽取。 | N72: year_story | O72: 1 | P72: 夏 | Q72: zhou | R72: 老周 | S72: [{"id": "1", "text": "收下，就当还老周一个人情", "hint": "老周记你的好 · 别人也会记这件事", "result": "小伙子进了三车间，干活还算利索。这事没人当面说什么，但那年招工，又来了三个\"谁谁家的孩子\"。你后来才知道，一个口子开了，关上要难十倍。", "effects": {"morale": -3, "aff": {"zhou": 7}, "flag": "nepo_in"}}, {"id": "2", "text": "不收，规矩是规矩", "hint": "干净 · 但你伤了他", "result": "老周站起来说了句\"我知道了，是我唐突\"，然后正常上班，正常汇报，正常交代。他再没有跟你说过一句厂子以外的话。有些距离一旦拉开，就再没有理由拉回来。", "effects": {"aff": {"zhou": -6}, "flag": "nepo_out"}}, {"id": "3", "text": "让他跟别人一起考，考上我不拦", "hint": "看起来最公道 · 两头都不落好", "result": "厂里第一次有了招工考试。他侄子考了第四，招三个。老周什么也没说，倒是别的班组的人私下议论：\"厂长这是不想收，又不想担名声。\"公道这东西，有时候比偏袒还伤人。", "effects": {"morale": 2, "aff": {"zhou": -3}, "flag": "hire_exam"}}] | T72: 这事你一直没答复。老周没再提，但那年之后凡是你交代的事，他都办得一丝不苟——太一丝不苟了，多一句话都没有。
A73: GF15_Y02_AUTUMN_068 | B73: 前任留下的那家供应商 | C73: 第2年·秋季 | D73: 100 | E73: 是 | F73: 有家供料的，价格比市面高一成，质量倒是稳。他们老板是前任厂长的连襟。合同年底到期。厂长，这事您得知道，怎么办我不敢替您想。 | G73: 0 | H73: 0 | J73: 0 | L73: 是 | M73: 源自 green-factory-15-years 厂长路线；原版条件事件已保留条件文本，当前按年份与季节抽取。 | N73: year_story | O73: 2 | P73: 秋 | Q73: zhao | R73: 老赵 | S73: [{"id": "1", "text": "换掉，走公开比价", "hint": "省钱 · 前任还在集团", "result": "比价换了一家，一年省下二十来万。三个月后集团一位老同志来厂里\"了解情况\"，什么也没查，临走说了句：\"年轻人做事，是要利落一点。\"这句话你琢磨了很久。", "effects": {"money": 26, "group": -6, "flag": "cut_crony"}}, {"id": "2", "text": "留着，不惹这个麻烦", "hint": "省事 · 每年多掏一笔", "result": "合同照续。这一成的差价此后年年都在，老赵每次做报表都会用红笔在那一行画个圈，然后什么也不说。", "effects": {"money": -14, "aff": {"zhao": -3}, "flag": "keep_crony"}}, {"id": "3", "text": "留着，但把标准提上去", "hint": "不撕破脸 · 要花力气盯", "result": "你重新签了合同，价格不动，但加了来料检验和考核条款。对方老板一开始不高兴，半年后反而认真起来。这条路最麻烦，你自己也说不清是聪明还是懦弱。", "effects": {"money": -4, "tech": 4, "aff": {"zhao": 2}, "flag": "tame_crony"}}] | T73: 这事你没碰。那家供应商又供了十几年，料价一直高一成。老赵每年都在报表上标出来，每年都没有人问。
A74: GF15_Y07_SUMMER_069 | B74: 账上有一笔说不清的钱 | C74: 第7年·夏季 | D74: 100 | E74: 是 | F74: 去年那笔环保设备的款，付了款，设备到了，但验收单上的签字不是本人的。金额不大，十六万。厂长，我可以按流程补一份，也可以往上报。 | G74: 0 | H74: 0 | J74: 0 | L74: 是 | M74: 源自 green-factory-15-years 厂长路线；原版条件事件已保留条件文本，当前按年份与季节抽取。 | N74: year_story | O74: 7 | P74: 夏 | Q74: zhao | R74: 老赵 | S74: [{"id": "1", "text": "往上报，请集团来查", "hint": "干净 · 会牵出人", "result": "审计组来了十天。结论是采购员违规代签，没有资金问题，那人调离。老赵说：\"厂长，您这次做对了，但采购科那几个人，从此不会替您办任何一件不在纸面上的事。\"", "effects": {"money": -6, "group": 6, "morale": -6, "flag": "audit_self"}}, {"id": "2", "text": "补一份，事情到此为止", "hint": "省事 · 你也签了字", "result": "手续补齐了，账平了。这件事从此有了两个知情人——你和老赵。他后来没再提过，只是每次遇到需要你签字的模糊地带，他都会多问一句\"确定吗\"。", "effects": {"risk": 1, "aff": {"zhao": -2}, "flag": "covered"}}, {"id": "3", "text": "先查清楚这钱到底去哪儿了", "hint": "自己动手 · 可能挖出更多", "result": "你查了两周，发现是采购员图省事替供应商代签，钱没有问题。但顺带翻出了另外三笔类似的操作。你把这些一起做了内部通报，没有报上去。厂里的人从此知道：这位厂长自己是会查账的。", "effects": {"morale": -3, "risk": -1, "group": 2, "aff": {"zhao": 4}, "flag": "self_clean"}}] | T74: 你没有处理。这笔钱在账上挂了很多年，每次审计都被问一次，每次都被含糊过去。它不大，但它一直在那儿。
A75: GF15_Y09_SUMMER_070 | B75: 宏远挖走了你的销售骨干 | C75: 第9年·夏季 | D75: 100 | E75: 是 | F75: 我手下最能跑的那个去了宏远，带走了三家客户的联系人。他跟了我六年，我一点风声都没听到。厂长，我这两年是不是把人管松了。 | G75: 0 | H75: 0 | J75: 0 | L75: 是 | M75: 源自 green-factory-15-years 厂长路线；原版条件事件已保留条件文本，当前按年份与季节抽取。 | N75: year_story | O75: 9 | P75: 夏 | Q75: lin | R75: 林薇 | S75: [{"id": "1", "text": "给销售团队重做一套提成和晋升", "hint": "花 26 万/年 · 治本，但要两年才见效", "result": "方案改了三稿才定。头一年成本上去了，业绩没动；第二年开始，跑客户的人明显多了。林薇说：\"以前他们是替我跑，现在是替自己跑。\"", "effects": {"money": -26, "orders": 9, "morale": 4, "aff": {"lin": 5}, "flag": "sales_sys"}}, {"id": "2", "text": "把那三家客户抢回来", "hint": "打一场 · 打赢打输都伤", "result": "林薇亲自跑了两个月，抢回来两家。宏远那边的报价压到了成本线以下，两家厂都没赚到钱。她回来的时候瘦了一圈，说：\"厂长，这种仗赢一次，我少活一年。\"", "effects": {"money": -10, "orders": 6, "rival": -6, "morale": -3, "aff": {"lin": -1}}}, {"id": "3", "text": "不追了，让她重新带人", "hint": "认了 · 也是信任", "result": "你只说了一句\"人走了就走了，你重新带\"。林薇愣了一下。半年后她带出来两个新人，其中一个后来接了她的班。有些事不追究，本身就是一种交代。", "effects": {"orders": -5, "morale": 3, "aff": {"lin": 4}, "flag": "lin_trust"}}] | T75: 人走了，客户跟着走了两家。林薇一个人补了半年的窟窿，从那以后她再没跟你提过团队的事。
A76: GF15_Y11_SUMMER_071 | B76: 副厂长和车间顶上了 | C76: 第11年·夏季 | D76: 100 | E76: 是 | F76: 厂长，副厂长和车间那位在生产会上又杠上了。一个说流程要改，一个说改了车间转不动。这两个人您都用得着，可现在底下人开会得先看谁先说话。 | G76: 0 | H76: 0 | J76: 0 | L76: 是 | M76: 源自 green-factory-15-years 厂长路线；原版条件事件已保留条件文本，当前按年份与季节抽取。 | N76: year_story | O76: 11 | P76: 夏 | Q76: zhao | R76: 老赵 | S76: [{"id": "1", "text": "把两摊事切开，各管各的", "hint": "不吵了 · 也不通气了", "result": "职责重新划了线，会开得顺了。但半年后出了一次交付事故，追下去发现是两边都以为对方在管。〔#zhou〕说：\"厂长，把人分开容易，把事分开难。\"", "effects": {"orders": -4, "morale": 4, "flag": "split_org"}}, {"id": "2", "text": "让他们俩共同负责一个项目，绑在一起", "hint": "逼他们磨合 · 也可能一起搞砸", "result": "那个项目做得磕磕绊绊，延期两个月。但结束之后两个人能一起吃饭了。〔#zhou〕评价：\"厂长这是拿一个项目当学费。\"这笔学费花得值不值，得看后面三年。", "effects": {"orders": -3, "morale": 6, "tech": 5, "flag": "forged_pair"}}, {"id": "3", "text": "明确一个人说了算", "hint": "快刀 · 另一个会走", "result": "你在会上说清楚了谁拍板。效率立刻上来，事故也少了。另一个人年底提了调动，走的时候只说了一句\"厂长，我明白\"。厂里的人也都明白了。", "effects": {"orders": 5, "morale": -7, "group": 2, "flag": "one_boss"}}] | T76: 两个人的事你没有过问。半年后车间那位申请调岗去了后勤，副厂长从此一个人管两摊，什么都亲力亲为，也什么都慢了半拍。 | U76: function(s){ return !!(s.flag.vp_zhou || s.flag.vp_out); }
A77: GF15_Y12_SUMMER_072 | B77: 宏远开始低价倾销 | C77: 第12年·夏季 | D77: 100 | E77: 是 | F77: 宏远今年报价压到了成本以下，几个片区一起压。他们背后有笔新融资，摆明了要先把人耗死。厂长，这一仗打不打？ | G77: 0 | H77: 0 | J77: 0 | L77: 是 | M77: 源自 green-factory-15-years 厂长路线；原版条件事件已保留条件文本，当前按年份与季节抽取。 | N77: year_story | O77: 12 | P77: 夏 | Q77: lin | R77: 林薇 | S77: [{"id": "1", "text": "跟，他们能扛多久我们扛多久", "hint": "硬碰 · 两败俱伤", "result": "两家厂在三个片区打了一年价格战。你守住了份额，账上少了一大截，年终奖砍了一半。宏远也没讨到便宜，但他们背后有钱，你背后是老赵的白头发。", "effects": {"money": -38, "orders": 6, "morale": -8, "rival": -6, "aff": {"zhao": -3}}}, {"id": "2", "text": "不跟，把力气花在他们抢不走的客户上", "hint": "要有底子才敢这么说", "result": "你让林薇把资源全压在几家看资质、看数据、看审核的客户上。那年丢了三成低价单，但保住的那些客户，宏远的报价再低也进不去。林薇说：\"原来我们这些年做的东西，是在这时候用的。\"", "effects": {"orders": 8, "fame": 6, "money": 10, "rival": -4}}, {"id": "3", "text": "退出那三个片区，保住利润", "hint": "止血 · 也是认输", "result": "你主动收缩。账面上比打价格战好看得多，但那三个片区从此没有你们的名字。两年后价格回升，回去的成本比当初守住要高三倍。", "effects": {"orders": -11, "money": 20, "rival": 10, "group": -4}}] | T77: 你没有应对。那一年报价单发出去十七份，回来三份。老赵在年终会上把订单曲线投在墙上，一句话也没说。
A78: GF15_Y13_SUMMER_073 | B78: 有人替你写了封表功信 | C78: 第13年·夏季 | D78: 100 | E78: 是 | F78: 办公室有人给集团写了封信，讲您这些年在绿色上做的事，写得挺动人。信还没发出去，被我压下来了。厂长，这封信，发还是不发？ | G78: 0 | H78: 0 | J78: 0 | L78: 是 | M78: 源自 green-factory-15-years 厂长路线；原版条件事件已保留条件文本，当前按年份与季节抽取。 | N78: year_story | O78: 13 | P78: 夏 | Q78: zhao | R78: 老赵 | S78: [{"id": "1", "text": "不发，做了就是做了", "hint": "干净 · 也可能白做", "result": "信被撕了。老赵说了句：\"厂长，您这样的人，集团一年能看见两三个，但记住的一个都没有。\"这句话你没反驳，因为你知道他说的是实话。", "effects": {"fame": 2, "aff": {"zhao": 3}, "flag": "no_selfpr"}}, {"id": "2", "text": "发，但把名字换成全厂", "hint": "不居功 · 效果打折", "result": "信改成了以厂部名义发的，通篇没提你。集团回了封表扬信，贴在厂里的公告栏上。车间的人第一次觉得这些事跟自己有关系。至于是谁做的，没有人特别在意——包括你。", "effects": {"group": 5, "morale": 7, "fame": 3, "flag": "credit_shared"}}, {"id": "3", "text": "发，原样发", "hint": "争一次 · 有人会不舒服", "result": "信发上去了，集团批了一笔奖励。年会上你被点名表扬。回厂那周，办公室的气氛有点怪，老赵提醒你：\"写信那个人现在到处说这是他的主意。\"", "effects": {"group": 9, "money": 22, "morale": -5, "fame": 4, "report": 1}}] | T78: 信递上去了，你事后才知道。集团有人看了，也有人在私下说"那个厂长挺会来事"。这两种印象后来一直纠缠在一起。
A79: GF15_Y14_SUMMER_074 | B79: 集团要你写一份说明 | C79: 第14年·夏季 | D79: 100 | E79: 是 | F79: 集团在做任期审计。你这十几年在环保和技改上花的钱，要一笔笔说清楚产出。说实话，有些是说不清的——但说不清不等于没用。这份说明，你得自己写。 | G79: 0 | H79: 0 | J79: 0 | L79: 是 | M79: 源自 green-factory-15-years 厂长路线；原版条件事件已保留条件文本，当前按年份与季节抽取。 | N79: year_story | O79: 14 | P79: 夏 | Q79: ma | R79: 马副总 | S79: [{"id": "1", "text": "一笔笔算，能量化的量化，不能的就写不能", "hint": "笨办法 · 也最经得起看", "result": "你写了十九页。有七笔算得出回收期，五笔只能写\"避免了处罚风险，金额无法量化\"。审计组的人后来说，这是他见过唯一一份敢写\"无法量化\"的说明。这份材料后来被集团当成模板发给了别的厂。", "effects": {"group": 11, "fame": 5, "flag": "honest_audit"}}, {"id": "2", "text": "把能算的都往好里算", "hint": "好看 · 但每个数字都要经得起追问", "result": "说明写得很漂亮，回收期一律按最乐观口径。审计组挑了三笔追问，你答得含糊。最后结论是\"投入产出测算依据不足\"——比不写好一点，但只好一点。", "effects": {"group": -3, "risk": 1}}, {"id": "3", "text": "不算钱，只写这些年少出过多少事", "hint": "另辟蹊径 · 赌他们听得懂", "result": "你列了同行这些年的处罚、停产、退单案例，然后写了一句：这些我们一次都没有过。审计组组长在会上念了这一段，有人点头，也有人说\"这不是财务语言\"。结论最后写的是\"管理成效显著，量化依据待完善\"。", "effects": {"group": 5, "fame": 6, "flag": "risk_story"}}] | T79: 说明没写。集团按最不利的口径做了认定，那几年的技改投入被记成了"效益不明确支出"，写进了任期审计。
A80: GF15_Y15_SPRING_075 | B80: 谁来接你的班 | C80: 第15年·春季 | D80: 100 | E80: 是 | F80: 厂长，都传您快调走了。底下人问，接您班的是谁。〔zhou:我今年也快退了，有些话现在不说，以后就没机会说了。|老周退的时候交代过我一句：厂里的事，得有个准话。〕 | G80: 0 | H80: 0 | J80: 0 | L80: 是 | M80: 源自 green-factory-15-years 厂长路线；原版条件事件已保留条件文本，当前按年份与季节抽取。 | N80: year_story | O80: 15 | P80: 春 | Q80: zhou | R80: 老周 | S80: [{"id": "1", "text": "推荐现在管三车间的那位", "hint": "接得住车间 · 未必接得住外面", "result": "你写了推荐信，附了他这些年经手的项目清单。集团批了。交接那天他说：\"厂长，您那套我学了七成，剩下三成我得自己摔。\"", "effects": {"morale": 9, "group": 3, "aff": {"zhou": 4}, "flag": "succ_liu"}}, {"id": "2", "text": "推荐〔陈工|小吴〕", "hint": "接得住方向 · 车间未必服", "result": "你推荐了技术这条线上的人。集团有些犹豫，最后还是批了。〔zhou:老周私下说|他私下说〕：\"厂长，他懂设备，可他不知道半夜三点车间为什么会停。\"这句话你记下了，也没有改主意。", "effects": {"tech": 6, "morale": -5, "group": 2, "aff": {"chen": 6}, "flag": "succ_tech"}}, {"id": "3", "text": "不推荐，让集团自己定", "hint": "不干预 · 也是把厂交出去", "result": "你没有写任何推荐。集团空降了一位年轻干部。你交接了三天，把所有台账、方案本、客户档案交出去，对方很认真地记了笔记。走出厂门那天你想：这厂往后是什么样，已经不归你管了。", "effects": {"group": 2, "morale": -3, "flag": "succ_none"}}] | T80: 接班的事你没有安排。集团直接空降了一位，来的第一天开会讲了四十分钟战略，一句也没提这个厂过去十五年做过什么。
A81: GF15_Y15_SPRING_076 | B81: 最后一个客户问题 | C81: 第15年·春季 | D81: 100 | E81: 是 | F81: 又来了一份问卷，二十六页。比十五年前那份厚了三倍，问的东西具体到每一道工序。厂长，这可能是我替这个厂做的最后一件事了。 | G81: 0 | H81: 0 | J81: 0 | L81: 是 | M81: 源自 green-factory-15-years 厂长路线；原版条件事件已保留条件文本，当前按年份与季节抽取。 | N81: year_story | O81: 15 | P81: 春 | Q81: lin | R81: 林薇 | S81: [{"id": "1", "text": "一栏栏填，填不出的照旧写填不出", "hint": "和十五年前一样的答法", "result": "这一次，二十六页里只有两栏是空的。林薇填完最后一页，把它和十五年前那份复印件订在了一起，放进档案柜最上面那一格。她说：\"厂长，您看，就差这么两栏。\"", "effects": {"orders": 10, "fame": 8, "group": 4, "flag": "last_form"}}, {"id": "2", "text": "交给新人去填，她该歇歇了", "hint": "体面 · 但会差一点", "result": "新人填了三天，有六栏填错，两栏空着。客户回了封邮件要求澄清。林薇看到之后自己重做了一遍，只说了句：\"最后一次了，让我做完。\"", "effects": {"orders": 5, "fame": 3, "aff": {"lin": 3}}}, {"id": "3", "text": "这次找机构代填，别为难人了", "hint": "花 12 万 · 兜了一个圈回到原点", "result": "报告做得很专业。客户来现场核对时问了七个问题，接待的新人答不上来四个。林薇没有说话，只是那天下班走得比谁都早。", "effects": {"money": -12, "orders": 3, "fame": -3, "aff": {"lin": -4}}}] | T81: 那份问卷没有人回。这是十五年前的那一幕，只是这一次，连遗憾都淡了。 | U81: function(s){ return !s.flag.lin_left; }
A82: GF15_Y15_SUMMER_077 | B82: 宏远上市了 | C82: 第15年·夏季 | D82: 100 | E82: 是 | F82: 宏远今年过会了。招股书里绿色制造那一章写了十一页，引用的标准和你这些年做的是同一套。集团那边问：我们厂算不算落后了。 | G82: 0 | H82: 0 | J82: 0 | L82: 是 | M82: 源自 green-factory-15-years 厂长路线；原版条件事件已保留条件文本，当前按年份与季节抽取。 | N82: year_story | O82: 15 | P82: 夏 | Q82: ma | R82: 马副总 | S82: [{"id": "1", "text": "把我们这十五年的东西也整理成一份材料报上去", "hint": "花 18 万 · 东西得是真的", "result": "材料交上去，集团第一次完整看到了这个厂十五年的曲线。有位副总在会上说：\"这家的数据没有一年是断的。\"这句话比任何一份招股书都值钱——虽然它不会写进任何一份招股书。", "effects": {"money": -18, "group": 12, "fame": 8, "orders": 6}}, {"id": "2", "text": "实话说：我们落后，但不是落后在做没做，是落后在说没说", "hint": "坦白 · 集团未必爱听", "result": "你在电话里说了这句话。对面沉默了一会儿，说：\"这话你敢说，说明你心里有底。\"半年后集团请了家咨询公司来给下属厂做品牌梳理，第一站是你们。", "effects": {"group": 6, "fame": 5}}, {"id": "3", "text": "不比了，这十五年不是为了跟谁比", "hint": "放下 · 也可能只是不想面对", "result": "你说厂子挺好的，不用比。〔#zhao〕后来说了句：\"厂长，您这话我信，可集团不信这个。\"那年集团的资源分配里，你们厂还是那个中游偏后的位置。", "effects": {"group": -5, "morale": 4}}] | T82: 招股书你没有细看。倒是〔#zhao〕看完了，在办公室念了一段给你听，念到"绿色制造是我们的核心竞争力"那句时停了两秒，然后合上了。
A83: GF15_Y15_SUMMER_078 | B83: 最后一次盘账 | C83: 第15年·夏季 | D83: 100 | E83: 是 | F83: （他已经办完退休手续，是自己回来的）厂长，我把这十五年的账重新拉了一遍。有些当年我反对的，现在看是对的；有些当年我同意的，现在看是错的。要不要我做一份总账给您？ | G83: 0 | H83: 0 | J83: 0 | L83: 是 | M83: 源自 green-factory-15-years 厂长路线；原版条件事件已保留条件文本，当前按年份与季节抽取。 | N83: year_story | O83: 15 | P83: 夏 | Q83: zhao | R83: 老赵 | S83: [{"id": "1", "text": "做，我想知道这十五年到底花在了哪儿", "hint": "面对", "result": "总账做出来是三十七页。最贵的三笔里，有两笔当年他都反对过。他在最后一页写了一行字：\"本表由赵德海编制，此人曾于第三年、第七年、第十一年三次提出反对意见，事后证明两次是错的。\"", "effects": {"fame": 4, "group": 5, "aff": {"zhao": 5}, "flag": "final_ledger"}}, {"id": "2", "text": "不用了，老赵，回家歇着吧", "hint": "体面收场", "result": "他坐了一会儿就走了。第二个月你收到一个包裹，里面是那三十七页，他还是做完了。附了一张纸条：\"厂长，我做完才睡得着。\"", "effects": {"morale": 3, "aff": {"zhao": 4}}}, {"id": "3", "text": "做，但只做一件事：算算我们少赚了多少", "hint": "残酷 · 但你该知道", "result": "他算出来一个数字：这十五年，为了那些\"当时看不出产出\"的事，你少赚了大约六百八十万。他把纸推过来，又补了一句：\"另外我算了一下，同期倒掉的七家同行，加起来省了不止这个数。\"", "effects": {"fame": 3, "aff": {"zhao": 3}, "flag": "cost_of_clean"}}] | T83: 账最后是新来的会计盘的。那些年的技改台账、罚款记录、客户审核结论，被分门别类装了箱，谁也没有再翻开过。
A84: GF15_Y15_SPRING_079 | B84: 新人拿着一份问卷来问 | C84: 第15年·春季 | D84: 100 | E84: 是 | F84: 厂长，客户发来一份问卷，二十六页。林姐留下的档案里有十五年前那一份，一半是空的。我不知道该照着填，还是该照实填。 | G84: 0 | H84: 0 | J84: 0 | L84: 是 | M84: 源自 green-factory-15-years 厂长路线；原版条件事件已保留条件文本，当前按年份与季节抽取。 | N84: year_story | O84: 15 | P84: 春 | Q84: lin | R84: 林薇 | S84: [{"id": "1", "text": "照实填，填不出的就写填不出", "hint": "和十五年前一样的答法", "result": "这一次，二十六页里只有两栏是空的。你让她把这份和十五年前那份订在一起，放进档案柜最上面那一格。她翻着旧的那份问：\"厂长，这是林姐的字吧？\"你说是。她说：\"她在角上写了两个字，两年。\"", "effects": {"orders": 10, "fame": 8, "group": 4, "flag": "last_form"}}, {"id": "2", "text": "把这十五年的东西都调出来，教她怎么填", "hint": "花你一整周 · 传下去", "result": "你陪着她把台账、监测报告、审核结论一份份翻出来，讲了一周。填完那天她说：\"原来这些不是材料，是这个厂真做过的事。\"这句话你在十五年里听过两次，上一次是林薇说的。", "effects": {"orders": 8, "fame": 6, "morale": 5, "flag": "last_form"}}, {"id": "3", "text": "照着老档案填，别耽误时间", "hint": "快 · 也是回到了原点", "result": "她照着旧材料填完了，格式挑不出毛病。客户来现场核对时问了七个问题，答不上来四个。晚上你路过档案室，看见那两份问卷并排放着——十五年，好像什么都变了，又好像没有。", "effects": {"orders": 2, "fame": -4}}] | T84: 那份问卷没有人回。新人后来说她问过两次，没等到回话，就当这事过去了。这是十五年前的那一幕，只是这一次，连遗憾都淡了。 | U84: function(s){ return !!s.flag.lin_left; }
A85: GF15_Y14_SUMMER_080 | B85: 园区要收回西边那块地 | C85: 第14年·夏季 | D85: 100 | E85: 是 | F85: 园区要收回西边那块地做道路，那是咱们的成品仓和一半停车位。补偿谈得好是笔钱，谈不好是场麻烦。管委会那边等您一句话。 | G85: 0 | H85: 0 | J85: 0 | L85: 是 | M85: 源自 green-factory-15-years 厂长路线；原版条件事件已保留条件文本，当前按年份与季节抽取。 | N85: year_story | O85: 14 | P85: 夏 | Q85: zhao | R85: 老赵 | S85: [{"id": "1", "text": "配合，痛快签，换后面的关系", "hint": "吃点亏 · 换一份长期人情", "result": "你三天就签了，补偿按评估价打了九折。管委会主任在会上点了名：\"这家企业讲大局。\"后来两年，凡是园区的配套指标、用电扩容、危废转运通道，你申请什么批什么。有些便宜是从吃亏里长出来的。", "effects": {"money": -14, "group": 6, "fame": 5, "flag": "yard_deal"}}, {"id": "2", "text": "咬住评估价，一分不让", "hint": "钱到位 · 也把关系耗掉了", "result": "谈了七个月，最后按评估价全额拿到。老赵很高兴。只是那两年凡是需要园区盖章的事，你都得多跑三趟，而且从来没有人给你解释为什么慢。", "effects": {"money": 34, "group": -7, "morale": -3}}, {"id": "3", "text": "不谈钱，谈条件：让他们把管网接到我们墙外", "hint": "不要现钱 · 要一件真正管用的事", "result": "你提出用这块地换园区蒸汽管网和污水专管接到厂界。管委会犹豫了两个月，最后同意了。这笔账当年在报表上是亏的，第二年锅炉和废水两头都省了钱——〔#zhao〕说：\"厂长，您这是拿地换了十年的运行成本。\"", "effects": {"money": -6, "smoke": -6, "risk": -1, "group": 2, "fac": {"boiler": 1}, "flag": "yard_pipe"}}] | T85: 你一直没表态。收地的文件按最不利的方案下来了，补偿是评估价的六成，仓库限期三个月搬空。
A86: GF15_Y15_AUTUMN_081 | B86: 第 15 年秋季事件 | C86: 第15年·秋季 | D86: 100 | E86: 是 | F86: 年底最后一天，厂区安静下来。你从车间一路走到大门口，回头看了一眼那根烟囱。十五年前你第一次站在这儿的时候，它冒的烟比现在浓得多。 | G86: 0 | H86: 0 | J86: 0 | L86: 是 | M86: 源自 green-factory-15-years 厂长路线；原版条件事件已保留条件文本，当前按年份与季节抽取。 | N86: year_story | O86: 15 | P86: 秋 | Q86: narr | R86: 旁白 | S86: [{"id": "1", "text": "（走出厂门）", "hint": "", "result": "", "effects": {}}]

Sheet 经营时间序列
A2: 经营时间序列
A3: 120个月经营数据库。黄色格是可选覆盖值；空白时公式回落到“经营参数”。启用该行并保存 Excel 后，更新工具把计算结果交给游戏。
A5: 启用 | B5: 年月 | C5: 产能_万件年 | D5: 国内销量_万件月 | E5: 国内单价_元件 | F5: 大客户销量_万件月 | G5: 大客户单价_元件 | H5: 出口销量_万件月 | I5: 出口单价_元件 | J5: 材料单位成本_元件 | K5: 变动人工单位成本_元件 | L5: 固定人工_万元月 | M5: 用电量_万kWh月 | N5: 电价_元kWh | O5: 用气量_万m3月 | P5: 气价_元m3 | Q5: 维护费_万元月 | R5: 固定经营费_万元月 | S5: 融资费_万元月 | T5: 所得税率 | U5: 上缴比例 | V5: 经营收入_万元 | W5: 材料成本_万元 | X5: 人工成本_万元 | Y5: 能源成本_万元 | Z5: 经营总成本_万元 | AA5: 所得税_万元 | AB5: 净利润_万元 | AC5: 上缴集团_万元 | AD5: 经营现金流_万元 | AE5: 备注
A6: 否 | B6: 2030-03 | V6: =IF(A6="是",IF(D6="",'经营参数'!$D$47/12,D6)*IF(E6="",'经营参数'!$D$44,E6)+IF(F6="",0,F6)*IF(G6="",'经营参数'!$D$45,G6)+IF(H6="",0,H6)*IF(I6="",'经营参数'!$D$46,I6),"") | W6: =IF(A6="是",(IF(D6="",'经营参数'!$D$47/12,D6)+IF(F6="",0,F6)+IF(H6="",0,H6))*IF(J6="",'经营参数'!$D$20,J6),"") | X6: =IF(A6="是",(IF(D6="",'经营参数'!$D$47/12,D6)+IF(F6="",0,F6)+IF(H6="",0,H6))*IF(K6="",'经营参数'!$D$22,K6)+IF(L6="",'经营参数'!$D$21/12,L6),"") | Y6: =IF(A6="是",IF(M6="",(IF(D6="",'经营参数'!$D$47/12,D6)+IF(F6="",0,F6)+IF(H6="",0,H6))*'经营参数'!$D$51,M6)*IF(N6="",'经营参数'!$D$29,N6)+IF(O6="",(IF(D6="",'经营参数'!$D$47/12,D6)+IF(F6="",0,F6)+IF(H6="",0,H6))*'经营参数'!$D$52,O6)*IF(P6="",'经营参数'!$D$30,P6),"") | Z6: =IF(A6="是",W6+X6+Y6+IF(Q6="",'经营参数'!$D$25/12,Q6)+IF(R6="",'经营参数'!$D$24/12,R6)+IF(S6="",0,S6),"") | AA6: =IF(A6="是",MAX(0,(V6-Z6)*IF(T6="",'经营参数'!$D$26,T6)),"") | AB6: =IF(A6="是",V6-Z6-AA6,"") | AC6: =IF(A6="是",MAX(0,AB6*IF(U6="",'经营参数'!$D$27,U6)),"") | AD6: =IF(A6="是",AB6-AC6,"") | AE6: 黄色格为空时，右侧公式使用经营参数中的基础值；启用后，游戏优先采用本行已计算的结果。
A7: 否 | B7: 2030-04 | V7: =IF(A7="是",IF(D7="",'经营参数'!$D$47/12,D7)*IF(E7="",'经营参数'!$D$44,E7)+IF(F7="",0,F7)*IF(G7="",'经营参数'!$D$45,G7)+IF(H7="",0,H7)*IF(I7="",'经营参数'!$D$46,I7),"") | W7: =IF(A7="是",(IF(D7="",'经营参数'!$D$47/12,D7)+IF(F7="",0,F7)+IF(H7="",0,H7))*IF(J7="",'经营参数'!$D$20,J7),"") | X7: =IF(A7="是",(IF(D7="",'经营参数'!$D$47/12,D7)+IF(F7="",0,F7)+IF(H7="",0,H7))*IF(K7="",'经营参数'!$D$22,K7)+IF(L7="",'经营参数'!$D$21/12,L7),"") | Y7: =IF(A7="是",IF(M7="",(IF(D7="",'经营参数'!$D$47/12,D7)+IF(F7="",0,F7)+IF(H7="",0,H7))*'经营参数'!$D$51,M7)*IF(N7="",'经营参数'!$D$29,N7)+IF(O7="",(IF(D7="",'经营参数'!$D$47/12,D7)+IF(F7="",0,F7)+IF(H7="",0,H7))*'经营参数'!$D$52,O7)*IF(P7="",'经营参数'!$D$30,P7),"") | Z7: =IF(A7="是",W7+X7+Y7+IF(Q7="",'经营参数'!$D$25/12,Q7)+IF(R7="",'经营参数'!$D$24/12,R7)+IF(S7="",0,S7),"") | AA7: =IF(A7="是",MAX(0,(V7-Z7)*IF(T7="",'经营参数'!$D$26,T7)),"") | AB7: =IF(A7="是",V7-Z7-AA7,"") | AC7: =IF(A7="是",MAX(0,AB7*IF(U7="",'经营参数'!$D$27,U7)),"") | AD7: =IF(A7="是",AB7-AC7,"") | AE7: 黄色格为空时，右侧公式使用经营参数中的基础值；启用后，游戏优先采用本行已计算的结果。
A8: 否 | B8: 2030-05 | V8: =IF(A8="是",IF(D8="",'经营参数'!$D$47/12,D8)*IF(E8="",'经营参数'!$D$44,E8)+IF(F8="",0,F8)*IF(G8="",'经营参数'!$D$45,G8)+IF(H8="",0,H8)*IF(I8="",'经营参数'!$D$46,I8),"") | W8: =IF(A8="是",(IF(D8="",'经营参数'!$D$47/12,D8)+IF(F8="",0,F8)+IF(H8="",0,H8))*IF(J8="",'经营参数'!$D$20,J8),"") | X8: =IF(A8="是",(IF(D8="",'经营参数'!$D$47/12,D8)+IF(F8="",0,F8)+IF(H8="",0,H8))*IF(K8="",'经营参数'!$D$22,K8)+IF(L8="",'经营参数'!$D$21/12,L8),"") | Y8: =IF(A8="是",IF(M8="",(IF(D8="",'经营参数'!$D$47/12,D8)+IF(F8="",0,F8)+IF(H8="",0,H8))*'经营参数'!$D$51,M8)*IF(N8="",'经营参数'!$D$29,N8)+IF(O8="",(IF(D8="",'经营参数'!$D$47/12,D8)+IF(F8="",0,F8)+IF(H8="",0,H8))*'经营参数'!$D$52,O8)*IF(P8="",'经营参数'!$D$30,P8),"") | Z8: =IF(A8="是",W8+X8+Y8+IF(Q8="",'经营参数'!$D$25/12,Q8)+IF(R8="",'经营参数'!$D$24/12,R8)+IF(S8="",0,S8),"") | AA8: =IF(A8="是",MAX(0,(V8-Z8)*IF(T8="",'经营参数'!$D$26,T8)),"") | AB8: =IF(A8="是",V8-Z8-AA8,"") | AC8: =IF(A8="是",MAX(0,AB8*IF(U8="",'经营参数'!$D$27,U8)),"") | AD8: =IF(A8="是",AB8-AC8,"") | AE8: 黄色格为空时，右侧公式使用经营参数中的基础值；启用后，游戏优先采用本行已计算的结果。
A9: 否 | B9: 2030-06 | V9: =IF(A9="是",IF(D9="",'经营参数'!$D$47/12,D9)*IF(E9="",'经营参数'!$D$44,E9)+IF(F9="",0,F9)*IF(G9="",'经营参数'!$D$45,G9)+IF(H9="",0,H9)*IF(I9="",'经营参数'!$D$46,I9),"") | W9: =IF(A9="是",(IF(D9="",'经营参数'!$D$47/12,D9)+IF(F9="",0,F9)+IF(H9="",0,H9))*IF(J9="",'经营参数'!$D$20,J9),"") | X9: =IF(A9="是",(IF(D9="",'经营参数'!$D$47/12,D9)+IF(F9="",0,F9)+IF(H9="",0,H9))*IF(K9="",'经营参数'!$D$22,K9)+IF(L9="",'经营参数'!$D$21/12,L9),"") | Y9: =IF(A9="是",IF(M9="",(IF(D9="",'经营参数'!$D$47/12,D9)+IF(F9="",0,F9)+IF(H9="",0,H9))*'经营参数'!$D$51,M9)*IF(N9="",'经营参数'!$D$29,N9)+IF(O9="",(IF(D9="",'经营参数'!$D$47/12,D9)+IF(F9="",0,F9)+IF(H9="",0,H9))*'经营参数'!$D$52,O9)*IF(P9="",'经营参数'!$D$30,P9),"") | Z9: =IF(A9="是",W9+X9+Y9+IF(Q9="",'经营参数'!$D$25/12,Q9)+IF(R9="",'经营参数'!$D$24/12,R9)+IF(S9="",0,S9),"") | AA9: =IF(A9="是",MAX(0,(V9-Z9)*IF(T9="",'经营参数'!$D$26,T9)),"") | AB9: =IF(A9="是",V9-Z9-AA9,"") | AC9: =IF(A9="是",MAX(0,AB9*IF(U9="",'经营参数'!$D$27,U9)),"") | AD9: =IF(A9="是",AB9-AC9,"") | AE9: 黄色格为空时，右侧公式使用经营参数中的基础值；启用后，游戏优先采用本行已计算的结果。
A10: 否 | B10: 2030-07 | V10: =IF(A10="是",IF(D10="",'经营参数'!$D$47/12,D10)*IF(E10="",'经营参数'!$D$44,E10)+IF(F10="",0,F10)*IF(G10="",'经营参数'!$D$45,G10)+IF(H10="",0,H10)*IF(I10="",'经营参数'!$D$46,I10),"") | W10: =IF(A10="是",(IF(D10="",'经营参数'!$D$47/12,D10)+IF(F10="",0,F10)+IF(H10="",0,H10))*IF(J10="",'经营参数'!$D$20,J10),"") | X10: =IF(A10="是",(IF(D10="",'经营参数'!$D$47/12,D10)+IF(F10="",0,F10)+IF(H10="",0,H10))*IF(K10="",'经营参数'!$D$22,K10)+IF(L10="",'经营参数'!$D$21/12,L10),"") | Y10: =IF(A10="是",IF(M10="",(IF(D10="",'经营参数'!$D$47/12,D10)+IF(F10="",0,F10)+IF(H10="",0,H10))*'经营参数'!$D$51,M10)*IF(N10="",'经营参数'!$D$29,N10)+IF(O10="",(IF(D10="",'经营参数'!$D$47/12,D10)+IF(F10="",0,F10)+IF(H10="",0,H10))*'经营参数'!$D$52,O10)*IF(P10="",'经营参数'!$D$30,P10),"") | Z10: =IF(A10="是",W10+X10+Y10+IF(Q10="",'经营参数'!$D$25/12,Q10)+IF(R10="",'经营参数'!$D$24/12,R10)+IF(S10="",0,S10),"") | AA10: =IF(A10="是",MAX(0,(V10-Z10)*IF(T10="",'经营参数'!$D$26,T10)),"") | AB10: =IF(A10="是",V10-Z10-AA10,"") | AC10: =IF(A10="是",MAX(0,AB10*IF(U10="",'经营参数'!$D$27,U10)),"") | AD10: =IF(A10="是",AB10-AC10,"") | AE10: 黄色格为空时，右侧公式使用经营参数中的基础值；启用后，游戏优先采用本行已计算的结果。
A11: 否 | B11: 2030-08 | V11: =IF(A11="是",IF(D11="",'经营参数'!$D$47/12,D11)*IF(E11="",'经营参数'!$D$44,E11)+IF(F11="",0,F11)*IF(G11="",'经营参数'!$D$45,G11)+IF(H11="",0,H11)*IF(I11="",'经营参数'!$D$46,I11),"") | W11: =IF(A11="是",(IF(D11="",'经营参数'!$D$47/12,D11)+IF(F11="",0,F11)+IF(H11="",0,H11))*IF(J11="",'经营参数'!$D$20,J11),"") | X11: =IF(A11="是",(IF(D11="",'经营参数'!$D$47/12,D11)+IF(F11="",0,F11)+IF(H11="",0,H11))*IF(K11="",'经营参数'!$D$22,K11)+IF(L11="",'经营参数'!$D$21/12,L11),"") | Y11: =IF(A11="是",IF(M11="",(IF(D11="",'经营参数'!$D$47/12,D11)+IF(F11="",0,F11)+IF(H11="",0,H11))*'经营参数'!$D$51,M11)*IF(N11="",'经营参数'!$D$29,N11)+IF(O11="",(IF(D11="",'经营参数'!$D$47/12,D11)+IF(F11="",0,F11)+IF(H11="",0,H11))*'经营参数'!$D$52,O11)*IF(P11="",'经营参数'!$D$30,P11),"") | Z11: =IF(A11="是",W11+X11+Y11+IF(Q11="",'经营参数'!$D$25/12,Q11)+IF(R11="",'经营参数'!$D$24/12,R11)+IF(S11="",0,S11),"") | AA11: =IF(A11="是",MAX(0,(V11-Z11)*IF(T11="",'经营参数'!$D$26,T11)),"") | AB11: =IF(A11="是",V11-Z11-AA11,"") | AC11: =IF(A11="是",MAX(0,AB11*IF(U11="",'经营参数'!$D$27,U11)),"") | AD11: =IF(A11="是",AB11-AC11,"") | AE11: 黄色格为空时，右侧公式使用经营参数中的基础值；启用后，游戏优先采用本行已计算的结果。
A12: 否 | B12: 2030-09 | V12: =IF(A12="是",IF(D12="",'经营参数'!$D$47/12,D12)*IF(E12="",'经营参数'!$D$44,E12)+IF(F12="",0,F12)*IF(G12="",'经营参数'!$D$45,G12)+IF(H12="",0,H12)*IF(I12="",'经营参数'!$D$46,I12),"") | W12: =IF(A12="是",(IF(D12="",'经营参数'!$D$47/12,D12)+IF(F12="",0,F12)+IF(H12="",0,H12))*IF(J12="",'经营参数'!$D$20,J12),"") | X12: =IF(A12="是",(IF(D12="",'经营参数'!$D$47/12,D12)+IF(F12="",0,F12)+IF(H12="",0,H12))*IF(K12="",'经营参数'!$D$22,K12)+IF(L12="",'经营参数'!$D$21/12,L12),"") | Y12: =IF(A12="是",IF(M12="",(IF(D12="",'经营参数'!$D$47/12,D12)+IF(F12="",0,F12)+IF(H12="",0,H12))*'经营参数'!$D$51,M12)*IF(N12="",'经营参数'!$D$29,N12)+IF(O12="",(IF(D12="",'经营参数'!$D$47/12,D12)+IF(F12="",0,F12)+IF(H12="",0,H12))*'经营参数'!$D$52,O12)*IF(P12="",'经营参数'!$D$30,P12),"") | Z12: =IF(A12="是",W12+X12+Y12+IF(Q12="",'经营参数'!$D$25/12,Q12)+IF(R12="",'经营参数'!$D$24/12,R12)+IF(S12="",0,S12),"") | AA12: =IF(A12="是",MAX(0,(V12-Z12)*IF(T12="",'经营参数'!$D$26,T12)),"") | AB12: =IF(A12="是",V12-Z12-AA12,"") | AC12: =IF(A12="是",MAX(0,AB12*IF(U12="",'经营参数'!$D$27,U12)),"") | AD12: =IF(A12="是",AB12-AC12,"") | AE12: 黄色格为空时，右侧公式使用经营参数中的基础值；启用后，游戏优先采用本行已计算的结果。
A13: 否 | B13: 2030-10 | V13: =IF(A13="是",IF(D13="",'经营参数'!$D$47/12,D13)*IF(E13="",'经营参数'!$D$44,E13)+IF(F13="",0,F13)*IF(G13="",'经营参数'!$D$45,G13)+IF(H13="",0,H13)*IF(I13="",'经营参数'!$D$46,I13),"") | W13: =IF(A13="是",(IF(D13="",'经营参数'!$D$47/12,D13)+IF(F13="",0,F13)+IF(H13="",0,H13))*IF(J13="",'经营参数'!$D$20,J13),"") | X13: =IF(A13="是",(IF(D13="",'经营参数'!$D$47/12,D13)+IF(F13="",0,F13)+IF(H13="",0,H13))*IF(K13="",'经营参数'!$D$22,K13)+IF(L13="",'经营参数'!$D$21/12,L13),"") | Y13: =IF(A13="是",IF(M13="",(IF(D13="",'经营参数'!$D$47/12,D13)+IF(F13="",0,F13)+IF(H13="",0,H13))*'经营参数'!$D$51,M13)*IF(N13="",'经营参数'!$D$29,N13)+IF(O13="",(IF(D13="",'经营参数'!$D$47/12,D13)+IF(F13="",0,F13)+IF(H13="",0,H13))*'经营参数'!$D$52,O13)*IF(P13="",'经营参数'!$D$30,P13),"") | Z13: =IF(A13="是",W13+X13+Y13+IF(Q13="",'经营参数'!$D$25/12,Q13)+IF(R13="",'经营参数'!$D$24/12,R13)+IF(S13="",0,S13),"") | AA13: =IF(A13="是",MAX(0,(V13-Z13)*IF(T13="",'经营参数'!$D$26,T13)),"") | AB13: =IF(A13="是",V13-Z13-AA13,"") | AC13: =IF(A13="是",MAX(0,AB13*IF(U13="",'经营参数'!$D$27,U13)),"") | AD13: =IF(A13="是",AB13-AC13,"") | AE13: 黄色格为空时，右侧公式使用经营参数中的基础值；启用后，游戏优先采用本行已计算的结果。
A14: 否 | B14: 2030-11 | V14: =IF(A14="是",IF(D14="",'经营参数'!$D$47/12,D14)*IF(E14="",'经营参数'!$D$44,E14)+IF(F14="",0,F14)*IF(G14="",'经营参数'!$D$45,G14)+IF(H14="",0,H14)*IF(I14="",'经营参数'!$D$46,I14),"") | W14: =IF(A14="是",(IF(D14="",'经营参数'!$D$47/12,D14)+IF(F14="",0,F14)+IF(H14="",0,H14))*IF(J14="",'经营参数'!$D$20,J14),"") | X14: =IF(A14="是",(IF(D14="",'经营参数'!$D$47/12,D14)+IF(F14="",0,F14)+IF(H14="",0,H14))*IF(K14="",'经营参数'!$D$22,K14)+IF(L14="",'经营参数'!$D$21/12,L14),"") | Y14: =IF(A14="是",IF(M14="",(IF(D14="",'经营参数'!$D$47/12,D14)+IF(F14="",0,F14)+IF(H14="",0,H14))*'经营参数'!$D$51,M14)*IF(N14="",'经营参数'!$D$29,N14)+IF(O14="",(IF(D14="",'经营参数'!$D$47/12,D14)+IF(F14="",0,F14)+IF(H14="",0,H14))*'经营参数'!$D$52,O14)*IF(P14="",'经营参数'!$D$30,P14),"") | Z14: =IF(A14="是",W14+X14+Y14+IF(Q14="",'经营参数'!$D$25/12,Q14)+IF(R14="",'经营参数'!$D$24/12,R14)+IF(S14="",0,S14),"") | AA14: =IF(A14="是",MAX(0,(V14-Z14)*IF(T14="",'经营参数'!$D$26,T14)),"") | AB14: =IF(A14="是",V14-Z14-AA14,"") | AC14: =IF(A14="是",MAX(0,AB14*IF(U14="",'经营参数'!$D$27,U14)),"") | AD14: =IF(A14="是",AB14-AC14,"") | AE14: 黄色格为空时，右侧公式使用经营参数中的基础值；启用后，游戏优先采用本行已计算的结果。
A15: 否 | B15: 2030-12 | V15: =IF(A15="是",IF(D15="",'经营参数'!$D$47/12,D15)*IF(E15="",'经营参数'!$D$44,E15)+IF(F15="",0,F15)*IF(G15="",'经营参数'!$D$45,G15)+IF(H15="",0,H15)*IF(I15="",'经营参数'!$D$46,I15),"") | W15: =IF(A15="是",(IF(D15="",'经营参数'!$D$47/12,D15)+IF(F15="",0,F15)+IF(H15="",0,H15))*IF(J15="",'经营参数'!$D$20,J15),"") | X15: =IF(A15="是",(IF(D15="",'经营参数'!$D$47/12,D15)+IF(F15="",0,F15)+IF(H15="",0,H15))*IF(K15="",'经营参数'!$D$22,K15)+IF(L15="",'经营参数'!$D$21/12,L15),"") | Y15: =IF(A15="是",IF(M15="",(IF(D15="",'经营参数'!$D$47/12,D15)+IF(F15="",0,F15)+IF(H15="",0,H15))*'经营参数'!$D$51,M15)*IF(N15="",'经营参数'!$D$29,N15)+IF(O15="",(IF(D15="",'经营参数'!$D$47/12,D15)+IF(F15="",0,F15)+IF(H15="",0,H15))*'经营参数'!$D$52,O15)*IF(P15="",'经营参数'!$D$30,P15),"") | Z15: =IF(A15="是",W15+X15+Y15+IF(Q15="",'经营参数'!$D$25/12,Q15)+IF(R15="",'经营参数'!$D$24/12,R15)+IF(S15="",0,S15),"") | AA15: =IF(A15="是",MAX(0,(V15-Z15)*IF(T15="",'经营参数'!$D$26,T15)),"") | AB15: =IF(A15="是",V15-Z15-AA15,"") | AC15: =IF(A15="是",MAX(0,AB15*IF(U15="",'经营参数'!$D$27,U15)),"") | AD15: =IF(A15="是",AB15-AC15,"") | AE15: 黄色格为空时，右侧公式使用经营参数中的基础值；启用后，游戏优先采用本行已计算的结果。
A16: 否 | B16: 2031-01 | V16: =IF(A16="是",IF(D16="",'经营参数'!$D$47/12,D16)*IF(E16="",'经营参数'!$D$44,E16)+IF(F16="",0,F16)*IF(G16="",'经营参数'!$D$45,G16)+IF(H16="",0,H16)*IF(I16="",'经营参数'!$D$46,I16),"") | W16: =IF(A16="是",(IF(D16="",'经营参数'!$D$47/12,D16)+IF(F16="",0,F16)+IF(H16="",0,H16))*IF(J16="",'经营参数'!$D$20,J16),"") | X16: =IF(A16="是",(IF(D16="",'经营参数'!$D$47/12,D16)+IF(F16="",0,F16)+IF(H16="",0,H16))*IF(K16="",'经营参数'!$D$22,K16)+IF(L16="",'经营参数'!$D$21/12,L16),"") | Y16: =IF(A16="是",IF(M16="",(IF(D16="",'经营参数'!$D$47/12,D16)+IF(F16="",0,F16)+IF(H16="",0,H16))*'经营参数'!$D$51,M16)*IF(N16="",'经营参数'!$D$29,N16)+IF(O16="",(IF(D16="",'经营参数'!$D$47/12,D16)+IF(F16="",0,F16)+IF(H16="",0,H16))*'经营参数'!$D$52,O16)*IF(P16="",'经营参数'!$D$30,P16),"") | Z16: =IF(A16="是",W16+X16+Y16+IF(Q16="",'经营参数'!$D$25/12,Q16)+IF(R16="",'经营参数'!$D$24/12,R16)+IF(S16="",0,S16),"") | AA16: =IF(A16="是",MAX(0,(V16-Z16)*IF(T16="",'经营参数'!$D$26,T16)),"") | AB16: =IF(A16="是",V16-Z16-AA16,"") | AC16: =IF(A16="是",MAX(0,AB16*IF(U16="",'经营参数'!$D$27,U16)),"") | AD16: =IF(A16="是",AB16-AC16,"") | AE16: 黄色格为空时，右侧公式使用经营参数中的基础值；启用后，游戏优先采用本行已计算的结果。
A17: 否 | B17: 2031-02 | V17: =IF(A17="是",IF(D17="",'经营参数'!$D$47/12,D17)*IF(E17="",'经营参数'!$D$44,E17)+IF(F17="",0,F17)*IF(G17="",'经营参数'!$D$45,G17)+IF(H17="",0,H17)*IF(I17="",'经营参数'!$D$46,I17),"") | W17: =IF(A17="是",(IF(D17="",'经营参数'!$D$47/12,D17)+IF(F17="",0,F17)+IF(H17="",0,H17))*IF(J17="",'经营参数'!$D$20,J17),"") | X17: =IF(A17="是",(IF(D17="",'经营参数'!$D$47/12,D17)+IF(F17="",0,F17)+IF(H17="",0,H17))*IF(K17="",'经营参数'!$D$22,K17)+IF(L17="",'经营参数'!$D$21/12,L17),"") | Y17: =IF(A17="是",IF(M17="",(IF(D17="",'经营参数'!$D$47/12,D17)+IF(F17="",0,F17)+IF(H17="",0,H17))*'经营参数'!$D$51,M17)*IF(N17="",'经营参数'!$D$29,N17)+IF(O17="",(IF(D17="",'经营参数'!$D$47/12,D17)+IF(F17="",0,F17)+IF(H17="",0,H17))*'经营参数'!$D$52,O17)*IF(P17="",'经营参数'!$D$30,P17),"") | Z17: =IF(A17="是",W17+X17+Y17+IF(Q17="",'经营参数'!$D$25/12,Q17)+IF(R17="",'经营参数'!$D$24/12,R17)+IF(S17="",0,S17),"") | AA17: =IF(A17="是",MAX(0,(V17-Z17)*IF(T17="",'经营参数'!$D$26,T17)),"") | AB17: =IF(A17="是",V17-Z17-AA17,"") | AC17: =IF(A17="是",MAX(0,AB17*IF(U17="",'经营参数'!$D$27,U17)),"") | AD17: =IF(A17="是",AB17-AC17,"") | AE17: 黄色格为空时，右侧公式使用经营参数中的基础值；启用后，游戏优先采用本行已计算的结果。
... A125: 否 | B125: 2040-02 | V125: =IF(A125="是",IF(D125="",'经营参数'!$D$47/12,D125)*IF(E125="",'经营参数'!$D$44,E125)+IF(F125="",0,F125)*IF(G125="",'经营参数'!$D$45,G125)+IF(H125="",0,H125)*IF(I125="",'经营参数'!$D$46,I125),"") | W125: =IF(A125="是",(IF(D125="",'经营参数'!$D$47/12,D125)+IF(F125="",0,F125)+IF(H125="",0,H125))*IF(J125="",'经营参数'!$D$20,J125),"") | X125: =IF(A125="是",(IF(D125="",'经营参数'!$D$47/12,D125)+IF(F125="",0,F125)+IF(H125="",0,H125))*IF(K125="",'经营参数'!$D$22,K125)+IF(L125="",'经营参数'!$D$21/12,L125),"") | Y125: =IF(A125="是",IF(M125="",(IF(D125="",'经营参数'!$D$47/12,D125)+IF(F125="",0,F125)+IF(H125="",0,H125))*'经营参数'!$D$51,M125)*IF(N125="",'经营参数'!$D$29,N125)+IF(O125="",(IF(D125="",'经营参数'!$D$47/12,D125)+IF(F125="",0,F125)+IF(H125="",0,H125))*'经营参数'!$D$52,O125)*IF(P125="",'经营参数'!$D$30,P125),"") | Z125: =IF(A125="是",W125+X125+Y125+IF(Q125="",'经营参数'!$D$25/12,Q125)+IF(R125="",'经营参数'!$D$24/12,R125)+IF(S125="",0,S125),"") | AA125: =IF(A125="是",MAX(0,(V125-Z125)*IF(T125="",'经营参数'!$D$26,T125)),"") | AB125: =IF(A125="是",V125-Z125-AA125,"") | AC125: =IF(A125="是",MAX(0,AB125*IF(U125="",'经营参数'!$D$27,U125)),"") | AD125: =IF(A125="是",AB125-AC125,"") | AE125: 黄色格为空时，右侧公式使用经营参数中的基础值；启用后，游戏优先采用本行已计算的结果。

Sheet 公式规则
A2: 公式规则
A3: 锁定的公式字典，用于说明 Excel 与新 HTML 采用的共同计算口径；黄色输入区不在本页。
A5: 规则ID | B5: 规则名称 | C5: 计算表达式 | D5: 游戏字段 | E5: 单位 | F5: 说明 | G5: 公式版本
A6: F01 | B6: 月度经营收入 | C6: 国内销量×国内单价＋大客户销量×大客户单价＋出口销量×出口单价 | D6: rev | E6: 万元/月 | F6: 启用月度行时由经营时间序列 V 列计算；未启用时由游戏按同口径动态计算 | G6: GF-OPERATING-1
A7: F02 | B7: 材料成本 | C7: 总销量×材料单位成本×项目修正系数 | D7: mat | E7: 万元/月 | F7: 材料节约项目在游戏动态经营公式中生效 | G7: GF-OPERATING-1
A8: F03 | B8: 人工成本 | C8: 固定人工÷12＋总销量×变动人工单位成本＋招聘人数×年薪÷12 | D8: lab | E8: 万元/月 | F8: 自动化与通胀修正在游戏动态经营公式中生效 | G8: GF-OPERATING-1
A9: F04 | B9: 能源成本 | C9: 购电量×电价＋用气量×气价＋绿电/绿证溢价－余电收益－储能收益 | D9: eng | E9: 万元/月 | F9: 月度覆盖表展示基础电气成本；完整项目修正由游戏动态公式计算 | G9: GF-OPERATING-1
A10: F05 | B10: 维护成本 | C10: 基础维护费÷12 | D10: mnt | E10: 万元/月 | F10: 未覆盖时由游戏动态计算 | G10: GF-OPERATING-1
A11: F06 | B11: 经营总成本 | C11: 材料＋人工＋能源＋维护＋固定经营费＋融资费 | D11: cost | E11: 万元/月 | F11: 不含项目施工支出 | G11: GF-OPERATING-1
A12: F07 | B12: 所得税 | C12: MAX(0,(经营收入－经营总成本)×所得税率) | D12: tax | E12: 万元/月 | F12: 亏损月份不计所得税 | G12: GF-OPERATING-1
A13: F08 | B13: 净利润 | C13: 经营收入－经营总成本－所得税 | D13: net | E13: 万元/月 | F13: 项目施工支出单列，不在本式中重复扣除 | G13: GF-OPERATING-1
A14: F09 | B14: 上缴集团 | C14: MAX(0,净利润×上缴比例) | D14: payout | E14: 万元/月 | F14: 亏损月份不上缴 | G14: GF-OPERATING-1
A15: F10 | B15: 经营现金流 | C15: 净利润－上缴集团 | D15: keep | E15: 万元/月 | F15: 每月计入现金；项目施工款另行扣减 | G15: GF-OPERATING-1
A16: F11 | B16: 项目月度施工款 | C16: 项目总成本÷实际完成月数 | D16: projectPayment | E16: 万元/月 | F16: 项目卡直接维护基础完成月数；招聘后按团队能力缩短 | G16: GF-PROJECT-3
... A20: F15 | B20: 绿色信贷本金余额 | C20: 上月本金余额－绿色信贷本金÷(贷款年限×12) | D20: loanBalance | E20: 万元 | F20: 有欠款时逐月减少；每月还本付息另计入融资费用 | G20: GF-OPERATING-1

Sheet CG配置
A2: CG配置
A3: 填写说明：A—E列为触发结构；F—N列为可编辑内容。完整文案、触发条件和CG图片文件名均由本页统一管理；图片放入 cg/images/ 后运行管理员更新工具。
A5: CG_ID | B5: 分类 | C5: 人物ID | D5: 人物名称 | E5: 解锁阈值 | F5: CG标题 | G5: 触发条件 | H5: 画面说明 | I5: 剧情正文 | J5: 图鉴文字 | K5: 分支替换文案 | L5: 图片文件名 | M5: 启用 | N5: 素材备注
A6: S01 | B6: 序章 | E6: 0 | F6: 上任第一天 | G6: 首次开始新游戏 | H6: 2030年的工业园区、集团办公室与传统制造工厂依次出现，最后切换至厂长办公室。 | I6: 2030年。 这一年，中国迎来了碳达峰目标的重要时间节点。 从节能降碳到资源循环，从生产工艺到产品全生命周期，绿色转型正逐渐成为制造业竞争的重要议题。 越来越多的客户开始关注供应商的环境表现。企业不仅要把产品做好，还要回答一个新的问题： 工厂如何在经营发展的同时，走上低碳转型之路？ 但对于许多传统制造企业来说，改变并没有那么容易。 2030年1月。 你今年32岁，在制造业工作了近十年。 今天，你收到集团的一份任命书。 从现在开始，你就是这座工厂的新任厂长。 过去，你只需要做好自己负责的工作。 而现在，生产、订单、成本、人员，以及工厂未来的发展，都需要你来决定。 这是一座经营了多年的传统制造工厂。 订单还算稳定，也有一些利润。但设备逐渐老化，能源和原材料成本不断上涨，能够用于改造的资金并不宽裕。 更重要的是，外面的世界正在变化。 客户开始提出新的绿色采购要求，同行陆续开展节能降碳改造，集团希望工厂继续增长，却又不愿承担过高的投资风险。 是优先扩大生产，还是更新设备？是先改善利润，还是提前布局绿色转型？ 未来十年，这座工厂会变成什么样子？ 2030年1月。 你的第一天，开始了。 【开始经营】 | J6: 十年的经营，从上任第一天开始。 | L6: S01_上任第一天.png | M6: 是 | N6: 序章可使用多张分镜；当前图片文件名为首张CG占位。图片暂未制作。
A7: A01 | B7: 人物关系 | C7: chen_engineer | D7: 陈工 | E7: 60 | F7: 陈工：画到一半的图 | G7: 陈工达到第一阶段好感度。 | H7: 傍晚的技术办公室，桌上摊着工程图纸，陈工正用铅笔在纸上修改细节。夕阳照在散落的尺子和笔记本上。 | I7: 你来技术办公室找陈工，发现桌上放着一本画满了草图的旧笔记本。有设备结构，也有厂房、树木和办公室窗外的景色。 “都是等设备跑数据的时候随手画的。”陈工有点不好意思地把本子合上。 你这才知道，原来陈工除了喜欢研究机器，还挺喜欢画画。 | J7: 有些人眼中的工厂，不只有机器和图纸。 | L7: A01_陈工_画到一半的图.png | M7: 是 | N7: 图片暂未制作；完成后放入 cg/images/，文件名与本行一致。
A8: A02 | B8: 人物关系 | C8: chen_engineer | D8: 陈工 | E8: 100 | F8: 陈工：没画完的那一页 | G8: 陈工达到第二阶段好感度，且已经解锁A01。 | H8: 陈工和厂长站在办公室窗前，桌上摆着一本翻开的画册。画册记录了不同年份的工厂景象。 | I8: 陈工把那本旧笔记本拿给你看，里面多了许多这几年画下的厂区景色。 你从第一页翻到最后一页，发现办公楼前的树长高了，仓库换过屋顶，就连门卫室的样子也有些不同。 最后一页只画了一半。 “还没画完呢。”陈工笑了笑，“以后还会变的，留点地方。” | J8: 故事还没画完，工厂也一样。 | L8: A02_陈工_没画完的那一页.png | M8: 是 | N8: 图片暂未制作；完成后放入 cg/images/，文件名与本行一致。
A9: A03 | B9: 人物关系 | C9: liu_master | D9: 刘师傅 | E9: 60 | F9: 刘师傅：窗台上的橘子 | G9: 刘师傅达到第一阶段好感度。 | H9: 车间休息室，午后的阳光落在窗台上，两个人坐在旧桌旁剥橘子，桌上放着保温杯。 | I9: 你路过休息室时，刘师傅招呼你坐下，从袋子里拿出两个橘子。 “家里买多了，帮忙解决一下。” 你们聊了一会儿设备、天气，还有厂区附近那家新开的面馆。 快离开时，刘师傅又往你手里塞了一个：“这个也带着，别浪费。” | J9: 有些关心，不过是顺手多拿了一个橘子。 | L9: A03_刘师傅_窗台上的橘子.png | M9: 是 | N9: 图片暂未制作；完成后放入 cg/images/，文件名与本行一致。
A10: A04 | B10: 人物关系 | C10: liu_master | D10: 刘师傅 | E10: 100 | F10: 刘师傅：照片背面 | G10: 刘师傅达到第二阶段好感度，且已经解锁A03。 | H10: 刘师傅在休息室拿着一张旧合照，照片里是年轻时的员工们。厂长坐在一旁，桌面上摊着几张不同年代的照片。 | I10: 刘师傅翻出一张许多年前的车间合照，让你猜哪个是年轻时的自己。 你猜了三次都没猜对，他笑得连眼角都皱了起来。 照片背面写着日期，还有几个人的名字。 “有的人早就不在这儿干了。”刘师傅用手指轻轻压平照片的一角，“不过那时候的事，现在想起来还是挺清楚的。” | J10: 照片会慢慢泛黄，记忆却总能找到回来的路。 | L10: A04_刘师傅_照片背面.png | M10: 是 | N10: 图片暂未制作；完成后放入 cg/images/，文件名与本行一致。
A11: A05 | B11: 人物关系 | C11: lin_manager | D11: 林经理 | E11: 60 | F11: 林经理：不在报表上的数字 | G11: 林经理达到第一阶段好感度。 | H11: 傍晚的财务办公室，电脑屏幕已经熄灭，林经理正用便利贴折一只小小的纸鹤，旁边放着计算器和半杯水。 | I11: 你发现林经理办公桌的一角摆着几只用废便签纸折成的小纸鹤。 她说，每次遇到特别难处理的账，就会在休息时折一只，换换脑子。 你数了数桌上的纸鹤，问她是不是最近工作特别辛苦。 “也没有。”她停顿了一下，“有些是以前留下来的。” | J11: 报表之外，也有一些不需要计算的事情。 | L11: A05_林经理_不在报表上的数字.png | M11: 是 | N11: 图片暂未制作；完成后放入 cg/images/，文件名与本行一致。
A12: A06 | B12: 人物关系 | C12: lin_manager | D12: 林经理 | E12: 100 | F12: 林经理：难得不算账 | G12: 林经理达到第二阶段好感度，且已经解锁A05。 | H12: 周末的城市公园，林经理穿着休闲服坐在长椅上，手里拿着一本书。厂长在旁边，远处有人遛狗、散步。 | I12: 周末，你在公园里偶遇了林经理。没有电脑，没有报表，她正坐在长椅上看书。 你开玩笑问她，是不是连周末出来玩也要算一算时间成本。 她合上书，认真想了两秒：“今天不算。” 你们在公园里坐了一会儿，聊了许多与工厂无关的事。 | J12: 偶尔不必计算得失，也是生活的一部分。 | L12: A06_林经理_难得不算账.png | M12: 是 | N12: 图片暂未制作；完成后放入 cg/images/，文件名与本行一致。
A13: A07 | B13: 人物关系 | C13: shao_director | D13: 邵总监 | E13: 60 | F13: 邵总监：没带公文包的人 | G13: 邵总监达到第一阶段好感度。 | H13: 普通书店的一角，邵总监穿着休闲外套，站在书架前翻书。厂长刚好从另一侧书架经过。 | I13: 你在书店里意外碰见了邵总监。 平时总是西装笔挺、带着公文包的他，今天穿了一件普通夹克，手里拿着一本旧版的小说。 你们一时都有些不习惯在工作场合之外见到对方。 “别愣着了。”他笑着说，“今天不用叫我邵总监。” | J13: 离开会议室以后，每个人也有自己的生活。 | L13: A07_邵总监_没带公文包的人.png | M13: 是 | N13: 图片暂未制作；完成后放入 cg/images/，文件名与本行一致。
A14: A08 | B14: 人物关系 | C14: shao_director | D14: 邵总监 | E14: 100 | F14: 邵总监：那张旧名片 | G14: 邵总监达到第二阶段好感度，且已经解锁A07。 | H14: 安静的咖啡馆，桌上放着一张磨旧的名片。窗外行人经过，两人坐在窗边聊天。 | I14: 邵总监从钱包里拿出一张很旧的名片，上面的职位和现在完全不同。 他说，那是自己刚开始负责工厂业务时印的，后来换了好几次岗位，却一直没舍得扔。 “那时候也不知道自己能干多久。”他把名片翻过来，又收回钱包里。 你忽然发现，原来那些看起来经验丰富的人，也都曾经是第一次担任某个职位。 | J14: 所谓经验，不过是许多个第一次留下来的痕迹。 | L14: A08_邵总监_那张旧名片.png | M14: 是 | N14: 图片暂未制作；完成后放入 cg/images/，文件名与本行一致。
A15: A09 | B15: 人物关系 | C15: qi_supervisor | D15: 祁主管 | E15: 60 | F15: 祁主管：通话结束之后 | G15: 祁主管达到第一阶段好感度。 | H15: 办公楼走廊尽头，祁主管坐在窗边台阶上，手机放在旁边，窗外是傍晚的工业园区。 | I15: 你看见祁主管一个人坐在走廊尽头，难得没有打电话。 他刚和客户结束一场漫长的沟通，正望着窗外发呆。 “别担心，我没事。”看见你过来，他笑着摆摆手，“就是想享受一下手机不响的这五分钟。” 你坐下来陪了他一会儿，谁也没有提工作的事。 | J15: 有时候，最好的陪伴是一起安静五分钟。 | L15: A09_祁主管_通话结束之后.png | M15: 是 | N15: 图片暂未制作；完成后放入 cg/images/，文件名与本行一致。
A16: A10 | B16: 人物关系 | C16: qi_supervisor | D16: 祁主管 | E16: 100 | F16: 祁主管：没有目的地的周末 | G16: 祁主管达到第二阶段好感度，且已经解锁A09。 | H16: 郊外的普通公路旁，祁主管背着相机，厂长站在旁边。远处是田野和树木，天空明亮。 | I16: 祁主管邀请你去郊外走走，说自己难得有个不用赶行程的周末。 一路上，他拍了很多照片：路边的老房子、田里的稻草堆，还有一只在树荫下睡觉的猫。 你问他为什么突然喜欢拍这些。 “平时到处跑，总觉得每个地方都待不够久。”他看了看相机里的照片，“今天不用赶下一站，挺好的。” | J16: 不是每一次出发，都需要一个目的地。 | K16: B组｜绿色工厂建设CG | L16: A10_祁主管_没有目的地的周末.png | M16: 是 | N16: 图片暂未制作；完成后放入 cg/images/，文件名与本行一致。
A17: B01 | B17: 绿色建设 | E17: 0 | F17: 灯亮起来了 | G17: 完成车间照明节能改造。 | H17: 改造后的车间内部，新照明设备均匀照亮工作区域，员工正在正常作业。厂长站在车间通道上观察。 | I17: 车间的照明改造终于完成了。 你沿着生产线走了一圈，发现原先有些昏暗的角落现在也能看清了。几位员工正在新灯下检查产品，似乎还不太习惯这样的变化。 “比以前亮堂多了。”有人抬头看了看灯，又继续手里的工作。 | J17: 改变有时候很简单，不过是让灯亮得更合适一些。 | L17: B01_灯亮起来了.png | M17: 是 | N17: 图片暂未制作；完成后放入 cg/images/，文件名与本行一致。
A18: B02 | B18: 绿色建设 | E18: 0 | F18: 第一次读懂曲线 | G18: 建立能源分项计量和监测系统，并完成首轮有效数据分析。 | H18: 办公室内，电脑显示着不同车间的用能曲线。厂长和陈工站在屏幕前，桌边放着手写记录和旧数据表。 | I18: 新的能源监测系统运行了一段时间，终于积累了足够的数据。 屏幕上的曲线有高有低，有些符合预期，也有几处让人摸不着头脑。 陈工把过去的记录摊在桌上，开始逐一比对。 你第一次感觉到，那些过去只能从电费账单上看到的消耗，终于有了更清楚的模样。 | J18: 看见问题，往往是改变问题的第一步。 | L18: B02_第一次读懂曲线.png | M18: 是 | N18: 图片暂未制作；完成后放入 cg/images/，文件名与本行一致。
A19: B03 | B19: 绿色建设 | E19: 0 | F19: 水的回程 | G19: 完成符合工厂工艺要求的生产用水循环利用项目。 | H19: 设备间里，循环水管道、储水设施和水处理设备整齐排列。维护人员正在查看仪表，厂长站在一旁。 | I19: 新的循环用水设施正式投入运行了。 你跟着工作人员走过设备间，听对方讲解水经过处理后，如何重新回到适用的生产环节。 那些过去看不见的用水过程，如今有了一条条可以追踪的管道和记录。 走出设备间时，你发现地上还留着安装设备时画下的标线。 | J19: 有些水的旅程，并不需要在使用一次后就结束。 | L19: B03_水的回程.png | M19: 是 | N19: 图片暂未制作；完成后放入 cg/images/，文件名与本行一致。
A20: B04 | B20: 绿色建设 | E20: 0 | F20: 屋顶上的阳光 | G20: 屋顶光伏项目完成并正常投入运行。 | H20: 从安全的厂区高处望去，阳光落在厂房屋顶排列整齐的光伏组件上。远处仍是普通的工业园区。 | I20: 屋顶光伏系统通过验收，开始正式运行。 你站在可以俯瞰厂房的位置，看着阳光落在一排排深蓝色组件上。厂房里依旧传来熟悉的生产声音，一切似乎和平时没什么不同。 只是从今天起，这些过去只能遮风挡雨的屋顶，也开始承担新的工作了。 | J20: 同样一片阳光，有了新的用处。 | L20: B04_屋顶上的阳光.png | M20: 是 | N20: 图片暂未制作；完成后放入 cg/images/，文件名与本行一致。
A21: B05 | B21: 绿色建设 | E21: 0 | F21: 腾出来的地方 | G21: 完成厂区空间优化及物料、废弃物分类周转设施改造。 | H21: 整理后的仓储周转区域，货架和物料摆放有序，不同类别的物料及废弃物有清晰标识，原先拥挤的通道恢复宽敞。 | I21: 仓储与物料周转区域的改造终于结束了。 你沿着新规划的通道走过去，发现原来堆满杂物的一角，现在已经可以顺畅通行。 仓库负责人拿着新旧两张平面图比划了半天，最后指着其中一处笑了笑。 “早知道可以这样安排，当初就不用绕那么远了。” | J21: 未必需要更多地方，有时候只是需要重新安排。 | L21: B05_腾出来的地方.png | M21: 是 | N21: 图片暂未制作；完成后放入 cg/images/，文件名与本行一致。
A22: B06 | B22: 绿色建设 | E22: 0 | F22: 产品的另一张图纸 | G22: 完成一项经过验证、不降低必要性能与质量要求的产品绿色设计改进。 | H22: 研发办公室里，两版产品结构图并排放在工作台上，旁边是新旧样品和测试记录。厂长与研发人员正在查看细节。 | I22: 新版产品完成了最后一轮验证。 它看起来和之前的产品没有太大不同，但部分材料、结构和制造方式已经悄悄发生了变化。 研发人员把新旧两份图纸摊开，指给你看那些调整过的细节。 你意识到，绿色改造不一定只发生在生产线上，有时也从一张图纸开始。 | J22: 让产品变得更好，也可以从重新设计它开始。 | L22: B06_产品的另一张图纸.png | M22: 是 | N22: 图片暂未制作；完成后放入 cg/images/，文件名与本行一致。
A23: B07 | B23: 绿色建设 | E23: 0 | F23: 从高处看这座工厂 | G23: 工厂在能源、资源、生产、产品和厂区管理等方面达到较高的综合绿色发展水平。 | H23: 从高处俯瞰已经历多年改造的工厂。可以辨认出不同阶段建设的设施、更新后的厂房、清晰的物流通道，以及仍在正常运转的生产线。 | I23: 今天，你有机会从一个平时很少经过的角度俯瞰整座工厂。 新的设备、重新规划的厂区、改造过的屋顶，还有那些已经习以为常的变化，都安静地出现在眼前。 你试着回忆自己刚来时这里的样子，发现有些细节已经记不太清了。 这座工厂仍然需要解决新的问题，但它确实和从前不一样了。 | J23: 改变不是一夜之间发生的，却能在某一天被清楚地看见。 | K23: C组｜生产经营CG | L23: B07_从高处看这座工厂.png | M23: 是 | N23: 图片暂未制作；完成后放入 cg/images/，文件名与本行一致。
A24: C01 | B24: 生产经营 | E24: 0 | F24: 第一份计划 | G24: 玩家首次确认2030年的经营计划。 | H24: 厂长办公室，桌上摊着年度经营计划、几份资料和一支签字笔。厂长坐在办公桌前，窗外是正在运转的工厂。 | I24: 你终于完成了上任后的第一份年度经营计划。 纸上写着今年准备做的事情，有些已经考虑得很清楚，有些还需要走一步看一步。 你又检查了一遍，确认没有遗漏，才把文件放到桌面最显眼的位置。 明天，这些写在纸上的计划，就要一点点变成现实了。 | J24: 十年的经营，从这张纸开始。 | L24: C01_第一份计划.png | M24: 是 | N24: 图片暂未制作；完成后放入 cg/images/，文件名与本行一致。
A25: C02 | B25: 生产经营 | E25: 0 | F25: 第一年的最后一天 | G25: 玩家完成2030年全部12个月的经营，首次进入年度结束结算。 | H25: 冬日傍晚的厂长办公室，夕阳落在办公桌上，桌边放着2030年的日历。厂长站在窗边，看着仍在运转的工厂。 | I25: 这一年的最后一个工作月终于结束了。 你翻看着年初制定的计划，有些事情顺利完成，有些比想象中困难，还有一些不得不留到明年。 窗外，工厂依旧和往常一样忙碌。 你把旧日历合上，忽然发现，自己已经在这里当了一整年的厂长。 | J25: 原来一年的时间，真的可以发生这么多事。 | L25: C02_第一年的最后一天.png | M25: 是 | N25: 图片暂未制作；完成后放入 cg/images/，文件名与本行一致。
A26: C03 | B26: 生产经营 | E26: 0 | F26: 报表上的红字 | G26: 首次出现年度经营亏损。 | H26: 夜晚的厂长办公室，办公桌上摊着年度经营报表，几项数字被红笔圈了起来。厂长独自坐在桌前，神情凝重。 | I26: 今年的经营结果并不理想。 你重新看了一遍报表，确认自己没有看错那些数字。收入、成本、投入，每一项都有来由，但放在一起，结果还是让人有些难以接受。 办公室安静了很久。 最后，你拿起笔，在新的一页纸上写下明年需要重新考虑的事情。 | J26: 不是每一年的努力，都会换来满意的结果。 | L26: C03_报表上的红字.png | M26: 是 | N26: 图片暂未制作；完成后放入 cg/images/，文件名与本行一致。
A27: C04 | B27: 生产经营 | E27: 0 | F27: 还剩多少钱 | G27: 可用资金首次进入预设的资金紧张区间。 | H27: 午后的办公室，厂长拿着资金情况表，桌边放着计算器和几份尚待安排的年度计划资料。窗外阳光很好，室内却显得格外安静。 | I27: 你看着最新的可用资金数字，开始重新盘算接下来的安排。 原本想做的事情还有不少，但钱显然不能同时花在所有地方。 你把计划翻到第一页，又从头看了一遍。 有些决定并不是不想做，只是眼下还需要再等等。 | J27: 当钱不够用的时候，每一种选择都变得具体起来。 | L27: C04_还剩多少钱.png | M27: 是 | N27: 图片暂未制作；完成后放入 cg/images/，文件名与本行一致。
A28: C05 | B28: 生产经营 | E28: 0 | F28: 今天先到这里 | G28: 厂长压力首次达到预设的较高水平。 | H28: 深夜的厂长办公室，台灯照着桌上的资料，窗外厂区大部分区域已经熄灯。厂长靠在椅背上，揉着眉心，桌上放着一杯已经凉掉的水。 | I28: 你发现自己已经盯着同一页文件看了很久。 这一阵子要考虑的事情实在太多，连平时很容易做出的决定，现在也要反复想上好几遍。 你合上文件，伸手关掉台灯。 剩下的事，明天再说吧。 | J28: 厂长也不是一台可以一直运转的机器。 | L28: C05_今天先到这里.png | M28: 是 | N28: 图片暂未制作；完成后放入 cg/images/，文件名与本行一致。
A29: C06 | B29: 生产经营 | E29: 0 | F29: 终于转正的数字 | G29: 上一年度经营亏损，本年度经营重新实现盈利。 | H29: 明亮的办公室，厂长坐在桌前查看年度经营报表，阳光透过窗户照进来。报表上的经营结果已经由负转正。 | I29: 你看到今年的经营结果时，忍不住又核对了一遍。 那些曾经让人头疼的数字，终于重新回到了正数。 这并不意味着所有问题都解决了。下一年依旧有很多需要考虑的事情，但至少此前做过的调整，有了一份看得见的结果。 你把报表放回文件夹，心情比昨天轻松了不少。 | J29: 有些好消息，需要等很久才能等到。 | L29: C06_终于转正的数字.png | M29: 是 | N29: 图片暂未制作；完成后放入 cg/images/，文件名与本行一致。
A30: C07 | B30: 生产经营 | E30: 0 | F30: 平稳的三年 | G30: 工厂连续三个完整经营年度实现盈利，首次达成时触发。 | H30: 厂长办公室的桌面上，三份不同年份的年度经营总结依次摆放。窗外阳光明亮，厂长正在整理文件，神情平静。 | I30: 整理文件时，你把最近三年的经营总结放在了一起。 这三年里，并不是每个月都顺利。成本有过波动，计划也调整过许多次。 但至少到每年结束时，工厂都交出了一份盈利的成绩单。 你把三份文件整齐地放进柜子里，忽然觉得，能够一直稳稳地经营下去，也是一件不容易的事。 | J30: 比起偶尔的一次成功，平稳地走下去也需要本事。 | L30: C07_平稳的三年.png | M30: 是 | N30: 图片暂未制作；完成后放入 cg/images/，文件名与本行一致。
A31: C08 | B31: 生产经营 | E31: 0 | F31: 已经五年了 | G31: 完成2034年12月的经营，正式度过前五个经营年度。 | H31: 与《上任第一天》相近的办公室构图。厂长站在窗前，办公桌上放着2030年和2034年的文件，窗外是经营五年后的工厂。 | I31: 今天整理旧文件时，你翻出了2030年刚上任时制定的第一份年度计划。 那时你刚坐进这间办公室，对许多事情还没有把握。 如今五年过去，有些当年的计划已经完成，有些改变了方向，还有些问题仍然需要继续面对。 你望向窗外，试着回忆自己第一次走进这间办公室时的心情。 五年好像很长，又好像只是一转眼。 | J31: 走到一半时，才发现自己已经走了很远。 | K31: 2040年结局CG | L31: C08_已经五年了.png | M31: 是 | N31: 图片暂未制作；完成后放入 cg/images/，文件名与本行一致。
A32: E01 | B32: 2040结局 | E32: 0 | F32: 第十年的春天 | G32: 经营表现优秀，绿色表现优秀。 | H32: 2040年春天，厂长站在办公室窗前。窗外的厂区经过多年改造，仍然是一座普通的制造工厂，但比十年前更加整洁、完善。门卫室旁的花正在开放。 | I32: 2040年春天，厂门口的花又开了。 你翻看着过去十年的经营记录。工厂的利润比刚来时好了许多，能源、资源和生产方式也有了实实在在的改善。 这十年并不是每一步都走得顺利。有过犹豫，有过资金紧张，也有些项目比预想中花了更长时间。 但最终，那些当初一点点做出的决定，都在今天留下了痕迹。 窗外，工人们正陆续走进车间。一切都和平时一样。 你忽然想起，十年前第一次来到这里时，也是这样的一个早晨。 | J32: 十年后，花照常开放，而这座工厂已经有了新的模样。 | L32: E01_第十年的春天.png | M32: 是 | N32: 图片暂未制作；完成后放入 cg/images/，文件名与本行一致。
A33: E02 | B33: 2040结局 | E33: 0 | F33: 留下来的改变 | G33: 绿色表现优秀，但经营表现未达到优秀水平；未进入严重资金危机结局。 | H33: 厂长站在改造后的厂区，身边是这些年陆续更新的设备和设施。天气晴朗，但厂区并不繁华，整体仍显得朴素。 | I33: 十年过去，这座工厂没有成为集团里最赚钱的那一家。 一些年份的经营成绩还不错，另一些年份却过得很紧张。为了筹措资金，你不止一次重新调整过投资计划。 好在许多绿色改造最终还是完成了。 如今，工厂的能源利用效率、资源管理和生产条件都比从前有了明显改善。那些曾经需要反复解释的改造项目，也已经成了日常生产的一部分。 只是经营上的难题并没有全部解决。 你望着眼前的厂区，知道这十年的努力并没有白费，也知道接下来还有不少事情要做。 | J33: 有些投入还没有得到理想的回报，但改变已经留了下来。 | L33: E02_留下来的改变.png | M33: 是 | N33: 图片暂未制作；完成后放入 cg/images/，文件名与本行一致。
A34: E03 | B34: 2040结局 | E34: 0 | F34: 两张成绩单 | G34: 经营表现优秀，绿色表现中等。 | H34: 厂长办公室的桌面上，一边是经营报表，另一边是绿色工厂评价记录。窗外部分设备和建筑已经更新，仍有一些地方保留着过去的样子。 | I34: 2040年的经营报告令人满意。 利润增长了，账上的资金也更加充裕。至少从经营成绩来看，你把这座工厂管理得不错。 这些年，工厂也做过不少绿色改造。有的项目已经产生了效果，有的还没有达到最初的预期。 你把十年的经营报表和绿色绩效记录放在一起。 两份成绩单都有进步，只是进步的幅度并不一样。 你重新翻开了那份尚未完成的改造计划，在最后一页补上了今天的日期。 | J34: 把生意做好了，也开始改变工厂，只是故事还没有写完。 | L34: E03_两张成绩单.png | M34: 是 | N34: 图片暂未制作；完成后放入 cg/images/，文件名与本行一致。
A35: E04 | B35: 2040结局 | E35: 0 | F35: 漂亮的报表 | G35: 经营表现优秀，绿色表现较弱。 | H35: 桌上整齐摆放着十年的经营报表，窗外的工厂繁忙而略显老旧。角落里放着几份多年前的绿色改造方案。 | I35: 2040年的年度经营报告出来了。 利润不错，账上的资金也很充裕。从财务数字来看，你确实把这座工厂经营得很好。 只是当你翻到绿色绩效那一页时，才发现它与十年前相比并没有太大的变化。 这些年，你做过很多选择，也抓住了不少经营机会。至于那些节能、节水和生产改造项目，总有更紧急的事情排在前面。 如今的工厂仍然忙碌，设备每天照常运转。 你把两份报告收进同一个文件夹，心里却很清楚，它们讲述的是两种不太一样的十年。 | J35: 这是一份漂亮的成绩单，只是有些题目始终没有回答。 | L35: E04_漂亮的报表.png | M35: 是 | N35: 图片暂未制作；完成后放入 cg/images/，文件名与本行一致。
A36: E05 | B36: 2040结局 | E36: 0 | F36: 照常开门 | G36: 经营表现平稳，绿色表现中等。 | H36: 2040年一个普通的早晨。厂长站在办公室窗前，门卫室的灯刚刚熄灭，工人陆续进入厂区，车间准备开始新一天的生产。 | I36: 2040年，工厂照常开门。 过去十年，没有发生什么足以让人津津乐道的大事。 经营有起有伏，绿色改造也陆续做了一些。部分设备已经换过，几个困扰多年的问题终于得到改善，但还有不少事情没来得及完成。 你曾经期待过，这座工厂会不会在自己手里发生翻天覆地的变化。 现在回头看，变化好像并没有那么惊人。 不过，车间还在运转，熟悉的声音依旧从窗外传来。 你喝完杯子里最后一口水，拿起文件，准备开始今天的工作。 | J36: 大多数日子平平常常，十年就是这样一点点过来的。 | L36: E05_照常开门.png | M36: 是 | N36: 图片暂未制作；完成后放入 cg/images/，文件名与本行一致。
A37: E06 | B37: 2040结局 | E37: 0 | F37: 明年再说 | G37: 经营表现平稳，绿色表现较弱。 | H37: 厂长办公室内，几份不同年份的改造方案堆在文件柜里。窗外的厂房依旧有些老旧，工厂仍然正常生产。 | I37: 整理文件时，你翻出了一份2031年的绿色改造计划。 那年因为资金安排紧张，几个项目被推迟到了下一年。 第二年，又出现了其他更急迫的经营事项。 后来几年，这份计划被修改过很多次。有些内容已经不再适用，也有些直到今天仍然没有完成。 工厂的经营倒是一直维持着，虽然没有特别亮眼的成绩，但也还算过得去。 你看着那份旧文件，忽然发现，自己曾经说过很多次“明年再说”。 如今，已经是2040年了。 | J37: 明年总会到来，只是机会未必一直等在那里。 | L37: E06_明年再说.png | M37: 是 | N37: 图片暂未制作；完成后放入 cg/images/，文件名与本行一致。
A38: E07 | B38: 2040结局 | E38: 0 | F38: 还没到放弃的时候 | G38: 工厂经营困难，但尚未达到严重资金危机条件；绿色表现未达到优秀。 | H38: 阴天的厂长办公室，桌上散放着报表和计划，厂长坐在办公桌前重新整理文件。窗外工厂仍在生产，但整体显得有些冷清。 | I38: 这十年的最后一份经营报表，仍然不太理想。 过去几年，你已经多次调整过经营计划。有些办法起了作用，有些却没能改变结果。 工厂也进行过一些改造，只是受到经营状况和资金的限制，许多计划始终没能推进下去。 你看着桌上的文件，突然有些怀念刚上任的时候。 那时你觉得，只要把计划安排得足够仔细，总能找到一条合适的路。 十年过去，你终于明白，有些问题不是靠一份漂亮的计划就能解决的。 不过，至少今天，工厂的大门仍然开着。 | J38: 没有走到想去的地方，但你还没有停下来。 | L38: E07_还没到放弃的时候.png | M38: 是 | N38: 图片暂未制作；完成后放入 cg/images/，文件名与本行一致。
A39: E08 | B39: 2040结局 | E39: 0 | F39: 最后一份通知 | G39: 严重资金危机，工厂已无法维持既定经营方式。优先于其他结局。 | H39: 冬日的厂长办公室。办公桌上放着一份经营调整通知和2030年的任命书，文件柜有些空了。厂长站在桌前整理物品，窗外是安静的工厂。 | I39: 集团的通知终于下来了。 长期的亏损和资金困难，让这座工厂已经无法继续按照原来的方式经营。经过讨论，集团决定对厂区业务和资产进行重新整合。 通知上只有短短几段话，但接下来需要处理的事情还有很多。 你开始整理办公室里的文件。 十年经营记录、尚未完成的改造计划，还有一张不知道什么时候夹进文件夹里的旧照片。 最后，你翻出了2030年的任命书。 那时你32岁，第一次来到这里。你还记得自己走进办公室时，曾经认真打量过窗外的每一栋厂房。 你把任命书折好，放进随身的文件夹。 离开之前，你又看了一眼窗外。 | J39: 十年没有按照预想的方式结束，但那些走过的日子都是真的。 | L39: E08_最后一份通知.png | M39: 是 | N39: 图片暂未制作；完成后放入 cg/images/，文件名与本行一致。
A40: E09 | B40: 2040结局 | E40: 0 | F40: 那份材料 | G40: 玩家在2030—2039年的经营过程中，至少选择并执行过一次伪造数据截图或贿赂评审专家的行为，且在本轮游戏中被查实（90%概率）。 | H40: 阴沉的午后，厂长独自坐在办公室里。桌上摊着一份调查处理通知，旁边是几年前的绿色工厂评价材料。窗外仍然能看见正在运转的工厂，房间里却格外安静。 | I40: 2040年，你收到了一份有关工厂绿色评价违规问题的调查处理通知。 几年前的那次选择，终究还是被查了出来。 当时，为了让评价顺利通过，你曾试图在材料或评审环节走一条捷径。那时候，你以为只要过了眼前这一关，事情就算结束了。 如今，调查人员重新核对了相关记录。问题被确认，原有评价结果受到影响，工厂也需要承担相应的整改和责任追究。 你翻出当年的申报文件。那些曾经让人紧张的指标、来回修改的表格，以及最后作出的那个决定，都还清清楚楚地留在里面。 窗外，工厂依旧照常运转。 只是有些东西，已经不能再像从前一样了。 | J40: 走捷径省下的那段路，后来都要重新走一遍。 | K40: 根据玩家具体选择，替换正文中的一句话： - 伪造截图： “当年，为了让申报材料看起来符合要求，你提交了一份经过修改的数据截图。” - 贿赂专家： “当年，为了让评价顺利通过，你试图通过不正当利益影响评审专家的判断。” - 两种行为均有： “当年，那份经过修改的数据截图，以及评审期间的不正当安排，如今都成了需要重新核查的问题。” | L40: E09_那份材料.png | M40: 是 | N40: 图片暂未制作；完成后放入 cg/images/，文件名与本行一致。

Sheet 结算说明
A2: 结算说明
A3: 此页用于看清年值、月值和项目付款的区别；不直接作为游戏输入。
A5: 检查项 | B5: 年值/总价 | C5: 换算公式 | D5: 月值 | E5: 结果说明 | F5: 口径
A6: 每招聘1名工程师人工成本 | B6: 38 | C6: 年值÷12 | D6: =B6/12 | E6: 3.17 万/月，不是 38 万/月 | F6: 原 HTML：每年增加38万人工成本
A7: 6个月项目 | B7: 100 | C7: 总价÷6个月 | D7: =B7/6 | E7: 示例值可改；仅演示分6期均摊 | F7: 项目卡直接填写6个月
A8: 12个月项目 | B8: 850 | C8: 总价÷12个月 | D8: =B8/12 | E8: 850万扩建产线初始每月约70.83万 | F8: 项目卡直接填写12个月
A9: 绿色信贷还本付息 | B9: 62 | C9: 年值÷12 | D9: =B9/12 | E9: 5.17 万/月 | F9: 8年每年还本付息62万
A10: 绿色信贷本金减少 | B10: 400 | C10: 本金÷(8年×12个月) | D10: =B10/(8*12) | E10: 4.17 万/月 | F10: 贷款余额展示本金；月度还本付息含本金与利息
A12: 月度经营现金流字段 | B12: 年度计算基础 | C12: 月度处理 | D12: 是否包含项目施工款
A13: 经营收入 | B13: 销量×渠道价格 | C13: ÷12 | D13: 否
A14: 材料成本 | B14: 销量×单位材料成本 | C14: ÷12 | D14: 否
A15: 能源成本 | B15: 用电、用气、绿电、绿证等 | C15: ÷12 | D15: 否
A16: 人工成本 | B16: 固定人工+变动人工+招聘人工 | C16: ÷12 | D16: 否
A17: 维护成本 | B17: 基础维护费 | C17: ÷12 | D17: 否
A18: 固定费用 | B18: 固定经营费+出口附加费+ISO维持费 | C18: ÷12 | D18: 否
A19: 融资费用 | B19: 负现金利息+绿色信贷还本付息 | C19: ÷12 | D19: 否
A20: 所得税 | B20: 正的税前利润×税率 | C20: ÷12 | D20: 否
A21: 上缴集团 | B21: 正的净利润×上缴比例 | C21: ÷12 | D21: 否
A22: 项目施工支出 | B22: 项目总成本 | C22: ÷实际施工月数 | D22: 是；单列扣现金
